Workbook
Name Inflation: '1-P&L Modified'!$B$3
Name Preliminary_Analysis: WELCOME!$B$27
Name VAT: '1-F&B'!$B$5

Sheet WELCOME
B2: HOTEL ASSET MANAGEMENT – BOSC 5 - Team 5
B3: Radisson Blue - Wiesbaden
B5: HONOUR CODE As an EHL Hospitality Business School student, I uphold and defend academic integrity, academic rigor, and academic liberty as core values of higher learning. I attest, on my word of honor, that work submitted in my name is my own work and that any ideas or materials used in support of this work which is not originally my own, including AI-generated or assisted text, are cited and referenced accordingly in APA format.
B11: Students Team
B12: Team 5
F13: RADISSON BLU SCHWARZER BOCK HOTEL
B14: NAME | C14: LAST NAME | D14: STUDENT ID
B15: Matteo | C15: DELFINI | D15: 693625229
B16: Sophie | C16: LUSCHER | D16: 683 600 659
B17: Luca | C17: STETTLER | D17: 658937790
B18: Titouan | C18: GUYOT | D18: 704826420
B19: Margot | C19: CONCEPRIO | D19: 646947764
B20: Emilie | C20: KUSTER | D20: 651927774
B21: Daniella | C21: HALLEN | D21: 608900893
B22: Alexandre | C22: CARBONI | D22: 557 689 718
B24: Table of Content
B26: Sheet | D26: Description
B27: Preliminary Analysis | D27: Market and asset diagnosis (STR trends, comp set benchmarking, historical KPIs, key underperformance drivers, positioning).
B28: Assumptions | D28: Central assumptions hub (ADR/Occ growth, inflation, fees, RR, discount rate, cap rate, sales costs, disruption).
B29: P&L Normal Situation | D29: 10-year forecast without CAPEX (baseline) + baseline market value.
B30: 1-P&L Modified | D30: 10-year forecast with CAPEX / repositioning (pro forma) + market value with CAPEX.
B31: 1-F&B Details | D31: Detailed F&B build-up (covers, average check, seat occupancy, brasserie/café concepts) + benchmarks.
B32: 1-Capex | D32: Detailed CAPEX budget by area and category (FF&E / soft goods / construction + fees/contingency).
B33: 1-Capex Planning | D33: CAPEX phasing (monthly/weekly), room cluster sequencing, and disruption/OOO assumptions.
B34: 1-Incremental Cash Flow | D34: Incremental cash flows (With–Without), total and by department, with KPIs (NPV/IRR/payback/yield).
B35: 1-Sensitivity | D35: Scenario and sensitivity tests (±ADR, ±Occ) with impact on GOP/EBITDA and NPV/IRR.
B36: Appendix 1-STR Trend | D36: STR comp-set trends (Occ/ADR/RevPAR + MPI/ARI/RGI) supporting demand, pricing, and baseline gap.
B37: Appendix 2- Graphics | D37: Monthly Occ% and ADR seasonality (Frankfurt Rhine-Main Upper Upscale) supporting seasonality and phasing assumptions.

Sheet PRELIMINARY ANALYSIS
A1: Preliminary Analysis
B4: 1. COMPSET
B5: *Based on the STR Report Frankfurt Rhine-Main - Upper upscale
B6: HOTEL NAME | C6: CLASS | D6: ADR | E6: # ROOMS | F6: REGION | G6: SPA | H6: RESTAURANTS | I6: ROOM SERVICE | J6: POOL | K6: MEETING ROOMS | L6: WEBSITE
B7: Radisson Blue | C7: Upper Upscale | D7: 143.32 | E7: 142 | F7: Weisbaden / urban | G7: yes | H7: yes | I7: no | J7: yes | K7: yes | L7: LINK
B8: Hyatt Regency Mainz | C8: Upper Upscale | D8: 150.21 | E8: 268 | F8: Mainz / urban | G8: yes | H8: yes | I8: yes | J8: yes | K8: yes | L8: LINK
B9: Dorint Pallas Wiesbaden | C9: Upscale | D9: 114.46 | E9: 297 | F9: Weisbaden / urban | G9: yes | H9: yes , 2 | I9: yes | J9: no | K9: yes | L9: LINK
B10: Hotel Orianen | C10: Upper Upscale | D10: 150.21 | E10: 80 | F10: Weisbaden / urban | G10: no | H10: yes | I10: yes | J10: yes | K10: yes | L10: LINK
B11: Mercure Hotel Wiesbaden City | C11: Upper - Midscale | D11: 73.69 | E11: 235 | F11: Weisbaden / urban | G11: yes | H11: yes | I11: yes | J11: yes | K11: yes | L11: LINK
B12: Hotel Nassauer Hof Wiesbaden | C12: Luxury | D12: 241.82 | E12: 159 | F12: Weisbaden / suburban | G12: yes | H12: yes, 2 | I12: yes | J12: yes | K12: yes | L12: LINK
B13: The primary comp set was selected based on similar positioning (Upscale/Upper-Upscale), location within the Rhine-Main corporate area, and similar service level. Luxury and Upper-Midscale properties are used solely for positioning analysis.
B16: 2. ADR
B18: HISTORICAL ADR GROWTH RATE | D18: DEPRECIATION RATE | F18: HISTORICAL INFLATION | H18: EXPECTED FUTURE INFLATION | J18: ADR GROWTH RATE
B19: *Based on the STR Report Frankfurt Rhine-Main - Upper upscale | D19: Source: Real Estate class, -1% because building is old | F19: https://www.rateinflation.com/consumer-price-index/germany-historical-cpi/?utm | H19: https://www.theglobaleconomy.com/Germany/inflation_outlook_imf/?utm_source
B20: Year | C20: Frankfurt Rhine-Main Upper Upscale | D20: Real Depreciation | E20: =-1% -> -0.01 | F20: Year | G20: CPI | H20: Year | I20: Inflation rate | J20: Historical ADR Growth rate | K20: =_xlfn.RRI(B32-B21,C21,C32) -> 0.01440779
B21: 2013 | C21: ='APPENDIX 1-STR Trend '!P27 -> 131.98999 | F21: 2024 | G21: 119.3 | H21: 2025 | I21: 0.0176 | J21: Real depreciation | K21: =-1% -> -0.01
B22: 2014 | C22: ='APPENDIX 1-STR Trend '!P28 -> 129.9366 | F22: 2023 | G22: 116.7 | H22: 2026 | I22: 0.0199 | J22: Historical inflation | K22: =-_xlfn.RRI(F21-F32,G32,G21) -> -0.017569355
B23: 2015 | C23: ='APPENDIX 1-STR Trend '!P29 -> 135.83353 | F23: 2022 | G23: 110.2 | H23: 2027 | I23: 0.0211 | J23: Expected future inflation | K23: =AVERAGE(I21:I31) -> 0.021181818
B24: 2016 | C24: ='APPENDIX 1-STR Trend '!P30 -> 133.92902 | F24: 2021 | G24: 109.1 | H24: 2028 | I24: 0.0218
B25: 2017 | C25: ='APPENDIX 1-STR Trend '!P31 -> 139.26257 | F25: 2020 | G25: 105.8 | H25: 2029 | I25: 0.0218 | J25: ADR GROWTH RATE | K25: =SUM(K20:K23) -> 0.0080202527
B26: 2018 | C26: ='APPENDIX 1-STR Trend '!P32 -> 139.82464 | F26: 2019 | G26: 105.3 | H26: 2030 | I26: 0.0218
B27: 2019 | C27: ='APPENDIX 1-STR Trend '!P33 -> 140.51502 | F27: 2018 | G27: 103.8 | H27: 2031 | I27: 0.0218
B28: 2020 | C28: ='APPENDIX 1-STR Trend '!P34 -> 126.00649 | F28: 2017 | G28: 102 | H28: 2032 | I28: 0.0218
B29: 2021 | C29: ='APPENDIX 1-STR Trend '!P35 -> 116.60951 | F29: 2016 | G29: 100.5 | H29: 2033 | I29: 0.0218
B30: 2022 | C30: ='APPENDIX 1-STR Trend '!P36 -> 149.95474 | F30: 2015 | G30: 100 | H30: 2034 | I30: 0.0218
B31: 2023 | C31: ='APPENDIX 1-STR Trend '!P37 -> 154.01433 | F31: 2014 | G31: 99.4 | H31: 2035 | I31: 0.0218
B32: 2024 | C32: ='APPENDIX 1-STR Trend '!P38 -> 154.48251 | F32: 2013 | G32: 98.5
B35: 3. OCCUPANCY DISCOUNT RATE, CAP RATE
B37: OCCUPANCY | E37: DISCOUNT RATE
B38: *Based on the STR Report Frankfurt Rhine-Main - Upper upscale | E38: Riskfree* | F38: 0.0285
B39: Years | C39: Occupancy (%) | E39: + Sector Premium | F39: =6.3%-5.2% -> 0.011
B40: ='APPENDIX 1-STR Trend '!B9 -> 2013 | C40: ='APPENDIX 1-STR Trend '!P9 -> 65.663899 | E40: + City/submarket Premium** | F40: 0.01
B41: ='APPENDIX 1-STR Trend '!B10 -> 2014 | C41: ='APPENDIX 1-STR Trend '!P10 -> 68.63277 | E41: + Property Premium*** | F41: 0.02
B42: ='APPENDIX 1-STR Trend '!B11 -> 2015 | C42: ='APPENDIX 1-STR Trend '!P11 -> 70.237815 | E42: = Discount Rate | F42: =SUM(F38:F41) -> 0.0695
B43: ='APPENDIX 1-STR Trend '!B12 -> 2016 | C43: ='APPENDIX 1-STR Trend '!P12 -> 70.923591 | E43: * https://tradingeconomics.com/germany/government-bond-yield | H43: Allemagne : 6.3 HMA | I43: Allemagne : 5.2 Prime Lease
B44: ='APPENDIX 1-STR Trend '!B13 -> 2017 | C44: ='APPENDIX 1-STR Trend '!P13 -> 72.891453 | E44: **City / Submarket Premium 1% because Wiesbaden is not a prime location.
B45: ='APPENDIX 1-STR Trend '!B14 -> 2018 | C45: ='APPENDIX 1-STR Trend '!P14 -> 72.390969 | E45: ***Property Premium 2% because it's an old building 1486 year of construction
B46: ='APPENDIX 1-STR Trend '!B15 -> 2019 | C46: ='APPENDIX 1-STR Trend '!P15 -> 69.854822
B47: ='APPENDIX 1-STR Trend '!B16 -> 2020 | C47: ='APPENDIX 1-STR Trend '!P16 -> 30.359108
B48: ='APPENDIX 1-STR Trend '!B17 -> 2021 | C48: ='APPENDIX 1-STR Trend '!P17 -> 32.094927
B49: ='APPENDIX 1-STR Trend '!B18 -> 2022 | C49: ='APPENDIX 1-STR Trend '!P18 -> 54.043043
B50: ='APPENDIX 1-STR Trend '!B19 -> 2023 | C50: ='APPENDIX 1-STR Trend '!P19 -> 61.116706 | E50: Cap Rate | F50: =F42-K25 -> 0.061479747
B51: ='APPENDIX 1-STR Trend '!B20 -> 2024 | C51: ='APPENDIX 1-STR Trend '!P20 -> 67.026017
B52: Occupancy Growth Rate | C52: =_xlfn.RRI(B51-B40,C40,C51) -> 0.0018682486

Sheet ASSUMPTIONS
A3: P&L ASSUMPTIONS
A5: P&L | B5: METRIC | C5: STR REPORT 2023 | D5: 2024 | E5: Adjustment | F5: NEW | G5: EXPLINATION
A6: ADR | C6: ='APPENDIX 1-STR Trend '!I45 -> 179.03 | D6: =' P&L Normal Situation'!X12 -> 119.69 | E6: See comment | G6: Increase thanks to repositionning and white label contract (see detailes on P&L Modified) | I6: Base management fees | J6: =AVERAGE(2.77%,3.08%) -> 0.02925
A7: Occupancy % | C7: ='APPENDIX 1-STR Trend '!I44 -> 0.618 | D7: =' P&L Normal Situation'!X11 -> 0.743 | E7: See comment | G7: Decrease due to renovation than Increase due to repositionning + branding (see detailes on P&L Modified)
A8: Operating Revenue
A9: Rooms | B9: % of TREV | C9: ='APPENDIX 1-STR Trend '!E54/100 -> 0.713 | D9: =' P&L Normal Situation'!Y18 -> 0.73457266 | E9: See comment | F9: - | G9: Depending on ADR et Occ
A10: Food and Beverage | B10: % of TREV | C10: =SUM('APPENDIX 1-STR Trend '!E55:E57)/100 -> 0.245 | D10: =' P&L Normal Situation'!Y19 -> 0.17939272 | E10: See comment | F10: - | G10: Increase: New F&B outlets,(see detailes on F&B sheet)
A11: Spa | B11: % of TREV | C11: - | D11: =' P&L Normal Situation'!Z20 -> 8.013814 | E11: 0.15 | F11: =D11*(1+E11) -> 9.2158862 | G11: Adjustment for repositionning (bleisure)
A12: Other | B12: % of TREV | C12: ='APPENDIX 1-STR Trend '!E58/100 -> 0.015 | D12: =' P&L Normal Situation'!Z21 -> 6.0079975 | E12: 0.15 | F12: =D12*(1+E12) -> 6.9091971 | G12: Higer quality meeting rooms allowing higher prices
A13: Departemental Expenses
A14: Rooms | B14: % of Dep. Rev. | C14: ='APPENDIX 1-STR Trend '!E63/100 -> 0.29 | D14: =' P&L Normal Situation'!Y24 -> 0.34198572 | E14: -0.035 | F14: =SUM(D14:E14) -> 0.30698572 | G14: Decrease: Cost per room sold remain stable and better cost control thanks to franchise standards
A15: Food and Beverage | B15: % of Dep. Rev. | C15: ='APPENDIX 1-STR Trend '!E64/100 -> 0.818 | D15: =' P&L Normal Situation'!Y25 -> 1.003543 | E15: See comment | F15: - | G15: Decrease: New F&B outlets (see F&B sheet)
A16: Spa | B16: % of Dep. Rev. | C16: - | D16: =' P&L Normal Situation'!Y26 -> 0.81882665 | E16: -0.17 | F16: =SUM(D16:E16) -> 0.64882665 | G16: Decrease : thanks to renovation
A17: Other | B17: % of Dep. Rev. | C17: ='APPENDIX 1-STR Trend '!E65/100 -> 0.37 | D17: =' P&L Normal Situation'!Y27 -> 0.5387931 | E17: -0.17 | F17: =SUM(D17:E17) -> 0.3687931 | G17: Decrease : thanks to renovation
A18: Undistributed Operating Expenses
A19: Aministrative and General | B19: PAR | C19: ='APPENDIX 1-STR Trend '!G75 -> 5079.69 | D19: ='1-P&L Modified'!AA30 -> 2676.0563 | E19: =-10% -> -0.1 | F19: =D19*(1+E19) -> 2408.4507 | G19: Decrease: better efficency thanks to Accor
A20: Sales And Marketing | B20: PAR | C20: ='APPENDIX 1-STR Trend '!G77 -> 3685.67 | D20: ='1-P&L Modified'!AA31 -> 1619.7183 | E20: 0 | F20: =D20*(1+E20) -> 1619.7183 | G20: New outlets open to external need new promotion (Brasserie+café), less marketing fees thanks to franchise | I20: https://hvs.com/PaidPublications/Samples/Excerpts_HVS%20Guide%20to%20Hotel%20Management%20Contracts%202020.pdf
A21: Franchise Fees (royalty, loyalty, and marketing) | B21: % of room Rev | D21: ='1-P&L Modified'!AA32 -> 0 | E21: =5%+2% -> 0.07 | F21: =SUM(D21:E21) -> 0.07 | G21: New Franchise contract 5% Royaltees + 2% marketing contribution | I21: https://www.hvs.com/article/9912-a-new-approach-to-hotel-management-fees
A22: Heat light and Power | B22: PAR | C22: ='APPENDIX 1-STR Trend '!G79 -> 3418.13 | D22: ='1-P&L Modified'!AA33 -> 2394.3662 | E22: -0.05 | F22: =D22*(1+E22) -> 2274.6479 | G22: Decrease: thanks to ESG renovations (LED lights)
A23: Repairs and Maintenance | B23: PAR | C23: ='APPENDIX 1-STR Trend '!G80 -> 2947.86 | D23: ='1-P&L Modified'!AA34 -> 2816.9014 | E23: 0.1 | F23: =D23*(1+E23) -> 3098.5915 | G23: Increase: due to new F&B outlets
A24: Management Fees | I24: RETAIL HAIRDRESSER & PHONE STORE | J24: €/SQM/MONTH | K24: SOURCE
A25: Base Management Fee | B25: % of TREV | C25: ='APPENDIX 1-STR Trend '!E84/100 -> 0.021 | D25: ='1-P&L Modified'!Y38 -> 0 | E25: 0.03 | F25: =D25+E25 -> 0.03 | G25: New white label management contract | J25: 36.74 | K25: https://www.ihk.de/wiesbaden/wirtschaftspolitik/region/gewerbeflaechen-und-mietpreise/mietpreisspiegel-1255370
A26: Incentive Management Fee | B26: % of (Gross operating profit) | C26: ='APPENDIX 1-STR Trend '!E85/100 -> 0.005 | D26: ='1-P&L Modified'!Y39 -> 0 | E26: 0.08 | F26: =D26+E26 -> 0.08 | G26: New white label management contract | J26: =4000/130.32 -> 30.693677 | K26: https://www.immobilienscout24.de/expose/160771843?referrer=HYBRID_VIEW_MAP&searchId=c63438fd-bbf2-3de9-afaf-3124b02ce239&searchUrl=%2Fde%2Fhessen%2Fwiesbaden%2Fgastronomie-mieten%3Fbbox%3Dc2hycEhzZWZxQH1mQj8-c3JFfGZCPw..&searchType=district#/
A27: Non-operating Income & Expenses | J27: =4000/115.09 -> 34.755409 | K27: https://www.immobilienscout24.de/expose/162096020?referrer=HYBRID_VIEW_MAP&searchId=c63438fd-bbf2-3de9-afaf-3124b02ce239&searchUrl=%2Fde%2Fhessen%2Fwiesbaden%2Fgastronomie-mieten%3Fbbox%3Dc2hycEhzZWZxQH1mQj8-c3JFfGZCPw..&searchType=district#/
A28: Non-Operating Income | B28: % tot. operating rev. | C28: -0.001 | J28: =1700/96 -> 17.708333 | K28: https://www.immobilienscout24.de/expose/162519246?referrer=HYBRID_VIEW_MAP_GROUPED&searchId=c63438fd-bbf2-3de9-afaf-3124b02ce239&searchUrl=%2Fde%2Fhessen%2Fwiesbaden%2Fgastronomie-mieten%3Fbbox%3Dc2hycEhzZWZxQH1mQj8-c3JFfGZCPw..&searchType=district#/
A29: Retail income | F29: =J34*90*12 -> 32740.017 | G29: Estimated rental price by benchmark (retail shops) | J29: =2400/193 -> 12.435233 | K29: https://www.immobilienscout24.de/expose/153822589?referrer=HYBRID_VIEW_MAP_GROUPED&searchId=c63438fd-bbf2-3de9-afaf-3124b02ce239&searchUrl=%2Fde%2Fhessen%2Fwiesbaden%2Fgastronomie-mieten%3Fbbox%3Dc2hycEhzZWZxQH1mQj8-c3JFfGZCPw..&searchType=district#/
A30: Rent | B30: PAR | C30: ='APPENDIX 1-STR Trend '!G90 -> 7467 | J30: =8100/290 -> 27.931034 | K30: https://www.immobilienscout24.de/expose/160736004?referrer=HYBRID_VIEW_MAP&searchId=a7cf4782-ca5a-3849-a6f4-7a39745c5e5e&searchUrl=%2Fde%2Fhessen%2Fwiesbaden%2Feinzelhandel-mieten%3Fbbox%3DcXdycEhhdWVxQH1mQj8-c3JFfGZCPw..&searchType=district#/
A31: Property Taxes & Insurance | B31: PAR | C31: ='APPENDIX 1-STR Trend '!G91+'APPENDIX 1-STR Trend '!G92 -> 366 | D31: ='1-P&L Modified'!AA48 -> 316.90141 | E31: 0.05 | F31: =D31*(1+E31) -> 332.74648 | G31: Increase: Due to new value with capex + outlets | J31: =3800/105 -> 36.190476 | K31: https://www.immobilienscout24.de/expose/157437826?referrer=HYBRID_VIEW_MAP&searchId=a7cf4782-ca5a-3849-a6f4-7a39745c5e5e&searchUrl=%2Fde%2Fhessen%2Fwiesbaden%2Feinzelhandel-mieten%3Fbbox%3Dc3ZzcEhnYmdxQF9zQD8-eWhCfnJAPw..&searchType=district#/
J32: =6000/145 -> 41.37931 | K32: https://www.immobilienscout24.de/expose/162664184?referrer=HYBRID_VIEW_MAP_GROUPED&searchId=a7cf4782-ca5a-3849-a6f4-7a39745c5e5e&searchUrl=%2Fde%2Fhessen%2Fwiesbaden%2Feinzelhandel-mieten%3Fbbox%3Dd2t0cEhhdmdxQF9ZPz99c0B_WD8.&searchType=district#/
J33: 35 | K33: https://www.immobilienscout24.de/expose/164275457?referrer=HYBRID_VIEW_MAP_GROUPED&searchId=a7cf4782-ca5a-3849-a6f4-7a39745c5e5e&searchUrl=%2Fde%2Fhessen%2Fwiesbaden%2Feinzelhandel-mieten%3Fbbox%3DX35zcEh5X2dxQF9zQD8-eWhCfnJAPw..&searchType=district#/
I34: Average | J34: =AVERAGE(J25:J33) -> 30.31483
A35: CAPEX ASSUMPTIONS
A37: CAPEX ADJUSMENT | B37: APPLY ON | C37: ADJUSMENT | D37: Source
A38: Architect fee | B38: Total N/A ajusted Capex | C38: 0.1 | D38: https://aron-studio.de/architect-costs-in-germany-a-comprehensive-guide/
A39: FF&E ajustement | B39: FF&E | C39: 0.15 | D39: https://www.hyhotelfurniture.com/blog/hotel-ff-e-costs.html | I39: LABOR ADJUSTMENT | J39: MEDIAN SALARY/YEAR | K39: SOURCE
A40: Contractor Markup | B40: Construction | C40: 0.15 | D40: https://switchhotelsolutions.com.au/hotel-renovation-budget-template-guide/ | I40: USA | J40: =45300*0.86 -> 38958 | K40: https://careers.usnews.com/best-jobs/construction-worker/salary
A41: Labor | B41: Total N/A ajusted Capex | C41: =J41/J40-1 -> 0.16879717 | I41: Germany | J41: =45534 -> 45534 | K41: https://www.salaryexpert.com/salary/job/construction-worker/germany?__cf_chl_tk=Eez7vyb9Bpvs49M77FDW2NqRe9mQJ9ZCfFsBeNN0ApA-1765468386-1.0.1.1-RSeoRcHPlRy50UhMkQrxzXbHBTbHebualtv_w0_N1LQ
A42: Contingency | B42: Total N/A ajusted Capex | C42: 0.1 | D42: HVS_Hotel Estimation Guide_2024
A43: Capex reserves check | B43: Total N/A ajusted Capex | C43: 0.06 | D43: https://www.costar.com/article/1366873980/capex-study-authors-4-reserves-not-enough
A44: Renovation time | D44: https://www.hyhotelfurniture.com/how-long-does-it-take-to-refurbish

Sheet  P&L Normal Situation
A1: P&L Normal Situation
A2: Hotel # rooms | B2: 142
A3: Expected future inflation | B3: ='PRELIMINARY ANALYSIS'!K23 -> 0.021181818
A4: ADR Growth Rate | B4: ='PRELIMINARY ANALYSIS'!K25 -> 0.0080202527
A5: Occupancy Growth Rate | B5: ='PRELIMINARY ANALYSIS'!C52 -> 0.0018682486
P6: COVID | AV6: Occupancy Stabilize form this year
A7: Year | B7: 2013 | D7: 2014 | F7: 2015 | H7: 2016 | J7: 2017 | L7: 2018 | N7: 2019 | P7: 2020 | R7: 2021 | T7: 2022 | V7: 2023 | X7: 2024 | AB7: 2025 | AF7: 2026 | AJ7: 2027 | AN7: 2028 | AR7: 2029 | AV7: 2030 | AZ7: 2031 | BD7: 2032 | BH7: 2033 | BL7: 2034 | BP7: 2035
A8: Days | B8: 365 | D8: 365 | F8: 365 | H8: 366 | J8: 365 | L8: 365 | N8: 365 | P8: 366 | R8: 365 | T8: 365 | V8: 365 | X8: 366 | AB8: 365 | AF8: 365 | AJ8: 365 | AN8: 366 | AR8: 365 | AV8: 365 | AZ8: 365 | BD8: 366 | BH8: 365 | BL8: 365 | BP8: 365
A9: Rooms Available | B9: =B8*$B$2 -> 51830 | D9: =D8*$B$2 -> 51830 | F9: =F8*$B$2 -> 51830 | H9: =H8*$B$2 -> 51972 | J9: =J8*$B$2 -> 51830 | L9: =L8*$B$2 -> 51830 | N9: =N8*$B$2 -> 51830 | P9: =P8*$B$2 -> 51972 | R9: =R8*$B$2 -> 51830 | T9: =T8*$B$2 -> 51830 | V9: =V8*$B$2 -> 51830 | X9: =X8*$B$2 -> 51972 | AB9: =AB8*$B$2 -> 51830 | AF9: =AF8*$B$2 -> 51830 | AJ9: =AJ8*$B$2 -> 51830 | AN9: =AN8*$B$2 -> 51972 | AR9: =AR8*$B$2 -> 51830 | AV9: =AV8*$B$2 -> 51830 | AZ9: =AZ8*$B$2 -> 51830 | BD9: =BD8*$B$2 -> 51972 | BH9: =BH8*$B$2 -> 51830 | BL9: =BL8*$B$2 -> 51830 | BP9: =BP8*$B$2 -> 51830
A10: Rooms Sold | B10: =B11*B9 -> 33406 | D10: =D11*D9 -> 28091.86 | F10: =F11*F9 -> 38561.52 | H10: =H11*H9 -> 40174.356 | J10: =J11*J9 -> 37576.75 | L10: =L11*L9 -> 38717.01 | N10: =N11*N9 -> 40220.08 | P10: =P11*P9 -> 11122.008 | R10: =R11*R9 -> 11765.41 | T10: =T11*T9 -> 23738.14 | V10: =V11*V9 -> 32963.88 | X10: =X11*X9 -> 38615.196 | AB10: =ROUNDDOWN(AB9*AB11,0) -> 38581 | AF10: =ROUNDDOWN(AF9*AF11,0) -> 38653 | AJ10: =ROUNDDOWN(AJ9*AJ11,0) -> 38725 | AN10: =ROUNDDOWN(AN9*AN11,0) -> 38904 | AR10: =ROUNDDOWN(AR9*AR11,0) -> 38870 | AV10: =ROUNDDOWN(AV9*AV11,0) -> 38943 | AZ10: =ROUNDDOWN(AZ9*AZ11,0) -> 38943 | BD10: =ROUNDDOWN(BD9*BD11,0) -> 39050 | BH10: =ROUNDDOWN(BH9*BH11,0) -> 38943 | BL10: =ROUNDDOWN(BL9*BL11,0) -> 38943 | BP10: =ROUNDDOWN(BP9*BP11,0) -> 38943
A11: Occupancy | B11: 0.64453019 | D11: 0.542 | F11: 0.744 | H11: 0.773 | J11: 0.725 | L11: 0.747 | N11: 0.776 | P11: 0.214 | R11: 0.227 | T11: 0.458 | V11: 0.636 | X11: 0.743 | AB11: =X11*(1+$B$5) -> 0.74438811 | AF11: =AB11*(1+$B$5) -> 0.74577881 | AJ11: =AF11*(1+$B$5) -> 0.74717211 | AN11: =AJ11*(1+$B$5) -> 0.74856801 | AR11: =AN11*(1+$B$5) -> 0.74996653 | AV11: =AR11*(1+$B$5) -> 0.75136765 | AZ11: =AV11 -> 0.75136765 | BD11: =AZ11 -> 0.75136765 | BH11: =BD11 -> 0.75136765 | BL11: =BH11 -> 0.75136765 | BP11: =BL11 -> 0.75136765
A12: ADR | B12: 112.49476 | D12: 116 | F12: 115 | H12: 117.25 | J12: 125.93 | L12: 126.6 | N12: 125.6 | P12: 108.9 | R12: 115.4 | T12: 121.7 | V12: 127.12 | X12: 119.69 | AB12: =X12*(1+$B$4) -> 120.64994 | AF12: =AB12*(1+$B$4) -> 121.61759 | AJ12: =AF12*(1+$B$4) -> 122.59299 | AN12: =AJ12*(1+$B$4) -> 123.57622 | AR12: =AN12*(1+$B$4) -> 124.56733 | AV12: =AR12*(1+$B$4) -> 125.56639 | AZ12: =AV12*(1+$B$4) -> 126.57347 | BD12: =AZ12*(1+$B$4) -> 127.58862 | BH12: =BD12*(1+$B$4) -> 128.61191 | BL12: =BH12*(1+$B$4) -> 129.64341 | BP12: =BL12*(1+$B$4) -> 130.68318
A13: RevPAR | B13: 72.50627 | D13: 62.872 | F13: 85.56 | H13: 90.63425 | J13: 91.29925 | L13: 94.5702 | N13: 97.4656 | P13: 23.3046 | R13: 26.1958 | T13: 55.7386 | V13: 80.84832 | X13: 88.92967 | AB13: =AB11*AB12 -> 89.810384 | AF13: =AF11*AF12 -> 90.699819 | AJ13: =AJ11*AJ12 -> 91.598064 | AN13: =AN11*AN12 -> 92.505204 | AR13: =AR11*AR12 -> 93.421328 | AV13: =AV11*AV12 -> 94.346524 | AZ13: =AZ11*AZ12 -> 95.103207 | BD13: =BD11*BD12 -> 95.865959 | BH13: =BH11*BH12 -> 96.634828 | BL13: =BL11*BL12 -> 97.409864 | BP13: =BP11*BP12 -> 98.191116
A14: TrevPar
B16: € | C16: % | D16: € | E16: % | F16: € | G16: % | H16: € | I16: % | J16: € | K16: % | L16: € | M16: % | N16: € | O16: % | P16: € | Q16: % | R16: € | S16: % | T16: € | U16: % | V16: € | W16: % | X16: € | Y16: % | Z16: POR | AA16: PAR | AB16: € | AC16: % | AD16: POR | AE16: PAR | AF16: € | AG16: % | AH16: POR | AI16: PAR | AJ16: € | AK16: % | AL16: POR | AM16: PAR | AN16: € | AO16: % | AP16: POR | AQ16: PAR | AR16: € | AS16: % | AT16: POR | AU16: PAR | AV16: € | AW16: % | AX16: POR | AY16: PAR | AZ16: € | BA16: % | BB16: POR | BC16: PAR | BD16: € | BE16: % | BF16: POR | BG16: PAR | BH16: € | BI16: % | BJ16: POR | BK16: PAR | BL16: € | BM16: % | BN16: POR | BO16: PAR | BP16: € | BQ16: % | BR16: POR | BS16: PAR
A17: Departemental Revenue
A18: Rooms | B18: 3758000 | C18: =B18/$B$22 -> 0.66031281 | D18: 3258000 | E18: =D18/$D$22 -> 0.65852012 | F18: 4433000 | G18: =F18/$F$22 -> 0.70170162 | H18: 4712000 | I18: =H18/$H$22 -> 0.70890616 | J18: 4734000 | K18: =J18/$J$22 -> 0.72250101 | L18: 4903000 | M18: =L18/$L$22 -> 0.73018246 | N18: 5038000 | O18: =N18/$N$22 -> 0.74406652 | P18: 1207877.4 | Q18: =P18/$P$22 -> 0.7537751 | R18: 1357728.3 | S18: =R18/$R$22 -> 0.70568795 | T18: 2888931.6 | U18: =T18/$T$22 -> 0.68502385 | V18: 4194000 | W18: =V18/$V$22 -> 0.75999808 | X18: 4623000 | Y18: =X18/$X$22 -> 0.73457266 | Z18: =X18/$X$10 -> 119.71971 | AA18: =X18/$B$2 -> 32556.338 | AB18: =AB10*AB12 -> 4654795.5 | AC18: =AB18/AB$22 -> 0.73607905 | AD18: =AB18/$AB$10 -> 120.64994 | AE18: =AB18/$B$2 -> 32780.25 | AF18: =AF10*AF12 -> 4700884.6 | AG18: =AF18/AF$22 -> 0.73762797 | AH18: =AF18/$AB$10 -> 121.84455 | AI18: =AF18/$B$2 -> 33104.821 | AJ18: =AJ10*AJ12 -> 4747413.6 | AK18: =AJ18/AJ$22 -> 0.73917103 | AL18: =AJ18/$AB$10 -> 123.05056 | AM18: =AJ18/$B$2 -> 33432.49 | AN18: =AN10*AN12 -> 4807609.2 | AO18: =AN18/AN$22 -> 0.7407082 | AP18: =AN18/$AB$10 -> 124.6108 | AQ18: =AN18/$B$2 -> 33856.403 | AR18: =AR10*AR12 -> 4841932.1 | AS18: =AR18/AR$22 -> 0.74223947 | AT18: =AR18/$AB$10 -> 125.50043 | AU18: =AR18/$B$2 -> 34098.114 | AV18: =AV10*AV12 -> 4889932 | AW18: =AV18/AV$22 -> 0.74376482 | AX18: =AV18/$AB$10 -> 126.74456 | AY18: =AV18/$B$2 -> 34436.141 | AZ18: =AZ10*AZ12 -> 4929150.5 | BA18: =AZ18/AZ$22 -> 0.74528425 | BB18: =AZ18/$AB$10 -> 127.76109 | BC18: =AZ18/$B$2 -> 34712.327 | BD18: =BD10*BD12 -> 4982335.5 | BE18: =BD18/BD$22 -> 0.74679773 | BF18: =BD18/$AB$10 -> 129.13962 | BG18: =BD18/$B$2 -> 35086.87 | BH18: =BH10*BH12 -> 5008533.6 | BI18: =BH18/BH$22 -> 0.74830526 | BJ18: =BH18/$AB$10 -> 129.81866 | BK18: =BH18/$B$2 -> 35271.363 | BL18: =BL10*BL12 -> 5048703.3 | BM18: =BL18/BL$22 -> 0.74980682 | BN18: =BL18/$AB$10 -> 130.85984 | BO18: =BL18/$B$2 -> 35554.249 | BP18: =BP10*BP12 -> 5089195.2 | BQ18: =BP18/BP$22 -> 0.75130239 | BR18: =BP18/$AB$10 -> 131.90936 | BS18: =BP18/$B$2 -> 35839.403
A19: Food and Bevarge | B19: 1391000 | C19: =B19/$B$22 -> 0.24441062 | D19: 1208000 | E19: =D19/$D$22 -> 0.24416584 | F19: 1297000 | G19: =F19/$F$22 -> 0.20530273 | H19: 1239000 | I19: =H19/$H$22 -> 0.18640381 | J19: 1293000 | K19: =J19/$J$22 -> 0.19733709 | L19: 1280000 | M19: =L19/$L$22 -> 0.19062483 | N19: 1194000 | O19: =N19/$N$22 -> 0.17634288 | P19: 200000 | Q19: =P19/$P$22 -> 0.12480987 | R19: 250000 | S19: =R19/$R$22 -> 0.12993909 | T19: 840000 | U19: =T19/$T$22 -> 0.19918091 | V19: 899000 | W19: =V19/$V$22 -> 0.16290851 | X19: 1129000 | Y19: =X19/$X$22 -> 0.17939272 | Z19: =X19/$X$10 -> 29.237195 | AA19: =X19/$B$2 -> 7950.7042 | AB19: =AD19*$AB$10 -> 1128000.2 | AC19: =AB19/AB$22 -> 0.17837461 | AD19: =Z19 -> 29.237195 | AE19: =AB19/$B$2 -> 7943.6634 | AF19: =AH19*AF$10 -> 1130105.3 | AG19: =AF19/AF$22 -> 0.17732775 | AH19: =AD19 -> 29.237195 | AI19: =AF19/$B$2 -> 7958.4879 | AJ19: =AL19*AJ$10 -> 1132210.4 | AK19: =AJ19/AJ$22 -> 0.17628485 | AL19: =AH19 -> 29.237195 | AM19: =AJ19/$B$2 -> 7973.3124 | AN19: =AP19*AN$10 -> 1137443.8 | AO19: =AN19/AN$22 -> 0.17524593 | AP19: =AL19 -> 29.237195 | AQ19: =AN19/$B$2 -> 8010.1677 | AR19: =AT19*AR$10 -> 1136449.8 | AS19: =AR19/AR$22 -> 0.174211 | AT19: =AP19 -> 29.237195 | AU19: =AR19/$B$2 -> 8003.1673 | AV19: =AX19*AV$10 -> 1138584.1 | AW19: =AV19/AV$22 -> 0.17318007 | AX19: =AT19 -> 29.237195 | AY19: =AV19/$B$2 -> 8018.1977 | AZ19: =BB19*AZ$10 -> 1138584.1 | BA19: =AZ19/AZ$22 -> 0.17215315 | BB19: =AX19 -> 29.237195 | BC19: =AZ19/$B$2 -> 8018.1977 | BD19: =BF19*BD$10 -> 1141712.4 | BE19: =BD19/BD$22 -> 0.17113024 | BF19: =BB19 -> 29.237195 | BG19: =BD19/$B$2 -> 8040.2285 | BH19: =BJ19*BH$10 -> 1138584.1 | BI19: =BH19/BH$22 -> 0.17011136 | BJ19: =BF19 -> 29.237195 | BK19: =BH19/$B$2 -> 8018.1977 | BL19: =BN19*BL$10 -> 1138584.1 | BM19: =BL19/BL$22 -> 0.16909651 | BN19: =BJ19 -> 29.237195 | BO19: =BL19/$B$2 -> 8018.1977 | BP19: =BR19*BP$10 -> 1138584.1 | BQ19: =BP19/BP$22 -> 0.1680857 | BR19: =BN19 -> 29.237195 | BS19: =BP19/$B$2 -> 8018.1977
A20: Spa | B20: 235242 | C20: =B20/$B$22 -> 0.041334036 | D20: 198457 | E20: =D20/$D$22 -> 0.040112931 | F20: 247500 | G20: =F20/$F$22 -> 0.03917689 | H20: 274860 | I20: =H20/$H$22 -> 0.041351856 | J20: 253240 | K20: =J20/$J$22 -> 0.038649378 | L20: 258760 | M20: =L20/$L$22 -> 0.038536001 | N20: 276900 | O20: =N20/$N$22 -> 0.040895597 | P20: 124560 | Q20: =P20/$P$22 -> 0.077731585 | R20: 174250 | S20: =R20/$R$22 -> 0.090567549 | T20: 303340 | U20: =T20/$T$22 -> 0.07192802 | V20: 297435 | W20: =V20/$V$22 -> 0.053898433 | X20: 309455 | Y20: =X20/$X$22 -> 0.049170924 | Z20: =X20/$X$10 -> 8.013814 | AA20: =X20/$B$2 -> 2179.2606 | AB20: =AD20*$AB$10 -> 309180.96 | AC20: =AB20/AB$22 -> 0.048891864 | AD20: =Z20 -> 8.013814 | AE20: =AB20/$B$2 -> 2177.3307 | AF20: =AH20*AF$10 -> 309757.95 | AG20: =AF20/AF$22 -> 0.048604923 | AH20: =AD20 -> 8.013814 | AI20: =AF20/$B$2 -> 2181.394 | AJ20: =AL20*AJ$10 -> 310334.95 | AK20: =AJ20/AJ$22 -> 0.048319069 | AL20: =AH20 -> 8.013814 | AM20: =AJ20/$B$2 -> 2185.4574 | AN20: =AP20*AN$10 -> 311769.42 | AO20: =AN20/AN$22 -> 0.048034305 | AP20: =AL20 -> 8.013814 | AQ20: =AN20/$B$2 -> 2195.5593 | AR20: =AT20*AR$10 -> 311496.95 | AS20: =AR20/AR$22 -> 0.047750635 | AT20: =AP20 -> 8.013814 | AU20: =AR20/$B$2 -> 2193.6405 | AV20: =AX20*AV$10 -> 312081.96 | AW20: =AV20/AV$22 -> 0.04746806 | AX20: =AT20 -> 8.013814 | AY20: =AV20/$B$2 -> 2197.7603 | AZ20: =BB20*AZ$10 -> 312081.96 | BA20: =AZ20/AZ$22 -> 0.047186583 | BB20: =AX20 -> 8.013814 | BC20: =AZ20/$B$2 -> 2197.7603 | BD20: =BF20*BD$10 -> 312939.44 | BE20: =BD20/BD$22 -> 0.046906207 | BF20: =BB20 -> 8.013814 | BG20: =BD20/$B$2 -> 2203.7989 | BH20: =BJ20*BH$10 -> 312081.96 | BI20: =BH20/BH$22 -> 0.046626935 | BJ20: =BF20 -> 8.013814 | BK20: =BH20/$B$2 -> 2197.7603 | BL20: =BN20*BL$10 -> 312081.96 | BM20: =BL20/BL$22 -> 0.046348768 | BN20: =BJ20 -> 8.013814 | BO20: =BL20/$B$2 -> 2197.7603 | BP20: =BR20*BP$10 -> 312081.96 | BQ20: =BP20/BP$22 -> 0.04607171 | BR20: =BN20 -> 8.013814 | BS20: =BP20/$B$2 -> 2197.7603
A21: Other | B21: 307000 | C21: =B21/$B$22 -> 0.053942531 | D21: 283000 | E21: =D21/$D$22 -> 0.057201104 | F21: 340000 | G21: =F21/$F$22 -> 0.053818757 | H21: 421000 | I21: =H21/$H$22 -> 0.063338178 | J21: 272000 | K21: =J21/$J$22 -> 0.041512521 | L21: 273000 | M21: =L21/$L$22 -> 0.040656703 | N21: 262000 | O21: =N21/$N$22 -> 0.038695004 | P21: 70000 | Q21: =P21/$P$22 -> 0.043683453 | R21: 142000 | S21: =R21/$R$22 -> 0.073805406 | T21: 185000 | U21: =T21/$T$22 -> 0.043867224 | V21: 128000 | W21: =V21/$V$22 -> 0.023194982 | X21: 232000 | Y21: =X21/$X$22 -> 0.036863694 | Z21: =X21/$X$10 -> 6.0079975 | AA21: =X21/$B$2 -> 1633.8028 | AB21: =AD21*$AB$10 -> 231794.55 | AC21: =AB21/AB$22 -> 0.036654481 | AD21: =Z21 -> 6.0079975 | AE21: =AB21/$B$2 -> 1632.356 | AF21: =AH21*AF$10 -> 232227.13 | AG21: =AF21/AF$22 -> 0.03643936 | AH21: =AD21 -> 6.0079975 | AI21: =AF21/$B$2 -> 1635.4023 | AJ21: =AL21*AJ$10 -> 232659.7 | AK21: =AJ21/AJ$22 -> 0.036225054 | AL21: =AH21 -> 6.0079975 | AM21: =AJ21/$B$2 -> 1638.4486 | AN21: =AP21*AN$10 -> 233735.13 | AO21: =AN21/AN$22 -> 0.036011565 | AP21: =AL21 -> 6.0079975 | AQ21: =AN21/$B$2 -> 1646.0221 | AR21: =AT21*AR$10 -> 233530.86 | AS21: =AR21/AR$22 -> 0.035798895 | AT21: =AP21 -> 6.0079975 | AU21: =AR21/$B$2 -> 1644.5835 | AV21: =AX21*AV$10 -> 233969.45 | AW21: =AV21/AV$22 -> 0.035587048 | AX21: =AT21 -> 6.0079975 | AY21: =AV21/$B$2 -> 1647.6722 | AZ21: =BB21*AZ$10 -> 233969.45 | BA21: =AZ21/AZ$22 -> 0.035376023 | BB21: =AX21 -> 6.0079975 | BC21: =AZ21/$B$2 -> 1647.6722 | BD21: =BF21*BD$10 -> 234612.3 | BE21: =BD21/BD$22 -> 0.035165824 | BF21: =BB21 -> 6.0079975 | BG21: =BD21/$B$2 -> 1652.1993 | BH21: =BJ21*BH$10 -> 233969.45 | BI21: =BH21/BH$22 -> 0.034956452 | BJ21: =BF21 -> 6.0079975 | BK21: =BH21/$B$2 -> 1647.6722 | BL21: =BN21*BL$10 -> 233969.45 | BM21: =BL21/BL$22 -> 0.034747909 | BN21: =BJ21 -> 6.0079975 | BO21: =BL21/$B$2 -> 1647.6722 | BP21: =BR21*BP$10 -> 233969.45 | BQ21: =BP21/BP$22 -> 0.034540197 | BR21: =BN21 -> 6.0079975 | BS21: =BP21/$B$2 -> 1647.6722
A22: Total Operating Revenue | B22: =SUM(B18:B21) -> 5691242 | C22: =B22/$B$22 -> 1 | D22: =SUM(D18:D21) -> 4947457 | E22: =D22/$D$22 -> 1 | F22: =SUM(F18:F21) -> 6317500 | G22: =F22/$F$22 -> 1 | H22: =SUM(H18:H21) -> 6646860 | I22: =H22/$H$22 -> 1 | J22: =SUM(J18:J21) -> 6552240 | K22: =J22/$J$22 -> 1 | L22: =SUM(L18:L21) -> 6714760 | M22: =L22/$L$22 -> 1 | N22: =SUM(N18:N21) -> 6770900 | O22: =N22/$N$22 -> 1 | P22: =SUM(P18:P21) -> 1602437.4 | Q22: =P22/$P$22 -> 1 | R22: =SUM(R18:R21) -> 1923978.3 | S22: =R22/$R$22 -> 1 | T22: =SUM(T18:T21) -> 4217271.6 | U22: =T22/$T$22 -> 1 | V22: =SUM(V18:V21) -> 5518435 | W22: =V22/$V$22 -> 1 | X22: =SUM(X18:X21) -> 6293455 | Y22: =X22/$X$22 -> 1 | Z22: =X22/$X$10 -> 162.97871 | AA22: =X22/$B$2 -> 44320.106 | AB22: =SUM(AB18:AB21) -> 6323771.2 | AC22: =AB22/$AB$22 -> 1 | AD22: =AB22/$AB$10 -> 163.90895 | AE22: =AB22/$B$2 -> 44533.6 | AF22: =SUM(AF18:AF21) -> 6372975 | AG22: =SUM(AG18:AG21) -> 1 | AH22: =SUM(AH18:AH21) -> 165.10356 | AI22: =AF22/$B$2 -> 44880.105 | AJ22: =SUM(AJ18:AJ21) -> 6422618.6 | AK22: =SUM(AK18:AK21) -> 1 | AL22: =SUM(AL18:AL21) -> 166.30956 | AM22: =AJ22/$B$2 -> 45229.708 | AN22: =SUM(AN18:AN21) -> 6490557.5 | AO22: =SUM(AO18:AO21) -> 1 | AP22: =SUM(AP18:AP21) -> 167.8698 | AQ22: =AN22/$B$2 -> 45708.152 | AR22: =SUM(AR18:AR21) -> 6523409.7 | AS22: =SUM(AS18:AS21) -> 1 | AT22: =SUM(AT18:AT21) -> 168.75944 | AU22: =AR22/$B$2 -> 45939.505 | AV22: =SUM(AV18:AV21) -> 6574567.5 | AW22: =SUM(AW18:AW21) -> 1 | AX22: =SUM(AX18:AX21) -> 170.00357 | AY22: =AV22/$B$2 -> 46299.771 | AZ22: =SUM(AZ18:AZ21) -> 6613786 | BA22: =SUM(BA18:BA21) -> 1 | BB22: =SUM(BB18:BB21) -> 171.02009 | BC22: =AZ22/$B$2 -> 46575.957 | BD22: =SUM(BD18:BD21) -> 6671599.7 | BE22: =SUM(BE18:BE21) -> 1 | BF22: =SUM(BF18:BF21) -> 172.39862 | BG22: =BD22/$B$2 -> 46983.096 | BH22: =SUM(BH18:BH21) -> 6693169.1 | BI22: =SUM(BI18:BI21) -> 1 | BJ22: =SUM(BJ18:BJ21) -> 173.07766 | BK22: =BH22/$B$2 -> 47134.994 | BL22: =SUM(BL18:BL21) -> 6733338.8 | BM22: =SUM(BM18:BM21) -> 1 | BN22: =SUM(BN18:BN21) -> 174.11884 | BO22: =BL22/$B$2 -> 47417.879 | BP22: =SUM(BP18:BP21) -> 6773830.7 | BQ22: =SUM(BQ18:BQ21) -> 1 | BR22: =SUM(BR18:BR21) -> 175.16837 | BS22: =BP22/$B$2 -> 47703.033
A23: Departemental Expenses
A24: Rooms | B24: 1294631 | C24: =B24/B18 -> 0.3445 | D24: 1161570.5 | E24: =D24/D18 -> 0.3565287 | F24: 1365913.7 | G24: =F24/F18 -> 0.308124 | H24: 1406202.2 | I24: =H24/H18 -> 0.29843 | J24: 1434000 | K24: =J24/J18 -> 0.30291508 | L24: 1391000 | M24: =L24/L18 -> 0.28370385 | N24: 1431000 | O24: =N24/N18 -> 0.28404129 | P24: 338205.68 | Q24: =P24/P18 -> 0.28 | R24: 380163.93 | S24: =R24/R18 -> 0.28 | T24: 808900.86 | U24: =T24/T18 -> 0.28 | V24: 1413000 | W24: =V24/V18 -> 0.33690987 | X24: 1581000 | Y24: =X24/X18 -> 0.34198572 | Z24: =X24/$X$10 -> 40.942431 | AA24: =X24/$B$2 -> 11133.803 | AB24: =AC24*AB18 -> 1591873.6 | AC24: =Y24 -> 0.34198572 | AD24: =AB24/$AB$10 -> 41.260558 | AE24: =AB24/$B$2 -> 11210.377 | AF24: =AG24*AF18 -> 1607635.4 | AG24: =AC24 -> 0.34198572 | AH24: =AF24/$AF$10 -> 41.591479 | AI24: =AF24/$B$2 -> 11321.376 | AJ24: =AK24*AJ18 -> 1623547.7 | AK24: =AG24 -> 0.34198572 | AL24: =AJ24/$AJ$10 -> 41.925053 | AM24: =AJ24/$B$2 -> 11433.434 | AN24: =AO24*AN18 -> 1644133.7 | AO24: =AK24 -> 0.34198572 | AP24: =AN24/$AN$10 -> 42.261302 | AQ24: =AN24/$B$2 -> 11578.406 | AR24: =AS24*AR18 -> 1655871.7 | AS24: =AO24 -> 0.34198572 | AT24: =AR24/$AR$10 -> 42.600249 | AU24: =AR24/$B$2 -> 11661.068 | AV24: =AW24*AV18 -> 1672286.9 | AW24: =AS24 -> 0.34198572 | AX24: =AV24/$AV$10 -> 42.941913 | AY24: =AV24/$B$2 -> 11776.669 | AZ24: =BA24*AZ18 -> 1685699.1 | BA24: =AW24 -> 0.34198572 | BB24: =AZ24/$AZ$10 -> 43.286318 | BC24: =AZ24/$B$2 -> 11871.12 | BD24: =BE24*BD18 -> 1703887.6 | BE24: =BA24 -> 0.34198572 | BF24: =BD24/$BD$10 -> 43.633485 | BG24: =BD24/$B$2 -> 11999.209 | BH24: =BI24*BH18 -> 1712847 | BI24: =BE24 -> 0.34198572 | BJ24: =BH24/$BH$10 -> 43.983437 | BK24: =BH24/$B$2 -> 12062.303 | BL24: =BM24*BL18 -> 1726584.5 | BM24: =BI24 -> 0.34198572 | BN24: =BL24/$BL$10 -> 44.336195 | BO24: =BL24/$B$2 -> 12159.045 | BP24: =BQ24*BP18 -> 1740432.1 | BQ24: =BM24 -> 0.34198572 | BR24: =BP24/$BL$10 -> 44.691783 | BS24: =BP24/$B$2 -> 12256.564
A25: Food and Beverage | B25: 1210091.6 | C25: =B25/B19 -> 0.86994363 | D25: 1102489.5 | E25: =D25/D19 -> 0.9126569 | F25: 1280953.9 | G25: =F25/F19 -> 0.98762827 | H25: 1267033.1 | I25: =H25/H19 -> 1.0226256 | J25: 1197000 | K25: =J25/J19 -> 0.92575406 | L25: 1099000 | M25: =L25/L19 -> 0.85859375 | N25: 1090000 | O25: =N25/N19 -> 0.91289782 | P25: 187134 | Q25: =P25/P19 -> 0.93567 | R25: 231175 | S25: =R25/R19 -> 0.9247 | T25: 770985.6 | U25: =T25/T19 -> 0.91784 | V25: 839000 | W25: =V25/V19 -> 0.93325918 | X25: 1133000 | Y25: =X25/X19 -> 1.003543 | Z25: =X25/$X$10 -> 29.340781 | AA25: =X25/$B$2 -> 7978.8732 | AB25: =AC25*AB19 -> 1131996.7 | AC25: =Y25 -> 1.003543 | AD25: =AB25/$AB$10 -> 29.340781 | AE25: =AB25/$B$2 -> 7971.8075 | AF25: =AG25*AF19 -> 1134109.2 | AG25: =AC25 -> 1.003543 | AH25: =AF25/$AF$10 -> 29.340781 | AI25: =AF25/$B$2 -> 7986.6845 | AJ25: =AK25*AJ19 -> 1136221.7 | AK25: =AG25 -> 1.003543 | AL25: =AJ25/$AJ$10 -> 29.340781 | AM25: =AJ25/$B$2 -> 8001.5615 | AN25: =AO25*AN19 -> 1141473.7 | AO25: =AK25 -> 1.003543 | AP25: =AN25/$AN$10 -> 29.340781 | AQ25: =AN25/$B$2 -> 8038.5474 | AR25: =AS25*AR19 -> 1140476.1 | AS25: =AO25 -> 1.003543 | AT25: =AR25/$AR$10 -> 29.340781 | AU25: =AR25/$B$2 -> 8031.5222 | AV25: =AW25*AV19 -> 1142618 | AW25: =AS25 -> 1.003543 | AX25: =AV25/$AV$10 -> 29.340781 | AY25: =AV25/$B$2 -> 8046.6058 | AZ25: =BA25*AZ19 -> 1142618 | BA25: =AW25 -> 1.003543 | BB25: =AZ25/$AZ$10 -> 29.340781 | BC25: =AZ25/$B$2 -> 8046.6058 | BD25: =BE25*BD19 -> 1145757.5 | BE25: =BA25 -> 1.003543 | BF25: =BD25/$BD$10 -> 29.340781 | BG25: =BD25/$B$2 -> 8068.7147 | BH25: =BI25*BH19 -> 1142618 | BI25: =BE25 -> 1.003543 | BJ25: =BH25/$BH$10 -> 29.340781 | BK25: =BH25/$B$2 -> 8046.6058 | BL25: =BM25*BL19 -> 1142618 | BM25: =BI25 -> 1.003543 | BN25: =BL25/$BL$10 -> 29.340781 | BO25: =BL25/$B$2 -> 8046.6058 | BP25: =BQ25*BP19 -> 1142618 | BQ25: =BM25 -> 1.003543 | BR25: =BP25/$BL$10 -> 29.340781 | BS25: =BP25/$B$2 -> 8046.6058
A26: Spa | B26: 176099.81 | C26: =B26/B20 -> 0.74859 | D26: 148562.93 | E26: =D26/D20 -> 0.74859 | F26: 185276.02 | G26: =F26/F20 -> 0.74859 | H26: 205757.45 | I26: =H26/H20 -> 0.74859 | J26: 189572.93 | K26: =J26/J20 -> 0.74859 | L26: 180200 | M26: =L26/L20 -> 0.69639821 | N26: 215400 | O26: =N26/N20 -> 0.77789816 | P26: 119378.3 | Q26: =P26/P20 -> 0.9584 | R26: 167001.2 | S26: =R26/R20 -> 0.9584 | T26: 238380 | U26: =T26/T20 -> 0.78585086 | V26: 239975 | W26: =V26/V20 -> 0.80681493 | X26: 253390 | Y26: =X26/X20 -> 0.81882665 | Z26: =X26/$X$10 -> 6.5619245 | AA26: =X26/$B$2 -> 1784.4366 | AB26: =AC26*AB20 -> 253165.61 | AC26: =Y26 -> 0.81882665 | AD26: =AB26/$AB$10 -> 6.5619245 | AE26: =AB26/$B$2 -> 1782.8564 | AF26: =AG26*AF20 -> 253638.07 | AG26: =AC26 -> 0.81882665 | AH26: =AF26/$AF$10 -> 6.5619245 | AI26: =AF26/$B$2 -> 1786.1836 | AJ26: =AK26*AJ20 -> 254110.53 | AK26: =AG26 -> 0.81882665 | AL26: =AJ26/$AJ$10 -> 6.5619245 | AM26: =AJ26/$B$2 -> 1789.5107 | AN26: =AO26*AN20 -> 255285.11 | AO26: =AK26 -> 0.81882665 | AP26: =AN26/$AN$10 -> 6.5619245 | AQ26: =AN26/$B$2 -> 1797.7825 | AR26: =AS26*AR20 -> 255062 | AS26: =AO26 -> 0.81882665 | AT26: =AR26/$AR$10 -> 6.5619245 | AU26: =AR26/$B$2 -> 1796.2113 | AV26: =AW26*AV20 -> 255541.03 | AW26: =AS26 -> 0.81882665 | AX26: =AV26/$AV$10 -> 6.5619245 | AY26: =AV26/$B$2 -> 1799.5847 | AZ26: =BA26*AZ20 -> 255541.03 | BA26: =AW26 -> 0.81882665 | BB26: =AZ26/$AZ$10 -> 6.5619245 | BC26: =AZ26/$B$2 -> 1799.5847 | BD26: =BE26*BD20 -> 256243.15 | BE26: =BA26 -> 0.81882665 | BF26: =BD26/$BD$10 -> 6.5619245 | BG26: =BD26/$B$2 -> 1804.5292 | BH26: =BI26*BH20 -> 255541.03 | BI26: =BE26 -> 0.81882665 | BJ26: =BH26/$BH$10 -> 6.5619245 | BK26: =BH26/$B$2 -> 1799.5847 | BL26: =BM26*BL20 -> 255541.03 | BM26: =BI26 -> 0.81882665 | BN26: =BL26/$BL$10 -> 6.5619245 | BO26: =BL26/$B$2 -> 1799.5847 | BP26: =BQ26*BP20 -> 255541.03 | BQ26: =BM26 -> 0.81882665 | BR26: =BP26/$BL$10 -> 6.5619245 | BS26: =BP26/$B$2 -> 1799.5847
A27: Other | B27: 96477.404 | C27: =B27/B21 -> 0.31425865 | D27: 180000 | E27: =D27/D21 -> 0.6360424 | F27: 162132.45 | G27: =F27/F21 -> 0.47686014 | H27: 137616.69 | I27: =H27/H21 -> 0.3268805 | J27: 135000 | K27: =J27/J21 -> 0.49632353 | L27: 115000 | M27: =L27/L21 -> 0.42124542 | N27: 128000 | O27: =N27/N21 -> 0.48854962 | P27: 128000 | Q27: =P27/P21 -> 1.8285714 | R27: 128000 | S27: =R27/R21 -> 0.90140845 | T27: 128000 | U27: =T27/T21 -> 0.69189189 | V27: 110000 | W27: =V27/V21 -> 0.859375 | X27: 125000 | Y27: =X27/X21 -> 0.5387931 | Z27: =X27/$X$10 -> 3.2370676 | AA27: =X27/$B$2 -> 880.28169 | AB27: =AC27*AB21 -> 124889.31 | AC27: =Y27 -> 0.5387931 | AD27: =AB27/$AB$10 -> 3.2370676 | AE27: =AB27/$B$2 -> 879.50215 | AF27: =AG27*AF21 -> 125122.37 | AG27: =AC27 -> 0.5387931 | AH27: =AF27/$AF$10 -> 3.2370676 | AI27: =AF27/$B$2 -> 881.14348 | AJ27: =AK27*AJ21 -> 125355.44 | AK27: =AG27 -> 0.5387931 | AL27: =AJ27/$AJ$10 -> 3.2370676 | AM27: =AJ27/$B$2 -> 882.78481 | AN27: =AO27*AN21 -> 125934.88 | AO27: =AK27 -> 0.5387931 | AP27: =AN27/$AN$10 -> 3.2370676 | AQ27: =AN27/$B$2 -> 886.86534 | AR27: =AS27*AR21 -> 125824.82 | AS27: =AO27 -> 0.5387931 | AT27: =AR27/$AR$10 -> 3.2370676 | AU27: =AR27/$B$2 -> 886.09027 | AV27: =AW27*AV21 -> 126061.12 | AW27: =AS27 -> 0.5387931 | AX27: =AV27/$AV$10 -> 3.2370676 | AY27: =AV27/$B$2 -> 887.75439 | AZ27: =BA27*AZ21 -> 126061.12 | BA27: =AW27 -> 0.5387931 | BB27: =AZ27/$AZ$10 -> 3.2370676 | BC27: =AZ27/$B$2 -> 887.75439 | BD27: =BE27*BD21 -> 126407.49 | BE27: =BA27 -> 0.5387931 | BF27: =BD27/$BD$10 -> 3.2370676 | BG27: =BD27/$B$2 -> 890.19359 | BH27: =BI27*BH21 -> 126061.12 | BI27: =BE27 -> 0.5387931 | BJ27: =BH27/$BH$10 -> 3.2370676 | BK27: =BH27/$B$2 -> 887.75439 | BL27: =BM27*BL21 -> 126061.12 | BM27: =BI27 -> 0.5387931 | BN27: =BL27/$BL$10 -> 3.2370676 | BO27: =BL27/$B$2 -> 887.75439 | BP27: =BQ27*BP21 -> 126061.12 | BQ27: =BM27 -> 0.5387931 | BR27: =BP27/$BL$10 -> 3.2370676 | BS27: =BP27/$B$2 -> 887.75439
A28: Total Departemental Expenses | B28: =SUM(B24:B27) -> 2777299.8 | C28: =B28/B22 -> 0.48799538 | D28: =SUM(D24:D27) -> 2592623 | E28: =D28/D22 -> 0.52403143 | F28: =SUM(F24:F27) -> 2994276 | G28: =F28/F22 -> 0.47396534 | H28: =SUM(H24:H27) -> 3016609.4 | I28: =H28/H22 -> 0.45383977 | J28: =SUM(J24:J27) -> 2955572.9 | K28: =J28/J22 -> 0.45107825 | L28: =SUM(L24:L27) -> 2785200 | M28: =L28/L22 -> 0.41478772 | N28: =SUM(N24:N27) -> 2864400 | O28: =N28/N22 -> 0.42304568 | P28: =SUM(P24:P27) -> 772717.98 | Q28: =P28/P22 -> 0.48221414 | R28: =SUM(R24:R27) -> 906340.13 | S28: =R28/R22 -> 0.47107606 | T28: =SUM(T24:T27) -> 1946266.5 | U28: =T28/T22 -> 0.46149896 | V28: =SUM(V24:V27) -> 2601975 | W28: =V28/V22 -> 0.47150596 | X28: =SUM(X24:X27) -> 3092390 | Y28: =X28/X22 -> 0.49136603 | Z28: =X28/$X$10 -> 80.082204 | AA28: =X28/$B$2 -> 21777.394 | AB28: =SUM(AB24:AB27) -> 3101925.2 | AC28: =AB28/$AB$22 -> 0.49051825 | AD28: =AB28/$AB$10 -> 80.400331 | AE28: =AB28/$B$2 -> 21844.544 | AF28: =SUM(AF24:AF27) -> 3120505.1 | AG28: =AF28/$AF$22 -> 0.48964653 | AH28: =AF28/$AF$10 -> 80.731251 | AI28: =AF28/$B$2 -> 21975.388 | AJ28: =SUM(AJ24:AJ27) -> 3139235.4 | AK28: =AJ28/$AJ$22 -> 0.48877811 | AL28: =AJ28/$AJ$10 -> 81.064826 | AM28: =AJ28/$B$2 -> 22107.291 | AN28: =SUM(AN24:AN27) -> 3166827.4 | AO28: =AN28/$AN$22 -> 0.487913 | AP28: =AN28/$AN$10 -> 81.401075 | AQ28: =AN28/$B$2 -> 22301.602 | AR28: =SUM(AR24:AR27) -> 3177234.6 | AS28: =AR28/$AR$22 -> 0.48705122 | AT28: =AR28/$AR$10 -> 81.740021 | AU28: =AR28/$B$2 -> 22374.892 | AV28: =SUM(AV24:AV27) -> 3196507.1 | AW28: =AV28/$AV$22 -> 0.48619276 | AX28: =AV28/$AV$10 -> 82.081686 | AY28: =AV28/$B$2 -> 22510.613 | AZ28: =SUM(AZ24:AZ27) -> 3209919.3 | BA28: =AZ28/$AZ$22 -> 0.48533764 | BB28: =AZ28/$AZ$10 -> 82.426091 | BC28: =AZ28/$B$2 -> 22605.065 | BD28: =SUM(BD24:BD27) -> 3232295.7 | BE28: =BD28/$BD$22 -> 0.48448586 | BF28: =BD28/$BD$10 -> 82.773258 | BG28: =BD28/$B$2 -> 22762.646 | BH28: =SUM(BH24:BH27) -> 3237067.2 | BI28: =BH28/$BH$22 -> 0.48363744 | BJ28: =BH28/$BH$10 -> 83.12321 | BK28: =BH28/$B$2 -> 22796.248 | BL28: =SUM(BL24:BL27) -> 3250804.6 | BM28: =BL28/$BL$22 -> 0.48279238 | BN28: =BL28/$BL$10 -> 83.475968 | BO28: =BL28/$B$2 -> 22892.99 | BP28: =SUM(BP24:BP27) -> 3264652.3 | BQ28: =BP28/$BL$22 -> 0.48484895 | BR28: =BP28/$BL$10 -> 83.831556 | BS28: =BP28/$B$2 -> 22990.509
A29: Total Departemental Profit | B29: =B22-B28 -> 2913942.2 | C29: =B29/$B$22 -> 0.51200462 | D29: =D22-D28 -> 2354834 | E29: =D29/$D$22 -> 0.47596857 | F29: =F22-F28 -> 3323224 | G29: =F29/$F$22 -> 0.52603466 | H29: =H22-H28 -> 3630250.6 | I29: =H29/$H$22 -> 0.54616023 | J29: =J22-J28 -> 3596667.1 | K29: =J29/$J$22 -> 0.54892175 | L29: =L22-L28 -> 3929560 | M29: =L29/$L$22 -> 0.58521228 | N29: =N22-N28 -> 3906500 | O29: =N29/$N$22 -> 0.57695432 | P29: =P22-P28 -> 829719.44 | Q29: =P29/$P$22 -> 0.51778586 | R29: =R22-R28 -> 1017638.2 | S29: =R29/$R$22 -> 0.52892394 | T29: =T22-T28 -> 2271005.2 | U29: =T29/$T$22 -> 0.53850104 | V29: =V22-V28 -> 2916460 | W29: =V29/$V$22 -> 0.52849404 | X29: =X22-X28 -> 3201065 | Y29: =X29/$X$22 -> 0.50863397 | Z29: =X29/$X$10 -> 82.89651 | AA29: =X29/$B$2 -> 22542.711 | AB29: =AB22-AB28 -> 3221846 | AC29: =AB29/$AB$22 -> 0.50948175 | AD29: =AB29/$AB$10 -> 83.508619 | AE29: =AB29/$B$2 -> 22689.057 | AF29: =AF22-AF28 -> 3252469.9 | AG29: =AF29/$AF$22 -> 0.51035347 | AH29: =AF29/$AF$10 -> 84.145342 | AI29: =AF29/$B$2 -> 22904.718 | AJ29: =AJ22-AJ28 -> 3283383.2 | AK29: =AJ29/$AJ$22 -> 0.51122189 | AL29: =AJ29/$AJ$10 -> 84.787171 | AM29: =AJ29/$B$2 -> 23122.417 | AN29: =AN22-AN28 -> 3323730.1 | AO29: =AN29/$AN$22 -> 0.512087 | AP29: =AN29/$AN$10 -> 85.434149 | AQ29: =AN29/$B$2 -> 23406.55 | AR29: =AR22-AR28 -> 3346175.1 | AS29: =AR29/$AR$22 -> 0.51294878 | AT29: =AR29/$AR$10 -> 86.086315 | AU29: =AR29/$B$2 -> 23564.613 | AV29: =AV22-AV28 -> 3378060.4 | AW29: =AV29/$AV$22 -> 0.51380724 | AX29: =AV29/$AV$10 -> 86.743712 | AY29: =AV29/$B$2 -> 23789.157 | AZ29: =AZ22-AZ28 -> 3403866.7 | BA29: =AZ29/$AZ$22 -> 0.51466236 | BB29: =AZ29/$AZ$10 -> 87.406381 | BC29: =AZ29/$B$2 -> 23970.892 | BD29: =BD22-BD28 -> 3439303.9 | BE29: =BD29/$BD$22 -> 0.51551414 | BF29: =BD29/$BD$10 -> 88.074365 | BG29: =BD29/$B$2 -> 24220.45 | BH29: =BH22-BH28 -> 3456101.9 | BI29: =BH29/$BH$22 -> 0.51636256 | BJ29: =BH29/$BH$10 -> 88.747706 | BK29: =BH29/$B$2 -> 24338.746 | BL29: =BL22-BL28 -> 3482534.2 | BM29: =BL29/$BL$22 -> 0.51720762 | BN29: =BL29/$BL$10 -> 89.426448 | BO29: =BL29/$B$2 -> 24524.888 | BP29: =BP22-BP28 -> 3509178.4 | BQ29: =BP29/$BL$22 -> 0.52116469 | BR29: =BP29/$BL$10 -> 90.110633 | BS29: =BP29/$B$2 -> 24712.524
A30: Undistributed Operating Expenses
A31: Aministrative and General | B31: 598000 | C31: =B31/$B$22 -> 0.10507373 | D31: 598700 | E31: =D31/$D$22 -> 0.12101166 | F31: 658400 | G31: =F31/$F$22 -> 0.10421844 | H31: 684200 | I31: =H31/$H$22 -> 0.10293582 | J31: 603000 | K31: =J31/$J$22 -> 0.092029596 | L31: 854000 | M31: =L31/$L$22 -> 0.12718251 | N31: 407000 | O31: =N31/$N$22 -> 0.060110177 | P31: 407000 | Q31: =P31/$P$22 -> 0.25398808 | R31: 407000 | S31: =R31/$R$22 -> 0.21154085 | T31: 407000 | U31: =T31/$T$22 -> 0.096507893 | V31: 666000 | W31: =V31/$V$22 -> 0.12068639 | X31: 380000 | Y31: =X31/$X$22 -> 0.060380189 | Z31: =X31/$X$10 -> 9.8406855 | AA31: =X31/$B$2 -> 2676.0563 | AB31: =AE31*$B$2 -> 388049.09 | AC31: =Y31 -> 0.060380189 | AD31: =AB31/$AB$10 -> 10.058036 | AE31: =AA31*(1+Inflation) -> 2732.7401 | AF31: =AI31*$B$2 -> 396268.68 | AG31: =AF31/AF$22 -> 0.062179544 | AH31: =AF31/$AF$10 -> 10.251951 | AI31: =AE31*(1+Inflation) -> 2790.6245 | AJ31: =AM31*$B$2 -> 404662.37 | AK31: =AJ31/AJ$22 -> 0.063005823 | AL31: =AJ31/$AF$10 -> 10.469106 | AM31: =AI31*(1+Inflation) -> 2849.735 | AN31: =AQ31*$B$2 -> 413233.85 | AO31: =AN31/AN$22 -> 0.063666927 | AP31: =AN31/$AF$10 -> 10.690861 | AQ31: =AM31*(1+Inflation) -> 2910.0975 | AR31: =AU31*$B$2 -> 421986.9 | AS31: =AR31/AR$22 -> 0.064688087 | AT31: =AR31/$AF$10 -> 10.917313 | AU31: =AQ31*(1+Inflation) -> 2971.7387 | AV31: =AY31*$B$2 -> 430925.35 | AW31: =AV31/AV$22 -> 0.065544288 | AX31: =AV31/$AF$10 -> 11.148561 | AY31: =AU31*(1+Inflation) -> 3034.6855 | AZ31: =BC31*$B$2 -> 440053.13 | BA31: =AZ31/AZ$22 -> 0.066535738 | BB31: =AZ31/$AF$10 -> 11.384708 | BC31: =AY31*(1+Inflation) -> 3098.9657 | BD31: =BG31*$B$2 -> 449374.25 | BE31: =BD31/BD$22 -> 0.067356298 | BF31: =BD31/$AF$10 -> 11.625857 | BG31: =BC31*(1+Inflation) -> 3164.6074 | BH31: =BK31*$B$2 -> 458892.82 | BI31: =BH31/BH$22 -> 0.068561366 | BJ31: =BH31/$AF$10 -> 11.872114 | BK31: =BG31*(1+Inflation) -> 3231.6396 | BL31: =BO31*$B$2 -> 468613 | BM31: =BL31/BL$22 -> 0.069595934 | BN31: =BL31/$AF$10 -> 12.123587 | BO31: =BK31*(1+Inflation) -> 3300.0916 | BP31: =BS31*$B$2 -> 478539.08 | BQ31: =BP31/BP$22 -> 0.070645267 | BR31: =BP31/$AF$10 -> 12.380386 | BS31: =BO31*(1+Inflation) -> 3369.9935
A32: Sales And Marketing | B32: 424700 | C32: =B32/$B$22 -> 0.07462343 | D32: 403250 | E32: =D32/$D$22 -> 0.081506519 | F32: 472140 | G32: =F32/$F$22 -> 0.074735259 | H32: 462370 | I32: =H32/$H$22 -> 0.069562169 | J32: 433000 | K32: =J32/$J$22 -> 0.06608427 | L32: 456000 | M32: =L32/$L$22 -> 0.067910097 | N32: 450000 | O32: =N32/$N$22 -> 0.066460884 | P32: 450000 | Q32: =P32/$P$22 -> 0.2808222 | R32: 450000 | S32: =R32/$R$22 -> 0.23389037 | T32: 450000 | U32: =T32/$T$22 -> 0.10670406 | V32: 366000 | W32: =V32/$V$22 -> 0.066323151 | X32: 230000 | Y32: =X32/$X$22 -> 0.036545904 | Z32: =X32/$X$10 -> 5.9562044 | AA32: =X32/$B$2 -> 1619.7183 | AB32: =AE32*$B$2 -> 234871.82 | AC32: =Y32 -> 0.036545904 | AD32: =AB32/$AB$10 -> 6.0877587 | AE32: =AA32*(1+Inflation) -> 1654.0269 | AF32: =AI32*$B$2 -> 239846.83 | AG32: =AF32/AF$22 -> 0.037634987 | AH32: =AF32/$AF$10 -> 6.2051285 | AI32: =AE32*(1+Inflation) -> 1689.0622 | AJ32: =AM32*$B$2 -> 244927.22 | AK32: =AJ32/AJ$22 -> 0.038135103 | AL32: =AJ32/$AF$10 -> 6.3365644 | AM32: =AI32*(1+Inflation) -> 1724.8396 | AN32: =AQ32*$B$2 -> 250115.23 | AO32: =AN32/AN$22 -> 0.038535245 | AP32: =AN32/$AF$10 -> 6.4707843 | AQ32: =AM32*(1+Inflation) -> 1761.3748 | AR32: =AU32*$B$2 -> 255413.12 | AS32: =AR32/AR$22 -> 0.039153316 | AT32: =AR32/$AF$10 -> 6.6078473 | AU32: =AQ32*(1+Inflation) -> 1798.684 | AV32: =AY32*$B$2 -> 260823.24 | AW32: =AV32/AV$22 -> 0.039671543 | AX32: =AV32/$AF$10 -> 6.7478135 | AY32: =AU32*(1+Inflation) -> 1836.7834 | AZ32: =BC32*$B$2 -> 266347.95 | BA32: =AZ32/AZ$22 -> 0.040271631 | BB32: =AZ32/$AF$10 -> 6.8907445 | BC32: =AY32*(1+Inflation) -> 1875.6898 | BD32: =BG32*$B$2 -> 271989.68 | BE32: =BD32/BD$22 -> 0.040768285 | BF32: =BD32/$AF$10 -> 7.036703 | BG32: =BC32*(1+Inflation) -> 1915.4203 | BH32: =BK32*$B$2 -> 277750.92 | BI32: =BH32/BH$22 -> 0.041497669 | BJ32: =BH32/$AF$10 -> 7.1857531 | BK32: =BG32*(1+Inflation) -> 1955.9924 | BL32: =BO32*$B$2 -> 283634.19 | BM32: =BL32/BL$22 -> 0.042123855 | BN32: =BL32/$AF$10 -> 7.3379604 | BO32: =BK32*(1+Inflation) -> 1997.4238 | BP32: =BS32*$B$2 -> 289642.07 | BQ32: =BP32/BP$22 -> 0.042758977 | BR32: =BP32/$AF$10 -> 7.4933918 | BS32: =BO32*(1+Inflation) -> 2039.7329
A33: Heat light and Power | B33: 324500 | C33: =B33/$B$22 -> 0.057017431 | D33: 314780 | E33: =D33/$D$22 -> 0.063624606 | F33: 384520 | G33: =F33/$F$22 -> 0.060865849 | H33: 395470 | I33: =H33/$H$22 -> 0.059497266 | J33: 395000 | K33: =J33/$J$22 -> 0.060284727 | L33: 266000 | M33: =L33/$L$22 -> 0.039614223 | N33: 297000 | O33: =N33/$N$22 -> 0.043864183 | P33: 297000 | Q33: =P33/$P$22 -> 0.18534265 | R33: 297000 | S33: =R33/$R$22 -> 0.15436764 | T33: 297000 | U33: =T33/$T$22 -> 0.070424679 | V33: 363000 | W33: =V33/$V$22 -> 0.065779519 | X33: 340000 | Y33: =X33/$X$22 -> 0.054024379 | Z33: =X33/$X$10 -> 8.8048239 | AA33: =X33/$B$2 -> 2394.3662 | AB33: =AE33*$B$2 -> 347201.82 | AC33: =Y33 -> 0.054024379 | AD33: =AB33/$AB$10 -> 8.9992955 | AE33: =AA33*(1+Inflation) -> 2445.0832 | AF33: =AI33*$B$2 -> 354556.18 | AG33: =AF33/AF$22 -> 0.055634329 | AH33: =AF33/$AF$10 -> 9.1727986 | AI33: =AE33*(1+Inflation) -> 2496.8745 | AJ33: =AM33*$B$2 -> 362066.33 | AK33: =AJ33/AJ$22 -> 0.056373631 | AL33: =AJ33/$AF$10 -> 9.3670951 | AM33: =AI33*(1+Inflation) -> 2549.7629 | AN33: =AQ33*$B$2 -> 369735.55 | AO33: =AN33/AN$22 -> 0.056965145 | AP33: =AN33/$AF$10 -> 9.5655072 | AQ33: =AM33*(1+Inflation) -> 2603.7715 | AR33: =AU33*$B$2 -> 377567.22 | AS33: =AR33/AR$22 -> 0.057878815 | AT33: =AR33/$AF$10 -> 9.7681221 | AU33: =AQ33*(1+Inflation) -> 2658.9241 | AV33: =AY33*$B$2 -> 385564.78 | AW33: =AV33/AV$22 -> 0.05864489 | AX33: =AV33/$AF$10 -> 9.9750287 | AY33: =AU33*(1+Inflation) -> 2715.245 | AZ33: =BC33*$B$2 -> 393731.75 | BA33: =AZ33/AZ$22 -> 0.059531976 | BB33: =AZ33/$AF$10 -> 10.186318 | BC33: =AY33*(1+Inflation) -> 2772.7588 | BD33: =BG33*$B$2 -> 402071.7 | BE33: =BD33/BD$22 -> 0.060266161 | BF33: =BD33/$AF$10 -> 10.402083 | BG33: =BC33*(1+Inflation) -> 2831.4908 | BH33: =BK33*$B$2 -> 410588.31 | BI33: =BH33/BH$22 -> 0.06134438 | BJ33: =BH33/$AF$10 -> 10.622418 | BK33: =BG33*(1+Inflation) -> 2891.467 | BL33: =BO33*$B$2 -> 419285.32 | BM33: =BL33/BL$22 -> 0.062270046 | BN33: =BL33/$AF$10 -> 10.84742 | BO33: =BK33*(1+Inflation) -> 2952.7135 | BP33: =BS33*$B$2 -> 428166.54 | BQ33: =BP33/BP$22 -> 0.063208923 | BR33: =BP33/$AF$10 -> 11.077188 | BS33: =BO33*(1+Inflation) -> 3015.2573
A34: Repairs and Maintenance | B34: 271600 | C34: =B34/$B$22 -> 0.047722448 | D34: 288047 | E34: =D34/$D$22 -> 0.058221224 | F34: 324940 | G34: =F34/$F$22 -> 0.051434903 | H34: 340360 | I34: =H34/$H$22 -> 0.051206133 | J34: 300000 | K34: =J34/$J$22 -> 0.045785869 | L34: 348000 | M34: =L34/$L$22 -> 0.051826126 | N34: 322000 | O34: =N34/$N$22 -> 0.047556455 | P34: 322000 | Q34: =P34/$P$22 -> 0.20094388 | R34: 322000 | S34: =R34/$R$22 -> 0.16736155 | T34: 322000 | U34: =T34/$T$22 -> 0.076352682 | V34: 595000 | W34: =V34/$V$22 -> 0.10782042 | X34: 400000 | Y34: =X34/$X$22 -> 0.063558093 | Z34: =X34/$X$10 -> 10.358616 | AA34: =X34/$B$2 -> 2816.9014 | AB34: =AE34*$B$2 -> 408472.73 | AC34: =Y34 -> 0.063558093 | AD34: =AB34/$AB$10 -> 10.587406 | AE34: =AA34*(1+Inflation) -> 2876.5685 | AF34: =AI34*$B$2 -> 417124.92 | AG34: =AF34/AF$22 -> 0.065452151 | AH34: =AF34/$AF$10 -> 10.791528 | AI34: =AE34*(1+Inflation) -> 2937.4995 | AJ34: =AM34*$B$2 -> 425960.39 | AK34: =AJ34/AJ$22 -> 0.066321919 | AL34: =AJ34/$AF$10 -> 11.020112 | AM34: =AI34*(1+Inflation) -> 2999.721 | AN34: =AQ34*$B$2 -> 434983 | AO34: =AN34/AN$22 -> 0.067017818 | AP34: =AN34/$AF$10 -> 11.253538 | AQ34: =AM34*(1+Inflation) -> 3063.2606 | AR34: =AU34*$B$2 -> 444196.73 | AS34: =AR34/AR$22 -> 0.068092724 | AT34: =AR34/$AF$10 -> 11.491908 | AU34: =AQ34*(1+Inflation) -> 3128.146 | AV34: =AY34*$B$2 -> 453605.63 | AW34: =AV34/AV$22 -> 0.068993988 | AX34: =AV34/$AF$10 -> 11.735328 | AY34: =AU34*(1+Inflation) -> 3194.4058 | AZ34: =BC34*$B$2 -> 463213.82 | BA34: =AZ34/AZ$22 -> 0.070037619 | BB34: =AZ34/$AF$10 -> 11.983903 | BC34: =AY34*(1+Inflation) -> 3262.0691 | BD34: =BG34*$B$2 -> 473025.53 | BE34: =BD34/BD$22 -> 0.070901366 | BF34: =BD34/$AF$10 -> 12.237744 | BG34: =BC34*(1+Inflation) -> 3331.1657 | BH34: =BK34*$B$2 -> 483045.07 | BI34: =BH34/BH$22 -> 0.072169859 | BJ34: =BH34/$AF$10 -> 12.496962 | BK34: =BG34*(1+Inflation) -> 3401.7259 | BL34: =BO34*$B$2 -> 493276.84 | BM34: =BL34/BL$22 -> 0.073258878 | BN34: =BL34/$AF$10 -> 12.76167 | BO34: =BK34*(1+Inflation) -> 3473.7806 | BP34: =BS34*$B$2 -> 503725.34 | BQ34: =BP34/BP$22 -> 0.074363439 | BR34: =BP34/$AF$10 -> 13.031986 | BS34: =BO34*(1+Inflation) -> 3547.3616
A35: Total Undistributed Undistributed Expenses | B35: =SUM(B31:B34) -> 1618800 | C35: =B35/$B$22 -> 0.28443704 | D35: =SUM(D31:D34) -> 1604777 | E35: =D35/$D$22 -> 0.32436401 | F35: =SUM(F31:F34) -> 1840000 | G35: =F35/$F$22 -> 0.29125445 | H35: =SUM(H31:H34) -> 1882400 | I35: =H35/$H$22 -> 0.28320139 | J35: =SUM(J31:J34) -> 1731000 | K35: =J35/$J$22 -> 0.26418446 | L35: =SUM(L31:L34) -> 1924000 | M35: =L35/$L$22 -> 0.28653295 | N35: =SUM(N31:N34) -> 1476000 | O35: =N35/$N$22 -> 0.2179917 | P35: =SUM(P31:P34) -> 1476000 | Q35: =P35/$P$22 -> 0.92109681 | R35: =SUM(R31:R34) -> 1476000 | S35: =R35/$R$22 -> 0.76716041 | T35: =SUM(T31:T34) -> 1476000 | U35: =T35/$T$22 -> 0.34998931 | V35: =SUM(V31:V34) -> 1990000 | W35: =V35/$V$22 -> 0.36060948 | X35: =SUM(X31:X34) -> 1350000 | Y35: =X35/$X$22 -> 0.21450856 | Z35: =X35/$X$10 -> 34.96033 | AA35: =X35/$B$2 -> 9507.0423 | AB35: =SUM(AB31:AB34) -> 1378595.5 | AC35: =AB35/$AB$22 -> 0.21800211 | AD35: =AB35/$AB$10 -> 35.732497 | AE35: =AB35/$B$2 -> 9708.4187 | AF35: =SUM(AF31:AF34) -> 1407796.6 | AG35: =AF35/$AF$22 -> 0.22090101 | AH35: =AF35/$AF$10 -> 36.421406 | AI35: =AF35/$B$2 -> 9914.0607 | AJ35: =SUM(AJ31:AJ34) -> 1437616.3 | AK35: =AJ35/$AJ$22 -> 0.22383648 | AL35: =AJ35/$AJ$10 -> 37.123726 | AM35: =AJ35/$B$2 -> 10124.058 | AN35: =SUM(AN31:AN34) -> 1468067.6 | AO35: =AN35/$AN$22 -> 0.22618513 | AP35: =AN35/$AN$10 -> 37.735648 | AQ35: =AN35/$B$2 -> 10338.504 | AR35: =SUM(AR31:AR34) -> 1499164 | AS35: =AR35/$AR$22 -> 0.22981294 | AT35: =AR35/$AR$10 -> 38.568664 | AU35: =AR35/$B$2 -> 10557.493 | AV35: =SUM(AV31:AV34) -> 1530919 | AW35: =AV35/$AV$22 -> 0.23285471 | AX35: =AV35/$AV$10 -> 39.311789 | AY35: =AV35/$B$2 -> 10781.12 | AZ35: =SUM(AZ31:AZ34) -> 1563346.6 | BA35: =AZ35/$AZ$22 -> 0.23637696 | BB35: =AZ35/$AZ$10 -> 40.144484 | BC35: =AZ35/$B$2 -> 11009.483 | BD35: =SUM(BD31:BD34) -> 1596461.2 | BE35: =BD35/$BD$22 -> 0.23929211 | BF35: =BD35/$BD$10 -> 40.882488 | BG35: =BD35/$B$2 -> 11242.684 | BH35: =SUM(BH31:BH34) -> 1630277.1 | BI35: =BH35/$BH$22 -> 0.24357328 | BJ35: =BH35/$BH$10 -> 41.863162 | BK35: =BH35/$B$2 -> 11480.825 | BL35: =SUM(BL31:BL34) -> 1664809.3 | BM35: =BL35/$BL$22 -> 0.24724871 | BN35: =BL35/$BL$10 -> 42.7499 | BO35: =BL35/$B$2 -> 11724.009 | BP35: =SUM(BP31:BP34) -> 1700073 | BQ35: =BP35/$BL$22 -> 0.25248589 | BR35: =BP35/$BL$10 -> 43.65542 | BS35: =BP35/$B$2 -> 11972.345
A36: Gross Operating Profit (GOP) | B36: =B29-B35 -> 1295142.2 | C36: =B36/$B$22 -> 0.22756758 | D36: =D29-D35 -> 750057.04 | E36: =D36/$D$22 -> 0.15160456 | F36: =F29-F35 -> 1483224 | G36: =F36/$F$22 -> 0.23478021 | H36: =H29-H35 -> 1747850.6 | I36: =H36/$H$22 -> 0.26295883 | J36: =J29-J35 -> 1865667.1 | K36: =J36/$J$22 -> 0.28473729 | L36: =L29-L35 -> 2005560 | M36: =L36/$L$22 -> 0.29867933 | N36: =N29-N35 -> 2430500 | O36: =N36/$N$22 -> 0.35896262 | P36: =P29-P35 -> -646280.56 | Q36: =P36/$P$22 -> -0.40331095 | R36: =R29-R35 -> -458361.81 | S36: =R36/$R$22 -> -0.23823648 | T36: =T29-T35 -> 795005.18 | U36: =T36/$T$22 -> 0.18851173 | V36: =V29-V35 -> 926460 | W36: =V36/$V$22 -> 0.16788455 | X36: =X29-X35 -> 1851065 | Y36: =X36/$X$22 -> 0.2941254 | Z36: =X36/$X$10 -> 47.93618 | AA36: =X36/$B$2 -> 13035.669 | AB36: =AB29-AB35 -> 1843250.6 | AC36: =AB36/$AB$22 -> 0.29147964 | AD36: =AB36/$AB$10 -> 47.776122 | AE36: =AB36/$B$2 -> 12980.638 | AF36: =AF29-AF35 -> 1844673.3 | AG36: =AF36/$AF$22 -> 0.28945246 | AH36: =AF36/$AF$10 -> 47.723936 | AI36: =AF36/$B$2 -> 12990.657 | AJ36: =AJ29-AJ35 -> 1845766.9 | AK36: =AJ36/$AJ$22 -> 0.28738542 | AL36: =AJ36/$AJ$10 -> 47.663445 | AM36: =AJ36/$B$2 -> 12998.359 | AN36: =AN29-AN35 -> 1855662.5 | AO36: =AN36/$AN$22 -> 0.28590186 | AP36: =AN36/$AN$10 -> 47.698501 | AQ36: =AN36/$B$2 -> 13068.046 | AR36: =AR29-AR35 -> 1847011.1 | AS36: =AR36/$AR$22 -> 0.28313584 | AT36: =AR36/$AR$10 -> 47.517651 | AU36: =AR36/$B$2 -> 13007.12 | AV36: =AV29-AV35 -> 1847141.4 | AW36: =AV36/$AV$22 -> 0.28095253 | AX36: =AV36/$AV$10 -> 47.431923 | AY36: =AV36/$B$2 -> 13008.038 | AZ36: =AZ29-AZ35 -> 1840520 | BA36: =AZ36/$AZ$22 -> 0.2782854 | BB36: =AZ36/$AZ$10 -> 47.261897 | BC36: =AZ36/$B$2 -> 12961.409 | BD36: =BD29-BD35 -> 1842842.8 | BE36: =BD36/$BD$22 -> 0.27622203 | BF36: =BD36/$BD$10 -> 47.191877 | BG36: =BD36/$B$2 -> 12977.766 | BH36: =BH29-BH35 -> 1825824.8 | BI36: =BH36/$BH$22 -> 0.27278928 | BJ36: =BH36/$BH$10 -> 46.884544 | BK36: =BH36/$B$2 -> 12857.921 | BL36: =BL29-BL35 -> 1817724.8 | BM36: =BL36/$BL$22 -> 0.26995891 | BN36: =BL36/$BL$10 -> 46.676548 | BO36: =BL36/$B$2 -> 12800.879 | BP36: =BP29-BP35 -> 1809105.4 | BQ36: =BP36/$BL$22 -> 0.2686788 | BR36: =BP36/$BL$10 -> 46.455213 | BS36: =BP36/$B$2 -> 12740.179
A37: Management Fee | B37: 0 | C37: =B37/$B$22 -> 0 | D37: 0 | E37: =D37/$D$22 -> 0 | F37: 0 | G37: =F37/$F$22 -> 0 | H37: 0 | I37: =H37/$H$22 -> 0 | J37: 0 | K37: =J37/$J$22 -> 0 | L37: 0 | M37: =L37/$L$22 -> 0 | N37: 0 | O37: =N37/$N$22 -> 0 | P37: 0 | Q37: =P37/$P$22 -> 0 | R37: 0 | S37: =R37/$R$22 -> 0 | T37: 0 | U37: =T37/$T$22 -> 0 | V37: 0 | W37: =V37/$V$22 -> 0 | X37: 0 | Y37: =X37/$X$22 -> 0 | Z37: =X37/$X$10 -> 0 | AA37: =X37/$B$2 -> 0 | AB37: 0 | AC37: =AB37/$AB$22 -> 0 | AD37: =AB37/$AB$10 -> 0 | AE37: =AB37/$B$2 -> 0 | AF37: 0 | AG37: =AF37/$AF$22 -> 0 | AH37: =AF37/$AF$10 -> 0 | AI37: =AF37/$B$2 -> 0 | AJ37: 0 | AK37: =AJ37/$AJ$22 -> 0 | AL37: =AJ37/$AJ$10 -> 0 | AM37: =AJ37/$B$2 -> 0 | AN37: 0 | AO37: =AN37/$AN$22 -> 0 | AP37: =AN37/$AN$10 -> 0 | AQ37: =AN37/$B$2 -> 0 | AR37: 0 | AS37: =AR37/$AR$22 -> 0 | AT37: =AR37/$AR$10 -> 0 | AU37: =AR37/$B$2 -> 0 | AV37: 0 | AW37: =AV37/$AV$22 -> 0 | AX37: =AV37/$AV$10 -> 0 | AY37: =AV37/$B$2 -> 0 | AZ37: 0 | BA37: =AZ37/$AZ$22 -> 0 | BB37: =AZ37/$AZ$10 -> 0 | BC37: =AZ37/$B$2 -> 0 | BD37: 0 | BE37: =BD37/$BD$22 -> 0 | BF37: =BD37/$BD$10 -> 0 | BG37: =BD37/$B$2 -> 0 | BH37: 0 | BI37: =BH37/$BH$22 -> 0 | BJ37: =BH37/$BH$10 -> 0 | BK37: =BH37/$B$2 -> 0 | BL37: 0 | BM37: =BL37/$BL$22 -> 0 | BN37: =BL37/$BL$10 -> 0 | BO37: =BL37/$B$2 -> 0 | BP37: 0 | BQ37: =BP37/$BL$22 -> 0 | BR37: =BP37/$BL$10 -> 0 | BS37: =BP37/$B$2 -> 0
A38: Income Before Non-Operating Income and Expenses | B38: =B36-B37 -> 1295142.2 | C38: =B38/$B$22 -> 0.22756758 | D38: =D36-D37 -> 750057.04 | E38: =D38/$D$22 -> 0.15160456 | F38: =F36-F37 -> 1483224 | G38: =F38/$F$22 -> 0.23478021 | H38: =H36-H37 -> 1747850.6 | I38: =H38/$H$22 -> 0.26295883 | J38: =J36-J37 -> 1865667.1 | K38: =J38/$J$22 -> 0.28473729 | L38: =L36-L37 -> 2005560 | M38: =L38/$L$22 -> 0.29867933 | N38: =N36-N37 -> 2430500 | O38: =N38/$N$22 -> 0.35896262 | P38: =P36-P37 -> -646280.56 | Q38: =P38/$P$22 -> -0.40331095 | R38: =R36-R37 -> -458361.81 | S38: =R38/$R$22 -> -0.23823648 | T38: =T36-T37 -> 795005.18 | U38: =T38/$T$22 -> 0.18851173 | V38: =V36-V37 -> 926460 | W38: =V38/$V$22 -> 0.16788455 | X38: =X36-X37 -> 1851065 | Y38: =X38/$X$22 -> 0.2941254 | Z38: =X38/$X$10 -> 47.93618 | AA38: =X38/$B$2 -> 13035.669 | AB38: =AB36-AB37 -> 1843250.6 | AC38: =AB38/$AB$22 -> 0.29147964 | AD38: =AB38/$AB$10 -> 47.776122 | AE38: =AB38/$B$2 -> 12980.638 | AF38: =AF36-AF37 -> 1844673.3 | AG38: =AF38/$AF$22 -> 0.28945246 | AH38: =AF38/$AF$10 -> 47.723936 | AI38: =AF38/$B$2 -> 12990.657 | AJ38: =AJ36-AJ37 -> 1845766.9 | AK38: =AJ38/$AJ$22 -> 0.28738542 | AL38: =AJ38/$AJ$10 -> 47.663445 | AM38: =AJ38/$B$2 -> 12998.359 | AN38: =AN36-AN37 -> 1855662.5 | AO38: =AN38/$AN$22 -> 0.28590186 | AP38: =AN38/$AN$10 -> 47.698501 | AQ38: =AN38/$B$2 -> 13068.046 | AR38: =AR36-AR37 -> 1847011.1 | AS38: =AR38/$AR$22 -> 0.28313584 | AT38: =AR38/$AR$10 -> 47.517651 | AU38: =AR38/$B$2 -> 13007.12 | AV38: =AV36-AV37 -> 1847141.4 | AW38: =AV38/$AV$22 -> 0.28095253 | AX38: =AV38/$AV$10 -> 47.431923 | AY38: =AV38/$B$2 -> 13008.038 | AZ38: =AZ36-AZ37 -> 1840520 | BA38: =AZ38/$AZ$22 -> 0.2782854 | BB38: =AZ38/$AZ$10 -> 47.261897 | BC38: =AZ38/$B$2 -> 12961.409 | BD38: =BD36-BD37 -> 1842842.8 | BE38: =BD38/$BD$22 -> 0.27622203 | BF38: =BD38/$BD$10 -> 47.191877 | BG38: =BD38/$B$2 -> 12977.766 | BH38: =BH36-BH37 -> 1825824.8 | BI38: =BH38/$BH$22 -> 0.27278928 | BJ38: =BH38/$BH$10 -> 46.884544 | BK38: =BH38/$B$2 -> 12857.921 | BL38: =BL36-BL37 -> 1817724.8 | BM38: =BL38/$BL$22 -> 0.26995891 | BN38: =BL38/$BL$10 -> 46.676548 | BO38: =BL38/$B$2 -> 12800.879 | BP38: =BP36-BP37 -> 1809105.4 | BQ38: =BP38/$BL$22 -> 0.2686788 | BR38: =BP38/$BL$10 -> 46.455213 | BS38: =BP38/$B$2 -> 12740.179
A39: Non-Operating Income and Expenses
A40: Income Minimum lease rental | B40: 1400000 | C40: =B40/$B$22 -> 0.245992 | D40: 1418200 | E40: =D40/$D$22 -> 0.28665231 | F40: 1436636.6 | G40: =F40/$F$22 -> 0.22740587 | H40: 1459000 | I40: =H40/$H$22 -> 0.21950214 | J40: 1376000 | K40: =J40/$J$22 -> 0.21000452 | L40: 1443000 | M40: =L40/$L$22 -> 0.21489971 | N40: 1460316 | O40: =N40/$N$22 -> 0.21567532 | P40: 1350000 | Q40: =P40/$P$22 -> 0.8424666 | R40: 1350000 | S40: =R40/$R$22 -> 0.70167111 | T40: 1350000 | U40: =T40/$T$22 -> 0.32011218
A41: Income Variable Lease Rental (21.5%) | B41: 1223617 | C41: =B41/$B$22 -> 0.215 | D41: 1063703.3 | E41: =D41/$D$22 -> 0.215 | F41: 1358262.5 | G41: =F41/$F$22 -> 0.215 | H41: 1429074.9 | I41: =H41/$H$22 -> 0.215 | J41: 1408731.6 | K41: =J41/$J$22 -> 0.215 | L41: 1443673.4 | M41: =L41/$L$22 -> 0.215 | N41: 1455743.5 | O41: =N41/$N$22 -> 0.215 | P41: 344524.04 | Q41: =P41/$P$22 -> 0.215 | R41: 413655.34 | S41: =R41/$R$22 -> 0.215 | T41: 906713.4 | U41: =T41/$T$22 -> 0.215
A42: Total Income | B42: =SUM(B40:B41) -> 2623617 | C42: =B42/$B$22 -> 0.460992 | D42: =SUM(D40:D41) -> 2481903.3 | E42: =D42/$D$22 -> 0.50165231 | F42: =SUM(F40:F41) -> 2794899.1 | G42: =F42/$F$22 -> 0.44240587 | H42: =SUM(H40:H41) -> 2888074.9 | I42: =H42/$H$22 -> 0.43450214 | J42: =SUM(J40:J41) -> 2784731.6 | K42: =J42/$J$22 -> 0.42500452 | L42: =SUM(L40:L41) -> 2886673.4 | M42: =L42/$L$22 -> 0.42989971 | N42: =SUM(N40:N41) -> 2916059.5 | O42: =N42/$N$22 -> 0.43067532 | P42: =SUM(P40:P41) -> 1694524 | Q42: =P42/$P$22 -> 1.0574666 | R42: =SUM(R40:R41) -> 1763655.3 | S42: =R42/$R$22 -> 0.91667111 | T42: =SUM(T40:T41) -> 2256713.4 | U42: =T42/$T$22 -> 0.53511218
A43: Rent
A44: Proprety tax and Inssurance | B44: 41000 | C44: =B44/$B$22 -> 0.0072040514 | D44: 41000 | E44: =D44/$D$22 -> 0.0082870857 | F44: 41000 | G44: =F44/$F$22 -> 0.006489909 | H44: 41000 | I44: =H44/$H$22 -> 0.0061683261 | J44: 41000 | K44: =J44/$J$22 -> 0.006257402 | L44: 43000 | M44: =L44/$L$22 -> 0.006403803 | N44: 43000 | O44: =N44/$N$22 -> 0.0063507067 | P44: 43000 | Q44: =P44/$P$22 -> 0.026834121 | R44: 43000 | S44: =R44/$R$22 -> 0.022349524 | T44: 43000 | U44: =T44/$T$22 -> 0.010196166 | V44: 43000 | W44: =V44/$V$22 -> 0.0077920642 | X44: 45000 | Y44: =X44/$X$22 -> 0.0071502855 | Z44: =X44/$X$10 -> 1.1653443 | AA44: =X44/$B$2 -> 316.90141 | AB44: =AA44*$B$2 -> 45000 | AC44: =AB44/$AB$22 -> 0.007116007 | AD44: =AB44/$AB$10 -> 1.1663772 | AE44: =AB44/$B$2 -> 316.90141 | AF44: =AE44*$B$2 -> 45000 | AG44: =AF44/$AF$22 -> 0.0070610665 | AH44: =AF44/$AF$10 -> 1.1642046 | AI44: =AF44/$B$2 -> 316.90141 | AJ44: =AI44*$B$2 -> 45000 | AK44: =AJ44/$AJ$22 -> 0.007006488 | AL44: =AJ44/$AJ$10 -> 1.16204 | AM44: =AJ44/$B$2 -> 316.90141 | AN44: =AM44*$B$2 -> 45000 | AO44: =AN44/$AN$22 -> 0.0069331486 | AP44: =AN44/$AN$10 -> 1.1566934 | AQ44: =AN44/$B$2 -> 316.90141 | AR44: =AQ44*$B$2 -> 45000 | AS44: =AR44/$AR$22 -> 0.006898233 | AT44: =AR44/$AR$10 -> 1.1577052 | AU44: =AR44/$B$2 -> 316.90141 | AV44: =AU44*$B$2 -> 45000 | AW44: =AV44/$AV$22 -> 0.0068445567 | AX44: =AV44/$AV$10 -> 1.155535 | AY44: =AV44/$B$2 -> 316.90141 | AZ44: =AY44*$B$2 -> 45000 | BA44: =AZ44/$AZ$22 -> 0.0068039698 | BB44: =AZ44/$AZ$10 -> 1.155535 | BC44: =AZ44/$B$2 -> 316.90141 | BD44: =BC44*$B$2 -> 45000 | BE44: =BD44/$BD$22 -> 0.006745009 | BF44: =BD44/$BD$10 -> 1.1523688 | BG44: =BD44/$B$2 -> 316.90141 | BH44: =BG44*$B$2 -> 45000 | BI44: =BH44/$BH$22 -> 0.0067232726 | BJ44: =BH44/$BH$10 -> 1.155535 | BK44: =BH44/$B$2 -> 316.90141 | BL44: =BK44*$B$2 -> 45000 | BM44: =BL44/$BL$22 -> 0.0066831629 | BN44: =BL44/$BL$10 -> 1.155535 | BO44: =BL44/$B$2 -> 316.90141 | BP44: =BO44*$B$2 -> 45000 | BQ44: =BP44/$BL$22 -> 0.0066831629 | BR44: =BP44/$BL$10 -> 1.155535 | BS44: =BP44/$B$2 -> 316.90141
A45: Insurrance
A46: Other
A47: Total Non-Operating Income and Expenses | B47: =B42-B44 -> 2582617 | C47: =B47/$B$22 -> 0.45378795 | D47: =D42-D44 -> 2440903.3 | E47: =D47/$D$22 -> 0.49336523 | F47: =F42-F44 -> 2753899.1 | G47: =F47/$F$22 -> 0.43591596 | H47: =H42-H44 -> 2847074.9 | I47: =H47/$H$22 -> 0.42833381 | J47: =J42-J44 -> 2743731.6 | K47: =J47/$J$22 -> 0.41874712 | L47: =L42-L44 -> 2843673.4 | M47: =L47/$L$22 -> 0.42349591 | N47: =N42-N44 -> 2873059.5 | O47: =N47/$N$22 -> 0.42432461 | P47: =P42-P44 -> 1651524 | Q47: =P47/$P$22 -> 1.0306325 | R47: =R42-R44 -> 1720655.3 | S47: =R47/$R$22 -> 0.89432159 | T47: =T42-T44 -> 2213713.4 | U47: =T47/$T$22 -> 0.52491601 | V47: =V42-V44 -> -43000 | W47: =V47/$V$22 -> -0.0077920642 | X47: =X42-X44 -> -45000 | Y47: =X47/$X$22 -> -0.0071502855 | Z47: =X47/$X$10 -> -1.1653443 | AA47: =X47/$B$2 -> -316.90141 | AB47: =AB42-AB44 -> -45000 | AC47: =AB47/$AB$22 -> -0.007116007 | AD47: =AB47/$AB$10 -> -1.1663772 | AE47: =AB47/$B$2 -> -316.90141 | AF47: =AF42-AF44 -> -45000 | AG47: =AF47/$AF$22 -> -0.0070610665 | AH47: =AF47/$AF$10 -> -1.1642046 | AI47: =AF47/$B$2 -> -316.90141 | AJ47: =AJ42-AJ44 -> -45000 | AK47: =AJ47/$AJ$22 -> -0.007006488 | AL47: =AJ47/$AJ$10 -> -1.16204 | AM47: =AJ47/$B$2 -> -316.90141 | AN47: =AN42-AN44 -> -45000 | AO47: =AN47/$AN$22 -> -0.0069331486 | AP47: =AN47/$AN$10 -> -1.1566934 | AQ47: =AN47/$B$2 -> -316.90141 | AR47: =AR42-AR44 -> -45000 | AS47: =AR47/$AR$22 -> -0.006898233 | AT47: =AR47/$AR$10 -> -1.1577052 | AU47: =AR47/$B$2 -> -316.90141 | AV47: =AV42-AV44 -> -45000 | AW47: =AV47/$AV$22 -> -0.0068445567 | AX47: =AV47/$AV$10 -> -1.155535 | AY47: =AV47/$B$2 -> -316.90141 | AZ47: =AZ42-AZ44 -> -45000 | BA47: =AZ47/$AZ$22 -> -0.0068039698 | BB47: =AZ47/$AZ$10 -> -1.155535 | BC47: =AZ47/$B$2 -> -316.90141 | BD47: =BD42-BD44 -> -45000 | BE47: =BD47/$BD$22 -> -0.006745009 | BF47: =BD47/$BD$10 -> -1.1523688 | BG47: =BD47/$B$2 -> -316.90141 | BH47: =BH42-BH44 -> -45000 | BI47: =BH47/$BH$22 -> -0.0067232726 | BJ47: =BH47/$BH$10 -> -1.155535 | BK47: =BH47/$B$2 -> -316.90141 | BL47: =BL42-BL44 -> -45000 | BM47: =BL47/$BL$22 -> -0.0066831629 | BN47: =BL47/$BL$10 -> -1.155535 | BO47: =BL47/$B$2 -> -316.90141 | BP47: =BP42-BP44 -> -45000 | BQ47: =BP47/$BL$22 -> -0.0066831629 | BR47: =BP47/$BL$10 -> -1.155535 | BS47: =BP47/$B$2 -> -316.90141
A48: Earnings Before Interest, Taxes, Depreciation, and Amortization (EBITDA) | B48: =B38+B47 -> 3877759.2 | C48: =B48/$B$22 -> 0.68135553 | D48: =D38+D47 -> 3190960.3 | E48: =D48/$D$22 -> 0.64496979 | F48: =F38+F47 -> 4237123.1 | G48: =F48/$F$22 -> 0.67069617 | H48: =H38+H47 -> 4594925.5 | I48: =H48/$H$22 -> 0.69129265 | J48: =J38+J47 -> 4609398.7 | K48: =J48/$J$22 -> 0.70348441 | L48: =L38+L47 -> 4849233.4 | M48: =L48/$L$22 -> 0.72217524 | N48: =N38+N47 -> 5303559.5 | O48: =N48/$N$22 -> 0.78328723 | P48: =P38+P47 -> 1005243.5 | Q48: =P48/$P$22 -> 0.62732152 | R48: =R38+R47 -> 1262293.5 | S48: =R48/$R$22 -> 0.65608511 | T48: =T38+T47 -> 3008718.6 | U48: =T48/$T$22 -> 0.71342774 | V48: =V38+V47 -> 883460 | W48: =V48/$V$22 -> 0.16009249 | X48: =X38+X47 -> 1806065 | Y48: =X48/$X$22 -> 0.28697512 | Z48: =X48/$X$10 -> 46.770836 | AA48: =X48/$B$2 -> 12718.768 | AB48: =AB38+AB47 -> 1798250.6 | AC48: =AB48/$AB$22 -> 0.28436364 | AD48: =AB48/$AB$10 -> 46.609745 | AE48: =AB48/$B$2 -> 12663.736 | AF48: =AF38+AF47 -> 1799673.3 | AG48: =AF48/$AF$22 -> 0.28239139 | AH48: =AF48/$AF$10 -> 46.559731 | AI48: =AF48/$B$2 -> 12673.756 | AJ48: =AJ38+AJ47 -> 1800766.9 | AK48: =AJ48/$AJ$22 -> 0.28037893 | AL48: =AJ48/$AJ$10 -> 46.501405 | AM48: =AJ48/$B$2 -> 12681.457 | AN48: =AN38+AN47 -> 1810662.5 | AO48: =AN48/$AN$22 -> 0.27896871 | AP48: =AN48/$AN$10 -> 46.541808 | AQ48: =AN48/$B$2 -> 12751.144 | AR48: =AR38+AR47 -> 1802011.1 | AS48: =AR48/$AR$22 -> 0.27623761 | AT48: =AR48/$AR$10 -> 46.359946 | AU48: =AR48/$B$2 -> 12690.219 | AV48: =AV38+AV47 -> 1802141.4 | AW48: =AV48/$AV$22 -> 0.27410797 | AX48: =AV48/$AV$10 -> 46.276388 | AY48: =AV48/$B$2 -> 12691.136 | AZ48: =AZ38+AZ47 -> 1795520 | BA48: =AZ48/$AZ$22 -> 0.27148143 | BB48: =AZ48/$AZ$10 -> 46.106362 | BC48: =AZ48/$B$2 -> 12644.507 | BD48: =BD38+BD47 -> 1797842.8 | BE48: =BD48/$BD$22 -> 0.26947702 | BF48: =BD48/$BD$10 -> 46.039508 | BG48: =BD48/$B$2 -> 12660.865 | BH48: =BH38+BH47 -> 1780824.8 | BI48: =BH48/$BH$22 -> 0.26606601 | BJ48: =BH48/$BH$10 -> 45.729009 | BK48: =BH48/$B$2 -> 12541.02 | BL48: =BL38+BL47 -> 1772724.8 | BM48: =BL48/$BL$22 -> 0.26327575 | BN48: =BL48/$BL$10 -> 45.521013 | BO48: =BL48/$B$2 -> 12483.978 | BP48: =BP38+BP47 -> 1764105.4 | BQ48: =BP48/$BL$22 -> 0.26199563 | BR48: =BP48/$BL$10 -> 45.299678 | BS48: =BP48/$B$2 -> 12423.277
A49: FF&E Reserve (4%) | B49: 227649.68 | C49: =B49/$B$22 -> 0.04 | D49: 197898.28 | E49: =D49/$D$22 -> 0.04 | F49: 252700 | G49: =F49/$F$22 -> 0.04 | H49: 265874.4 | I49: =H49/$H$22 -> 0.04 | J49: 262089.6 | K49: =J49/$J$22 -> 0.04 | L49: 268590.4 | M49: =L49/$L$22 -> 0.04 | N49: 270836 | O49: =N49/$N$22 -> 0.04 | P49: 64097.497 | Q49: =P49/$P$22 -> 0.04 | R49: 76959.133 | S49: =R49/$R$22 -> 0.04 | T49: 168690.87 | U49: =T49/$T$22 -> 0.04 | V49: 220737.4 | W49: =V49/$V$22 -> 0.04 | X49: 251738.2 | Y49: =X49/$X$22 -> 0.04 | Z49: =X49/$X$10 -> 6.5191486 | AA49: =X49/$B$2 -> 1772.8042 | AB49: =Y49*AB22 -> 252950.85 | AC49: =AB49/$AB$22 -> 0.04 | AD49: =AB49/$AB$10 -> 6.556358 | AE49: =AB49/$B$2 -> 1781.344 | AF49: =AC49*AF22 -> 254919 | AG49: =AF49/$AF$22 -> 0.04 | AH49: =AF49/$AF$10 -> 6.5950637 | AI49: =AF49/$B$2 -> 1795.2042 | AJ49: =AG49*AJ22 -> 256904.74 | AK49: =AJ49/$AJ$22 -> 0.04 | AL49: =AJ49/$AJ$10 -> 6.6340799 | AM49: =AJ49/$B$2 -> 1809.1883 | AN49: =AK49*AN22 -> 259622.3 | AO49: =AN49/$AN$22 -> 0.04 | AP49: =AN49/$AN$10 -> 6.673409 | AQ49: =AN49/$B$2 -> 1828.3261 | AR49: =AO49*AR22 -> 260936.39 | AS49: =AR49/$AR$22 -> 0.04 | AT49: =AR49/$AR$10 -> 6.7130535 | AU49: =AR49/$B$2 -> 1837.5802 | AV49: =AS49*AV22 -> 262982.7 | AW49: =AV49/$AV$22 -> 0.04 | AX49: =AV49/$AV$10 -> 6.7530159 | AY49: =AV49/$B$2 -> 1851.9908 | AZ49: =AW49*AZ22 -> 264551.44 | BA49: =AZ49/$AZ$22 -> 0.04 | BB49: =AZ49/$AZ$10 -> 6.7932989 | BC49: =AZ49/$B$2 -> 1863.0383 | BD49: =BA49*BD22 -> 266863.99 | BE49: =BD49/$BD$22 -> 0.04 | BF49: =BD49/$BD$10 -> 6.8339049 | BG49: =BD49/$B$2 -> 1879.3239 | BH49: =BE49*BH22 -> 267726.76 | BI49: =BH49/$BH$22 -> 0.04 | BJ49: =BH49/$BH$10 -> 6.8748366 | BK49: =BH49/$B$2 -> 1885.3997 | BL49: =BI49*BL22 -> 269333.55 | BM49: =BL49/$BL$22 -> 0.04 | BN49: =BL49/$BL$10 -> 6.9160966 | BO49: =BL49/$B$2 -> 1896.7152 | BP49: =BM49*BP22 -> 270953.23 | BQ49: =BP49/$BL$22 -> 0.040240546 | BR49: =BP49/$BL$10 -> 6.9576876 | BS49: =BP49/$B$2 -> 1908.1213
A50: EBITDA after Remplacement Reserve | B50: =B48-B49 -> 3650109.5 | C50: =B50/$B$22 -> 0.64135553 | D50: =D48-D49 -> 2993062 | E50: =D50/$D$22 -> 0.60496979 | F50: =F48-F49 -> 3984423.1 | G50: =F50/$F$22 -> 0.63069617 | H50: =H48-H49 -> 4329051.1 | I50: =H50/$H$22 -> 0.65129265 | J50: =J48-J49 -> 4347309.1 | K50: =J50/$J$22 -> 0.66348441 | L50: =L48-L49 -> 4580643 | M50: =L50/$L$22 -> 0.68217524 | N50: =N48-N49 -> 5032723.5 | O50: =N50/$N$22 -> 0.74328723 | P50: =P48-P49 -> 941145.99 | Q50: =P50/$P$22 -> 0.58732152 | R50: =R48-R49 -> 1185334.4 | S50: =R50/$R$22 -> 0.61608511 | T50: =T48-T49 -> 2840027.7 | U50: =T50/$T$22 -> 0.67342774 | V50: =V48-V49 -> 662722.6 | W50: =V50/$V$22 -> 0.12009249 | X50: =X48-X49 -> 1554326.8 | Y50: =X50/$X$22 -> 0.24697512 | Z50: =X50/$X$10 -> 40.251687 | AA50: =X50/$B$2 -> 10945.963 | AB50: =AB48-AB49 -> 1545299.7 | AC50: =AB50/$AB$22 -> 0.24436364 | AD50: =AB50/$AB$10 -> 40.053387 | AE50: =AB50/$B$2 -> 10882.392 | AF50: =AF48-AF49 -> 1544754.3 | AG50: =AF50/$AF$22 -> 0.24239139 | AH50: =AF50/$AF$10 -> 39.964667 | AI50: =AF50/$B$2 -> 10878.551 | AJ50: =AJ48-AJ49 -> 1543862.2 | AK50: =AJ50/$AJ$22 -> 0.24037893 | AL50: =AJ50/$AJ$10 -> 39.867325 | AM50: =AJ50/$B$2 -> 10872.269 | AN50: =AN48-AN49 -> 1551040.2 | AO50: =AN50/$AN$22 -> 0.23896871 | AP50: =AN50/$AN$10 -> 39.868399 | AQ50: =AN50/$B$2 -> 10922.818 | AR50: =AR48-AR49 -> 1541074.7 | AS50: =AR50/$AR$22 -> 0.23623761 | AT50: =AR50/$AR$10 -> 39.646892 | AU50: =AR50/$B$2 -> 10852.639 | AV50: =AV48-AV49 -> 1539158.7 | AW50: =AV50/$AV$22 -> 0.23410797 | AX50: =AV50/$AV$10 -> 39.523372 | AY50: =AV50/$B$2 -> 10839.146 | AZ50: =AZ48-AZ49 -> 1530968.6 | BA50: =AZ50/$AZ$22 -> 0.23148143 | BB50: =AZ50/$AZ$10 -> 39.313063 | BC50: =AZ50/$B$2 -> 10781.469 | BD50: =BD48-BD49 -> 1530978.8 | BE50: =BD50/$BD$22 -> 0.22947702 | BF50: =BD50/$BD$10 -> 39.205603 | BG50: =BD50/$B$2 -> 10781.541 | BH50: =BH48-BH49 -> 1513098 | BI50: =BH50/$BH$22 -> 0.22606601 | BJ50: =BH50/$BH$10 -> 38.854173 | BK50: =BH50/$B$2 -> 10655.62 | BL50: =BL48-BL49 -> 1503391.3 | BM50: =BL50/$BL$22 -> 0.22327575 | BN50: =BL50/$BL$10 -> 38.604916 | BO50: =BL50/$B$2 -> 10587.262 | BP50: =BP48-BP49 -> 1493152.1 | BQ50: =BP50/$BL$22 -> 0.22175509 | BR50: =BP50/$BL$10 -> 38.34199 | BS50: =BP50/$B$2 -> 10515.156
A53: Market value
A54: https://hypofriend.de/en/mortgage-rates-germany/hesse/wiesbaden
A55: Discount rate | B55: ='PRELIMINARY ANALYSIS'!$F$42 -> 0.0695
A56: Adjusted Cap Rate | B56: ='PRELIMINARY ANALYSIS'!$F$50 -> 0.061479747
A57: Going out Cap Rate ( = +0.5%) | B57: =B56+0.5% -> 0.066479747
A58: Property Discount Rate | B58: =B57+B4 -> 0.0745
A59: Sales transaction cost | B59: 0.06
B60: -1 | C60: 0 | D60: 1 | E60: 2 | F60: 3 | G60: 4 | H60: 5 | I60: 6 | J60: 7 | K60: 8 | L60: 9 | M60: 10
A61: Year | B61: 2024 | C61: 2025 | D61: 2026 | E61: 2027 | F61: 2028 | G61: 2029 | H61: 2030 | I61: 2031 | J61: 2032 | K61: 2033 | L61: 2034 | M61: 2035
A62: EBITDA aRR | C62: =AB50 -> 1545299.7 | D62: =AF50 -> 1544754.3 | E62: =AJ50 -> 1543862.2 | F62: =AN50 -> 1551040.2 | G62: =AR50 -> 1541074.7 | H62: =AV50 -> 1539158.7 | I62: =AZ50 -> 1530968.6 | J62: =BD50 -> 1530978.8 | K62: =BH50 -> 1513098 | L62: =BL50 -> 1503391.3 | M62: =BP50 -> 1493152.1
A63: Exit value | M63: =M62/B57 -> 22460256
A64: Transaction cost | M64: =-M63*B59 -> -1347615.3
A65: Initial investment | B65: =-21000000 -> -21000000
A66: Total CF | B66: =SUM(B62:B65) -> -21000000 | C66: =SUM(C62:C65) -> 1545299.7 | D66: =SUM(D62:D65) -> 1544754.3 | E66: =SUM(E62:E65) -> 1543862.2 | F66: =SUM(F62:F65) -> 1551040.2 | G66: =SUM(G62:G65) -> 1541074.7 | H66: =SUM(H62:H65) -> 1539158.7 | I66: =SUM(I62:I65) -> 1530968.6 | ... M66: =SUM(M62:M65) -> 22605793
A68: Incremental Value | B68: =NPV(B55,C66:M66) -> 21613177
A69: Market Value | B69: =NPV(B58,C66:M66) -> 20828353
A70: Net Present Value | B70: =NPV(B55,C66:M66)+B66 -> 613176.62
A71: IRR | B71: =IRR(B66:M66) -> 0.073385144
A72: MIRR | B72: =MIRR(B66:M66,B55,B55) -> 0.072301935

Sheet 1-P&L Modified
A1: 1 - P&L Modified
A2: Hotel #rooms | B2: 142
A3: Expected future inflation | B3: ='PRELIMINARY ANALYSIS'!$K$23 -> 0.021181818
A4: ADR Growth Rate | B4: ='PRELIMINARY ANALYSIS'!$K$25 -> 0.0080202527
A5: Occupancy Growth Rate | B5: ='PRELIMINARY ANALYSIS'!$C$52 -> 0.0018682486 | P5: COVID | AZ5: Occupancy Stabilize form this year
A6: Year | B6: 2013 | D6: 2014 | F6: 2015 | H6: 2016 | J6: 2017 | L6: 2018 | N6: 2019 | P6: 2020 | R6: 2021 | T6: 2022 | V6: 2023 | X6: 2024 | AB6: 2025 | AF6: 2026 | AJ6: 2027 | AN6: 2028 | AR6: 2029 | AV6: 2030 | AZ6: 2031 | BD6: 2032 | BH6: 2033 | BL6: 2034 | BP6: 2035 | BT6: 2036
A7: Days | B7: 365 | D7: 365 | F7: 365 | H7: 366 | J7: 365 | L7: 365 | N7: 365 | P7: 366 | R7: 365 | T7: 365 | V7: 365 | X7: 366 | AB7: 365 | AF7: 365 | AJ7: 365 | AN7: 366 | AR7: 365 | AV7: 365 | AZ7: 365 | BD7: 366 | BH7: 365 | BL7: 365 | BP7: 365 | BT7: 366
A8: Rooms Available | B8: =$B$2*B7 -> 51830 | D8: =$B$2*D7 -> 51830 | F8: =$B$2*F7 -> 51830 | H8: =$B$2*H7 -> 51972 | J8: =$B$2*J7 -> 51830 | L8: =$B$2*L7 -> 51830 | N8: =$B$2*N7 -> 51830 | P8: =P7*$B$2 -> 51972 | R8: =R7*$B$2 -> 51830 | T8: =T7*$B$2 -> 51830 | V8: =V7*$B$2 -> 51830 | X8: =X7*$B$2 -> 51972 | AB8: =AB7*$B$2 -> 51830 | AF8: =B2*AF7-'1-CAPEX'!S15*(31+28)-'1-CAPEX'!T15*(31+31) -> 48728 | AJ8: =AJ7*$B$2-'1-CAPEX'!U15*(31+31) -> 49908 | AN8: =AN7*$B$2-'1-CAPEX'!V15*(31+29)-'1-CAPEX'!W15*(31+31) -> 48312 | AR8: =AR7*$B$2 -> 51830 | AV8: =AV7*$B$2 -> 51830 | AZ8: =AZ7*$B$2 -> 51830 | BD8: =BD7*$B$2 -> 51972 | BH8: =BH7*$B$2 -> 51830 | BL8: =BL7*$B$2 -> 51830 | BP8: =BP7*$B$2 -> 51830 | BT8: =BT7*$B$2 -> 51972
A9: Rooms Sold | B9: =B10*B8 -> 33406 | D9: =D10*D8 -> 28091.86 | F9: =F10*F8 -> 38561.52 | H9: =H10*H8 -> 40174.356 | J9: =J10*J8 -> 37576.75 | L9: =L10*L8 -> 38717.01 | N9: =N10*N8 -> 40220.08 | P9: =P10*P8 -> 11122.008 | R9: =R10*R8 -> 11765.41 | T9: =T10*T8 -> 23738.14 | V9: =V10*V8 -> 32963.88 | X9: =X10*X8 -> 38615.196 | AB9: =ROUNDDOWN(AB10*AB8,0) -> 38581 | AF9: =ROUNDDOWN(AF10*AF8,0) -> 36158 | AJ9: =ROUNDDOWN(AJ10*AJ8,0) -> 37011 | AN9: =ROUNDDOWN(AN10*AN8,0) -> 35894 | AR9: =ROUNDDOWN(AR10*AR8,0) -> 39735 | AV9: =ROUNDDOWN(AV10*AV8,0) -> 41399 | AZ9: =ROUNDDOWN(AZ10*AZ8,0) -> 41476 | BD9: =ROUNDDOWN(BD10*BD8,0) -> 41590 | BH9: =ROUNDDOWN(BH10*BH8,0) -> 41476 | BL9: =ROUNDDOWN(BL10*BL8,0) -> 41476 | BP9: =ROUNDDOWN(BP10*BP8,0) -> 41476 | BT9: =ROUNDDOWN(BT10*BT8,0) -> 41590
A10: Occupancy | B10: 0.64453019 | D10: 0.542 | F10: 0.744 | H10: 0.773 | J10: 0.725 | L10: 0.747 | N10: 0.776 | P10: 0.214 | R10: 0.227 | T10: 0.458 | V10: 0.636 | X10: 0.743 | AB10: =X10*(1+$B$5) -> 0.74438811 | AF10: =AB10*(1+$B$5+AG10) -> 0.74205687 | AG10: -0.005 | AJ10: =AF10*(1+$B$5+AK10) -> 0.74158807 | AK10: -0.0025 | AN10: =AJ10*(1+$B$5+AO10) -> 0.74297355 | AO10: 0 | AR10: =AN10*(1+$B$5+AS10) -> 0.76665081 | AS10: 0.03 | AV10: =AR10*(1+$B$5+AW10) -> 0.79874914 | AW10: 0.04 | AZ10: =AV10*(1+$B$5) -> 0.8002414 | BD10: =AZ10 -> 0.8002414 | BH10: =BD10 -> 0.8002414 | BL10: =BH10 -> 0.8002414 | BP10: =BL10 -> 0.8002414 | BT10: =BP10 -> 0.8002414
A11: ADR | B11: 112.49476 | D11: 116 | F11: 115 | H11: 117.25 | J11: 125.93 | L11: 126.6 | N11: 125.6 | P11: 108.9 | R11: 115.4 | T11: 121.7 | V11: 127.12 | X11: 119.69 | AB11: =X11*(1+$B$4) -> 120.64994 | AF11: =AB11*(1+$B$4+AG11) -> 126.44358 | AG11: 0.04 | AJ11: =AF11*(1+$B$4+AK11) -> 133.77987 | AK11: 0.05 | AN11: =AJ11*(1+$B$4+AO11) -> 146.89301 | AO11: 0.09 | AR11: =AN11*(1+$B$4+AS11) -> 161.2915 | AS11: 0.09 | AV11: =AR11*(1+$B$4) -> 162.5851 | AZ11: =AV11*(1+$B$4) -> 163.88907 | BD11: =AZ11*(1+$B$4) -> 165.2035 | BH11: =BD11*(1+$B$4) -> 166.52848 | BL11: =BH11*(1+$B$4) -> 167.86408 | BP11: =BL11*(1+$B$4) -> 169.21039 | BT11: =BP11*(1+$B$4) -> 170.5675
A12: RevPAR | B12: 72.50627 | D12: 62.872 | F12: 85.56 | H12: 90.63425 | J12: 91.29925 | L12: 94.5702 | N12: 97.4656 | P12: 23.3046 | R12: 26.1958 | T12: 55.7386 | V12: 80.84832 | X12: 88.92967 | AB12: =AB10*AB11 -> 89.810384 | AF12: =AF10*AF11 -> 93.828331 | AJ12: =AJ10*AJ11 -> 99.209559 | AN12: =AN10*AN11 -> 109.13762 | AR12: =AR10*AR11 -> 123.65426 | AV12: =AV10*AV11 -> 129.86471 | AZ12: =AZ10*AZ11 -> 131.15082 | BD12: =BD10*BD11 -> 132.20268 | BH12: =BH10*BH11 -> 133.26298 | BL12: =BL10*BL11 -> 134.33179 | BP12: =BP10*BP11 -> 135.40916 | BT12: =BT10*BT11 -> 136.49518
A13: TrevPar
B15: € | C15: % | D15: € | E15: % | F15: € | G15: % | H15: € | I15: % | J15: € | K15: % | L15: € | M15: % | N15: € | O15: % | P15: € | Q15: % | R15: € | S15: % | T15: € | U15: % | V15: € | W15: % | X15: € | Y15: % | Z15: POR | AA15: PAR | AB15: € | AC15: % | AD15: POR | AE15: PAR | AF15: € | AG15: % | AH15: POR | AI15: PAR | AJ15: € | AK15: % | AL15: POR | AM15: PAR | AN15: € | AO15: % | AP15: POR | AQ15: PAR | AR15: € | AS15: % | AT15: POR | AU15: PAR | AV15: € | AW15: % | AX15: POR | AY15: PAR | AZ15: € | BA15: % | BB15: POR | BC15: PAR | BD15: € | BE15: % | BF15: POR | BG15: PAR | BH15: € | BI15: % | BJ15: POR | BK15: PAR | BL15: € | BM15: % | BN15: POR | BO15: PAR | BP15: € | BQ15: % | BR15: POR | BS15: PAR | BT15: € | BU15: % | BV15: POR | BW15: PAR
A16: Departemental Revenue
A17: Rooms | B17: 3758000 | C17: =B17/$B$21 -> 0.66031281 | D17: 3258000 | E17: =D17/$D$21 -> 0.65852012 | F17: 4433000 | G17: =F17/$F$21 -> 0.70170162 | H17: 4712000 | I17: =H17/$H$21 -> 0.70890616 | J17: 4734000 | K17: =J17/$J$21 -> 0.72250101 | L17: 4903000 | M17: =L17/$L$21 -> 0.73018246 | N17: 5038000 | O17: =N17/$N$21 -> 0.74406652 | P17: 1207877.4 | Q17: =P17/$P$21 -> 0.7537751 | R17: 1357728.3 | S17: =R17/$R$21 -> 0.70568795 | T17: 2888931.6 | U17: =T17/$T$21 -> 0.68502385 | V17: 4194000 | W17: =V17/$V$21 -> 0.75999808 | X17: 4623000 | Y17: =X17/X$21 -> 0.73457266 | Z17: =X17/$X$9 -> 119.71971 | AA17: =X17/$B$2 -> 32556.338 | AB17: =AB9*AB11 -> 4654795.5 | AC17: =Y17 -> 0.73457266 | AD17: =AB17/$AB$9 -> 120.64994 | AE17: =AB17/$B$2 -> 32780.25 | AF17: =AF9*AF11 -> 4571947.1 | AG17: =AF17/$AF$21 -> 0.62484957 | AH17: =AF17/AF$9 -> 126.44358 | AI17: =AF17/$B$2 -> 32196.811 | AJ17: =AJ9*AJ11 -> 4951326.9 | AK17: =AJ17/AJ$21 -> 0.64005619 | AL17: =AJ17/AJ$9 -> 133.77987 | AM17: =AJ17/$B$2 -> 34868.499 | AN17: =AN9*AN11 -> 5272577.7 | AO17: =AN17/AN$21 -> 0.62910179 | AP17: =AN17/AN$9 -> 146.89301 | AQ17: =AN17/$B$2 -> 37130.829 | AR17: =AR9*AR11 -> 6408917.8 | AS17: =AR17/AR$21 -> 0.66135317 | AT17: =AR17/AR$9 -> 161.2915 | AU17: =AR17/$B$2 -> 45133.224 | AV17: =AV9*AV11 -> 6730860.5 | AW17: =AV17/AV$21 -> 0.66505059 | AX17: =AV17/AV$9 -> 162.5851 | AY17: =AV17/$B$2 -> 47400.426 | AZ17: =AZ9*AZ11 -> 6797463.2 | BA17: =AZ17/AZ$21 -> 0.66332639 | BB17: =AZ17/AZ$9 -> 163.88907 | BC17: =AZ17/$B$2 -> 47869.459 | BD17: =BD9*BD11 -> 6870813.8 | BE17: =BD17/BD$21 -> 0.66170741 | BF17: =BD17/BD$9 -> 165.2035 | BG17: =BD17/$B$2 -> 48386.012 | BH17: =BH9*BH11 -> 6906935.2 | BI17: =BH17/BH$21 -> 0.65930506 | BJ17: =BH17/BH$9 -> 166.52848 | BK17: =BH17/$B$2 -> 48640.389 | BL17: =BL9*BL11 -> 6962330.5 | BM17: =BL17/BL$21 -> 0.65726302 | BN17: =BL17/BL$9 -> 167.86408 | BO17: =BL17/$B$2 -> 49030.497 | BP17: =BP9*BP11 -> 7018170.2 | BQ17: =BP17/$BP$21 -> 0.65520022 | BR17: =BP17/BP$9 -> 169.21039 | BS17: =BP17/$B$2 -> 49423.734 | BT17: =BT9*BT11 -> 7093902.4 | BU17: =BT17/$BP$21 -> 0.6622704 | BV17: =BT17/BT$9 -> 170.5675 | BW17: =BT17/$B$2 -> 49957.059
A18: Total Food and Beverage | B18: 1391000 | C18: =B18/$B$21 -> 0.24441062 | D18: 1208000 | E18: =D18/$D$21 -> 0.24416584 | F18: 1297000 | G18: =F18/$F$21 -> 0.20530273 | H18: 1239000 | I18: =H18/$H$21 -> 0.18640381 | J18: 1293000 | K18: =J18/$J$21 -> 0.19733709 | L18: 1280000 | M18: =L18/$L$21 -> 0.19062483 | N18: 1194000 | O18: =N18/$N$21 -> 0.17634288 | P18: 200000 | Q18: =P18/$P$21 -> 0.12480987 | R18: 250000 | S18: =R18/$R$21 -> 0.12993909 | T18: 840000 | U18: =T18/$T$21 -> 0.19918091 | V18: 899000 | W18: =V18/$V$21 -> 0.16290851 | X18: 1129000 | Y18: =X18/X$21 -> 0.17939272 | Z18: =X18/$X$9 -> 29.237195 | AA18: =X18/$B$2 -> 7950.7042 | AB18: =AD18*$AB$9 -> 1128000.2 | AC18: =Y18 -> 0.17939272 | AD18: =Z18 -> 29.237195 | AE18: =AB18/$B$2 -> 7943.6634 | AF18: ='1-F&B'!F93 -> 2161878.7 | AG18: =AF18/$AF$21 -> 0.29546469 | AH18: =AF18/AF$9 -> 59.789774 | AI18: =AF18/$B$2 -> 15224.498 | AJ18: ='1-F&B'!H93 -> 2187636.8 | AK18: =AJ18/AJ$21 -> 0.28279499 | AL18: =AJ18/AJ$9 -> 59.107745 | AM18: =AJ18/$B$2 -> 15405.893 | AN18: ='1-F&B'!J93 -> 2529748.8 | AO18: =AN18/AN$21 -> 0.30183898 | AP18: =AN18/AN$9 -> 70.478318 | AQ18: =AN18/$B$2 -> 17815.132 | AR18: ='1-F&B'!L93 -> 2640965.3 | AS18: =AR18/AR$21 -> 0.27252819 | AT18: =AR18/AR$9 -> 66.46446 | AU18: =AR18/$B$2 -> 18598.347 | AV18: ='1-F&B'!N93 -> 2722401.9 | AW18: =AV18/AV$21 -> 0.26899012 | AX18: =AV18/AV$9 -> 65.760089 | AY18: =AV18/$B$2 -> 19171.844 | AZ18: ='1-F&B'!P93 -> 2781272.1 | BA18: =AZ18/AZ$21 -> 0.27140878 | BB18: =AZ18/AZ$9 -> 67.057386 | BC18: =AZ18/$B$2 -> 19586.423 | BD18: ='1-F&B'!R93 -> 2842006 | BE18: =BD18/BD$21 -> 0.27370506 | BF18: =BD18/BD$9 -> 68.333879 | BG18: =BD18/$B$2 -> 20014.127 | BH18: ='1-F&B'!T93 -> 2900344.8 | BI18: =BH18/BH$21 -> 0.27685391 | BJ18: =BH18/BH$9 -> 69.928267 | BK18: =BH18/$B$2 -> 20424.963 | BL18: ='1-F&B'!V93 -> 2961779.4 | BM18: =BL18/BL$21 -> 0.27960006 | BN18: =BL18/BL$9 -> 71.409475 | BO18: =BL18/$B$2 -> 20857.601 | BP18: ='1-F&B'!X93 -> 3024515.3 | BQ18: =BP18/$BP$21 -> 0.28236178 | BR18: =BP18/BP$9 -> 72.922057 | BS18: =BP18/$B$2 -> 21299.403 | BT18: ='1-F&B'!Z93 -> 3090560.8 | BU18: =BT18/$BP$21 -> 0.28852764 | BV18: =BT18/BT$9 -> 74.31019 | BW18: =BT18/$B$2 -> 21764.513
A19: Spa | B19: 235242 | C19: =B19/$B$21 -> 0.041334036 | D19: 198457 | E19: =D19/$D$21 -> 0.040112931 | F19: 247500 | G19: =F19/$F$21 -> 0.03917689 | H19: 274860 | I19: =H19/$H$21 -> 0.041351856 | J19: 253240 | K19: =J19/$J$21 -> 0.038649378 | L19: 258760 | M19: =L19/$L$21 -> 0.038536001 | N19: 276900 | O19: =N19/$N$21 -> 0.040895597 | P19: 124560 | Q19: =P19/$P$21 -> 0.077731585 | R19: 174250 | S19: =R19/$R$21 -> 0.090567549 | T19: 303340 | U19: =T19/$T$21 -> 0.07192802 | V19: 297435 | W19: =V19/$V$21 -> 0.053898433 | X19: 309455 | Y19: =X19/X$21 -> 0.049170924 | Z19: =X19/$X$9 -> 8.013814 | AA19: =X19/$B$2 -> 2179.2606 | AB19: =AD19*$AB$9 -> 309180.96 | AC19: =Y19 -> 0.049170924 | AD19: =Z19 -> 8.013814 | AE19: =AB19/$B$2 -> 2177.3307 | AF19: =AH19*AF$9 -> 333228.01 | AG19: =AF19/$AF$21 -> 0.045542385 | AH19: =ASSUMPTIONS!$F$11 -> 9.2158862 | AI19: =AF19/$B$2 -> 2346.6761 | AJ19: =AL19*AJ$9 -> 341089.16 | AK19: =AJ19/AJ$21 -> 0.044092469 | AL19: =ASSUMPTIONS!$F$11 -> 9.2158862 | AM19: =AJ19/$B$2 -> 2402.0364 | AN19: =AP19*AN$9 -> 330795.02 | AO19: =AN19/AN$21 -> 0.03946907 | AP19: =ASSUMPTIONS!$F$11 -> 9.2158862 | AQ19: =AN19/$B$2 -> 2329.5424 | AR19: =AT19*AR$9 -> 366193.24 | AS19: =AR19/AR$21 -> 0.037788448 | AT19: =ASSUMPTIONS!$F$11 -> 9.2158862 | AU19: =AR19/$B$2 -> 2578.8256 | AV19: =AX19*AV$9 -> 381528.47 | AW19: =AV19/AV$21 -> 0.03769737 | AX19: =ASSUMPTIONS!$F$11 -> 9.2158862 | AY19: =AV19/$B$2 -> 2686.8202 | AZ19: =BB19*AZ$9 -> 382238.09 | BA19: =AZ19/AZ$21 -> 0.037300476 | BB19: =ASSUMPTIONS!$F$11 -> 9.2158862 | BC19: =AZ19/$B$2 -> 2691.8176 | BD19: =BF19*BD$9 -> 383288.7 | BE19: =BD19/BD$21 -> 0.036913382 | BF19: =ASSUMPTIONS!$F$11 -> 9.2158862 | BG19: =BD19/$B$2 -> 2699.2162 | BH19: =BJ19*BH$9 -> 382238.09 | BI19: =BH19/BH$21 -> 0.036486735 | BJ19: =ASSUMPTIONS!$F$11 -> 9.2158862 | BK19: =BH19/$B$2 -> 2691.8176 | BL19: =BN19*BL$9 -> 382238.09 | BM19: =BL19/BL$21 -> 0.03608432 | BN19: =ASSUMPTIONS!$F$11 -> 9.2158862 | BO19: =BL19/$B$2 -> 2691.8176 | BP19: =BR19*BP$9 -> 382238.09 | BQ19: =BP19/BP$21 -> 0.035684869 | BR19: =ASSUMPTIONS!$F$11 -> 9.2158862 | BS19: =BP19/$B$2 -> 2691.8176 | BT19: =BV19*BT$9 -> 383288.7 | BU19: =BT19/BT$21 -> 0.035309533 | BV19: =ASSUMPTIONS!$F$11 -> 9.2158862 | BW19: =BT19/$B$2 -> 2699.2162
A20: Other | B20: 307000 | C20: =B20/$B$21 -> 0.053942531 | D20: 283000 | E20: =D20/$D$21 -> 0.057201104 | F20: 340000 | G20: =F20/$F$21 -> 0.053818757 | H20: 421000 | I20: =H20/$H$21 -> 0.063338178 | J20: 272000 | K20: =J20/$J$21 -> 0.041512521 | L20: 273000 | M20: =L20/$L$21 -> 0.040656703 | N20: 262000 | O20: =N20/$N$21 -> 0.038695004 | P20: 70000 | Q20: =P20/$P$21 -> 0.043683453 | R20: 142000 | S20: =R20/$R$21 -> 0.073805406 | T20: 185000 | U20: =T20/$T$21 -> 0.043867224 | V20: 128000 | W20: =V20/$V$21 -> 0.023194982 | X20: 232000 | Y20: =X20/X$21 -> 0.036863694 | Z20: =X20/$X$9 -> 6.0079975 | AA20: =X20/$B$2 -> 1633.8028 | AB20: =AD20*$AB$9 -> 231794.55 | AC20: =Y20 -> 0.036863694 | AD20: =Z20 -> 6.0079975 | AE20: =AB20/$B$2 -> 1632.356 | AF20: =AH20*AF$9 -> 249822.75 | AG20: =AF20/$AF$21 -> 0.03414336 | AH20: =ASSUMPTIONS!$F$12 -> 6.9091971 | AI20: =AF20/$B$2 -> 1759.3151 | AJ20: =AL20*AJ$9 -> 255716.29 | AK20: =AJ20/AJ$21 -> 0.03305635 | AL20: =ASSUMPTIONS!$F$12 -> 6.9091971 | AM20: =AJ20/$B$2 -> 1800.819 | AN20: =AP20*AN$9 -> 247998.72 | AO20: =AN20/AN$21 -> 0.029590164 | AP20: =ASSUMPTIONS!$F$12 -> 6.9091971 | AQ20: =AN20/$B$2 -> 1746.4699 | AR20: =AT20*AR$9 -> 274536.95 | AS20: =AR20/AR$21 -> 0.028330193 | AT20: =ASSUMPTIONS!$F$12 -> 6.9091971 | AU20: =AR20/$B$2 -> 1933.3588 | AV20: =AX20*AV$9 -> 286033.85 | AW20: =AV20/AV$21 -> 0.028261911 | AX20: =ASSUMPTIONS!$F$12 -> 6.9091971 | AY20: =AV20/$B$2 -> 2014.3229 | AZ20: =BB20*AZ$9 -> 286565.86 | BA20: =AZ20/AZ$21 -> 0.027964358 | BB20: =ASSUMPTIONS!$F$12 -> 6.9091971 | BC20: =AZ20/$B$2 -> 2018.0694 | BD20: =BF20*BD$9 -> 287353.51 | BE20: =BD20/BD$21 -> 0.027674152 | BF20: =ASSUMPTIONS!$F$12 -> 6.9091971 | BG20: =BD20/$B$2 -> 2023.6162 | BH20: =BJ20*BH$9 -> 286565.86 | BI20: =BH20/BH$21 -> 0.027354292 | BJ20: =ASSUMPTIONS!$F$12 -> 6.9091971 | BK20: =BH20/$B$2 -> 2018.0694 | BL20: =BN20*BL$9 -> 286565.86 | BM20: =BL20/BL$21 -> 0.0270526 | BN20: =ASSUMPTIONS!$F$12 -> 6.9091971 | BO20: =BL20/$B$2 -> 2018.0694 | BP20: =BR20*BP$9 -> 286565.86 | BQ20: =BP20/BP$21 -> 0.026753129 | BR20: =ASSUMPTIONS!$F$12 -> 6.9091971 | BS20: =BP20/$B$2 -> 2018.0694 | BT20: =BV20*BT$9 -> 287353.51 | BU20: =BT20/BT$21 -> 0.026471738 | BV20: =ASSUMPTIONS!$F$12 -> 6.9091971 | BW20: =BT20/$B$2 -> 2023.6162
A21: Total Operating Revenue | B21: =SUM(B17:B20) -> 5691242 | C21: =B21/$B$21 -> 1 | D21: =SUM(D17:D20) -> 4947457 | E21: =D21/$D$21 -> 1 | F21: =SUM(F17:F20) -> 6317500 | G21: =F21/$F$21 -> 1 | H21: =SUM(H17:H20) -> 6646860 | I21: =H21/$H$21 -> 1 | J21: =SUM(J17:J20) -> 6552240 | K21: =J21/$J$21 -> 1 | L21: =SUM(L17:L20) -> 6714760 | M21: =L21/$L$21 -> 1 | N21: =SUM(N17:N20) -> 6770900 | O21: =N21/$N$21 -> 1 | P21: =SUM(P17:P20) -> 1602437.4 | Q21: =P21/$P$21 -> 1 | R21: =SUM(R17:R20) -> 1923978.3 | S21: =R21/$R$21 -> 1 | T21: =SUM(T17:T20) -> 4217271.6 | U21: =T21/$T$21 -> 1 | V21: =SUM(V17:V20) -> 5518435 | W21: =V21/$V$21 -> 1 | X21: =SUM(X17:X20) -> 6293455 | Y21: =X21/X$21 -> 1 | Z21: =X21/$X$9 -> 162.97871 | AA21: =X21/$B$2 -> 44320.106 | AB21: =SUM(AB17:AB20) -> 6323771.2 | AC21: =AB21/$AB$21 -> 1 | AD21: =AB21/$AB$9 -> 163.90895 | AE21: =AB21/$B$2 -> 44533.6 | AF21: =SUM(AF17:AF20) -> 7316876.6 | AG21: =SUM(AG17:AG20) -> 1 | AH21: =AF21/AF$9 -> 202.35844 | AI21: =AF21/$B$2 -> 51527.3 | AJ21: =SUM(AJ17:AJ20) -> 7735769.1 | AK21: =SUM(AK17:AK20) -> 1 | AL21: =AJ21/AJ$9 -> 209.0127 | AM21: =AJ21/$B$2 -> 54477.247 | AN21: =SUM(AN17:AN20) -> 8381120.2 | AO21: =SUM(AO17:AO20) -> 1 | AP21: =AN21/AN$9 -> 233.49641 | AQ21: =AN21/$B$2 -> 59021.973 | AR21: =SUM(AR17:AR20) -> 9690613.3 | AS21: =SUM(AS17:AS20) -> 1 | AT21: =AR21/AR$9 -> 243.88104 | AU21: =AR21/$B$2 -> 68243.755 | AV21: =SUM(AV17:AV20) -> 10120825 | AW21: =SUM(AW17:AW20) -> 1 | AX21: =AV21/AV$9 -> 244.47027 | AY21: =AV21/$B$2 -> 71273.414 | AZ21: =SUM(AZ17:AZ20) -> 10247539 | BA21: =SUM(BA17:BA20) -> 1 | BB21: =AZ21/AZ$9 -> 247.07154 | BC21: =AZ21/$B$2 -> 72165.77 | BD21: =SUM(BD17:BD20) -> 10383462 | BE21: =SUM(BE17:BE20) -> 1 | BF21: =BD21/BD$9 -> 249.66247 | BG21: =BD21/$B$2 -> 73122.972 | BH21: =SUM(BH17:BH20) -> 10476084 | BI21: =SUM(BI17:BI20) -> 1 | BJ21: =BH21/BH$9 -> 252.58183 | BK21: =BH21/$B$2 -> 73775.239 | BL21: =SUM(BL17:BL20) -> 10592914 | BM21: =SUM(BM17:BM20) -> 1 | BN21: =BL21/BL$9 -> 255.39864 | BO21: =BL21/$B$2 -> 74597.985 | BP21: =SUM(BP17:BP20) -> 10711489 | BQ21: =SUM(BQ17:BQ20) -> 1 | BR21: =BP21/BP$9 -> 258.25753 | BS21: =BP21/$B$2 -> 75433.024 | BT21: =SUM(BT17:BT20) -> 10855105 | BU21: =SUM(BU17:BU20) -> 1.0125793 | BV21: =BT21/BT$9 -> 261.00277 | BW21: =BT21/$B$2 -> 76444.404
A22: Departemental Expenses | AI22: =AF22/$B$2 -> 0 | AM22: =AJ22/$B$2 -> 0 | AQ22: =AN22/$B$2 -> 0 | AU22: =AR22/$B$2 -> 0 | AY22: =AV22/$B$2 -> 0 | BC22: =AZ22/$B$2 -> 0 | BG22: =BD22/$B$2 -> 0 | BK22: =BH22/$B$2 -> 0 | BO22: =BL22/$B$2 -> 0 | BS22: =BP22/$B$2 -> 0 | BW22: =BT22/$B$2 -> 0
A23: Rooms | B23: 1294631 | C23: =B23/B17 -> 0.3445 | D23: 1161570.5 | E23: =D23/D17 -> 0.3565287 | F23: 1365913.7 | G23: =F23/F17 -> 0.308124 | H23: 1406202.2 | I23: =H23/H17 -> 0.29843 | J23: 1434000 | K23: =J23/J17 -> 0.30291508 | L23: 1391000 | M23: =L23/L17 -> 0.28370385 | N23: 1431000 | O23: =N23/N17 -> 0.28404129 | P23: 338205.68 | Q23: =P23/P17 -> 0.28 | R23: 380163.93 | S23: =R23/R17 -> 0.28 | T23: 808900.86 | U23: =T23/T17 -> 0.28 | V23: 1413000 | W23: =V23/V17 -> 0.33690987 | X23: 1581000 | Y23: =X23/X17 -> 0.34198572 | Z23: =X23/$X$9 -> 40.942431 | AA23: =X23/$B$2 -> 11133.803 | AB23: =AC23*AB17 -> 1591873.6 | AC23: =Y23 -> 0.34198572 | AD23: =AB23/$AB$9 -> 41.260558 | AE23: =AB23/$B$2 -> 11210.377 | AF23: =AG23*AF17 -> 1403522.5 | AG23: =ASSUMPTIONS!F14 -> 0.30698572 | AH23: =AF23/$AF$9 -> 38.816375 | AI23: =AF23/$B$2 -> 9883.9613 | AJ23: =AK23*AJ17 -> 1519986.7 | AK23: =AG23 -> 0.30698572 | AL23: =AJ23/$AJ$9 -> 41.068511 | AM23: =AJ23/$B$2 -> 10704.131 | AN23: =AO23*AN17 -> 1618606.1 | AO23: =AK23 -> 0.30698572 | AP23: =AN23/$AN$9 -> 45.094057 | AQ23: =AN23/$B$2 -> 11398.634 | AR23: =AS23*AR17 -> 1967446.3 | AS23: =AO23 -> 0.30698572 | AT23: =AP23*(1+Inflation) -> 46.049231 | AU23: =AR23/$B$2 -> 13855.255 | AV23: =AW23*AV17 -> 2066278.1 | AW23: =AS23 -> 0.30698572 | AX23: =AT23*(1+Inflation) -> 47.024638 | AY23: =AV23/$B$2 -> 14551.254 | AZ23: =BA23*AZ17 -> 2086724.2 | BA23: =AW23 -> 0.30698572 | BB23: =AX23*(1+Inflation) -> 48.020705 | BC23: =AZ23/$B$2 -> 14695.241 | BD23: =BE23*BD17 -> 2109241.7 | BE23: =BA23 -> 0.30698572 | BF23: =BB23*(1+Inflation) -> 49.037871 | BG23: =BD23/$B$2 -> 14853.815 | BH23: =BI23*BH17 -> 2120330.5 | BI23: =BE23 -> 0.30698572 | BJ23: =BF23*(1+Inflation) -> 50.076582 | BK23: =BH23/$B$2 -> 14931.905 | BL23: =BM23*BL17 -> 2137336.1 | BM23: =BI23 -> 0.30698572 | BN23: =BJ23*(1+Inflation) -> 51.137295 | BO23: =BL23/$B$2 -> 15051.663 | BP23: =BQ23*BP17 -> 2154478.1 | BQ23: =BM23 -> 0.30698572 | BR23: =BN23*(1+Inflation) -> 52.220476 | BS23: =BP23/$B$2 -> 15172.381 | BT23: =BU23*BT17 -> 2177726.8 | BU23: =BQ23 -> 0.30698572 | BV23: =BR23*(1+Inflation) -> 53.326601 | BW23: =BT23/$B$2 -> 15336.104
A24: Food and Beverage | B24: 1210091.6 | C24: =B24/B18 -> 0.86994363 | D24: 1102489.5 | E24: =D24/D18 -> 0.9126569 | F24: 1280953.9 | G24: =F24/F18 -> 0.98762827 | H24: 1267033.1 | I24: =H24/H18 -> 1.0226256 | J24: 1197000 | K24: =J24/J18 -> 0.92575406 | L24: 1099000 | M24: =L24/L18 -> 0.85859375 | N24: 1090000 | O24: =N24/N18 -> 0.91289782 | P24: 187134 | Q24: =P24/P18 -> 0.93567 | R24: 231175 | S24: =R24/R18 -> 0.9247 | T24: 770985.6 | U24: =T24/T18 -> 0.91784 | V24: 839000 | W24: =V24/V18 -> 0.93325918 | X24: 1133000 | Y24: =X24/X18 -> 1.003543 | Z24: =X24/$X$9 -> 29.340781 | AA24: =X24/$B$2 -> 7978.8732 | AB24: =AC24*AB18 -> 1131996.7 | AC24: =Y24 -> 1.003543 | AD24: =AB24/$AB$9 -> 29.340781 | AE24: =AB24/$B$2 -> 7971.8075 | AF24: =AG24*AF18 -> 1648299.2 | AG24: ='1-F&B'!G94 -> 0.76243834 | AH24: =AF24/$AF$9 -> 45.586016 | AI24: =AF24/$B$2 -> 11607.741 | AJ24: =AK24*AJ18 -> 1663830.7 | AK24: ='1-F&B'!I94 -> 0.76056075 | AL24: =AJ24/$AJ$9 -> 44.955031 | AM24: =AJ24/$B$2 -> 11717.117 | AN24: =AO24*AN18 -> 1917987.5 | AO24: ='1-F&B'!K94 -> 0.75817313 | AP24: =AN24/$AN$9 -> 53.434767 | AQ24: =AN24/$B$2 -> 13506.955 | AR24: =AS24*AR18 -> 1997112.1 | AS24: ='1-F&B'!M94 -> 0.75620535 | AT24: =AR24/$AR$9 -> 50.26078 | AU24: =AR24/$B$2 -> 14064.17 | AV24: =AW24*AV18 -> 2056446 | AW24: ='1-F&B'!O94 -> 0.75537928 | AX24: =AV24/$AV$9 -> 49.673808 | AY24: =AV24/$B$2 -> 14482.014 | AZ24: =BA24*AZ18 -> 2100810.1 | BA24: ='1-F&B'!Q94 -> 0.75534143 | BB24: =AZ24/$AZ$9 -> 50.651222 | BC24: =AZ24/$B$2 -> 14794.437 | BD24: =BE24*BD18 -> 2146525.8 | BE24: ='1-F&B'!S94 -> 0.75528545 | BF24: =BD24/$BD$9 -> 51.611585 | BG24: =BD24/$B$2 -> 15116.379 | BH24: =BI24*BH18 -> 2190750.6 | BI24: ='1-F&B'!U94 -> 0.75534143 | BJ24: =BH24/$BH$9 -> 52.819717 | BK24: =BH24/$B$2 -> 15427.821 | BL24: =BM24*BL18 -> 2237154.7 | BM24: ='1-F&B'!W94 -> 0.75534143 | BN24: =BL24/$BL$9 -> 53.938535 | BO24: =BL24/$B$2 -> 15754.61 | BP24: =BQ24*BP18 -> 2284541.7 | BQ24: ='1-F&B'!Y94 -> 0.75534143 | BR24: =BP24/$BL$9 -> 55.081051 | BS24: =BP24/$B$2 -> 16088.322 | BT24: =BU24*BT18 -> 2334255.6 | BU24: ='1-F&B'!AA94 -> 0.75528545 | BV24: =BT24/$BL$9 -> 56.27967 | BW24: =BT24/$B$2 -> 16438.42
A25: Spa | B25: 176099.81 | C25: =B25/B19 -> 0.74859 | D25: 148562.93 | E25: =D25/D19 -> 0.74859 | F25: 185276.02 | G25: =F25/F19 -> 0.74859 | H25: 205757.45 | I25: =H25/H19 -> 0.74859 | J25: 189572.93 | K25: =J25/J19 -> 0.74859 | L25: 180200 | M25: =L25/L19 -> 0.69639821 | N25: 215400 | O25: =N25/N19 -> 0.77789816 | P25: 119378.3 | Q25: =P25/P19 -> 0.9584 | R25: 167001.2 | S25: =R25/R19 -> 0.9584 | T25: 238380 | U25: =T25/T19 -> 0.78585086 | V25: 239975 | W25: =V25/V19 -> 0.80681493 | X25: 253390 | Y25: =X25/X19 -> 0.81882665 | Z25: =X25/$X$9 -> 6.5619245 | AA25: =X25/$B$2 -> 1784.4366 | AB25: =AC25*AB19 -> 253165.61 | AC25: =Y25 -> 0.81882665 | AD25: =AB25/$AB$9 -> 6.5619245 | AE25: =AB25/$B$2 -> 1782.8564 | AF25: =AG25*AF19 -> 216207.21 | AG25: =ASSUMPTIONS!F16 -> 0.64882665 | AH25: =AF25/$AF$9 -> 5.9795125 | AI25: =AF25/$B$2 -> 1522.586 | AJ25: =AK25*AJ19 -> 221307.74 | AK25: =AG25 -> 0.64882665 | AL25: =AJ25/$AJ$9 -> 5.9795125 | AM25: =AJ25/$B$2 -> 1558.5052 | AN25: =AO25*AN19 -> 214628.62 | AO25: =AK25 -> 0.64882665 | AP25: =AN25/$AN$9 -> 5.9795125 | AQ25: =AN25/$B$2 -> 1511.4692 | AR25: =AS25*AR19 -> 237595.93 | AS25: =AO25 -> 0.64882665 | AT25: =AR25/$AR$9 -> 5.9795125 | AU25: =AR25/$B$2 -> 1673.2108 | AV25: =AW25*AV19 -> 247545.84 | AW25: =AS25 -> 0.64882665 | AX25: =AV25/$AV$9 -> 5.9795125 | AY25: =AV25/$B$2 -> 1743.2806 | AZ25: =BA25*AZ19 -> 248006.26 | BA25: =AW25 -> 0.64882665 | BB25: =AZ25/$AZ$9 -> 5.9795125 | BC25: =AZ25/$B$2 -> 1746.523 | BD25: =BE25*BD19 -> 248687.93 | BE25: =BA25 -> 0.64882665 | BF25: =BD25/$BD$9 -> 5.9795125 | BG25: =BD25/$B$2 -> 1751.3234 | BH25: =BI25*BH19 -> 248006.26 | BI25: =BE25 -> 0.64882665 | BJ25: =BH25/$BH$9 -> 5.9795125 | BK25: =BH25/$B$2 -> 1746.523 | BL25: =BM25*BL19 -> 248006.26 | BM25: =BI25 -> 0.64882665 | BN25: =BL25/$BL$9 -> 5.9795125 | BO25: =BL25/$B$2 -> 1746.523 | BP25: =BQ25*BP19 -> 248006.26 | BQ25: =BM25 -> 0.64882665 | BR25: =BP25/$BL$9 -> 5.9795125 | BS25: =BP25/$B$2 -> 1746.523 | BT25: =BU25*BT19 -> 248687.93 | BU25: =BQ25 -> 0.64882665 | BV25: =BT25/$BL$9 -> 5.9959477 | BW25: =BT25/$B$2 -> 1751.3234
A26: Other | B26: 96477.404 | C26: =B26/B20 -> 0.31425865 | D26: 180000 | E26: =D26/D20 -> 0.6360424 | F26: 162132.45 | G26: =F26/F20 -> 0.47686014 | H26: 137616.69 | I26: =H26/H20 -> 0.3268805 | J26: 135000 | K26: =J26/J20 -> 0.49632353 | L26: 115000 | M26: =L26/L20 -> 0.42124542 | N26: 128000 | O26: =N26/N20 -> 0.48854962 | P26: 128000 | Q26: =P26/P20 -> 1.8285714 | R26: 128000 | S26: =R26/R20 -> 0.90140845 | T26: 128000 | U26: =T26/T20 -> 0.69189189 | V26: 110000 | W26: =V26/V20 -> 0.859375 | X26: 125000 | Y26: =X26/X20 -> 0.5387931 | Z26: =X26/$X$9 -> 3.2370676 | AA26: =X26/$B$2 -> 880.28169 | AB26: =AC26*AB20 -> 124889.31 | AC26: =Y26 -> 0.5387931 | AD26: =AB26/$AB$9 -> 3.2370676 | AE26: =AB26/$B$2 -> 879.50215 | AF26: =AG26*AF20 -> 92132.907 | AG26: =ASSUMPTIONS!F17 -> 0.3687931 | AH26: =AF26/$AF$9 -> 2.5480642 | AI26: =AF26/$B$2 -> 648.82329 | AJ26: =AK26*AJ20 -> 94306.406 | AK26: =AG26 -> 0.3687931 | AL26: =AJ26/$AJ$9 -> 2.5480642 | AM26: =AJ26/$B$2 -> 664.12962 | AN26: =AO26*AN20 -> 91460.218 | AO26: =AK26 -> 0.3687931 | AP26: =AN26/$AN$9 -> 2.5480642 | AQ26: =AN26/$B$2 -> 644.08604 | AR26: =AS26*AR20 -> 101247.33 | AS26: =AO26 -> 0.3687931 | AT26: =AR26/$AR$9 -> 2.5480642 | AU26: =AR26/$B$2 -> 713.00938 | AV26: =AW26*AV20 -> 105487.31 | AW26: =AS26 -> 0.3687931 | AX26: =AV26/$AV$9 -> 2.5480642 | AY26: =AV26/$B$2 -> 742.86839 | AZ26: =BA26*AZ20 -> 105683.51 | BA26: =AW26 -> 0.3687931 | BB26: =AZ26/$AZ$9 -> 2.5480642 | BC26: =AZ26/$B$2 -> 744.25009 | BD26: =BE26*BD20 -> 105973.99 | BE26: =BA26 -> 0.3687931 | BF26: =BD26/$BD$9 -> 2.5480642 | BG26: =BD26/$B$2 -> 746.29572 | BH26: =BI26*BH20 -> 105683.51 | BI26: =BE26 -> 0.3687931 | BJ26: =BH26/$BH$9 -> 2.5480642 | BK26: =BH26/$B$2 -> 744.25009 | BL26: =BM26*BL20 -> 105683.51 | BM26: =BI26 -> 0.3687931 | BN26: =BL26/$BL$9 -> 2.5480642 | BO26: =BL26/$B$2 -> 744.25009 | BP26: =BQ26*BP20 -> 105683.51 | BQ26: =BM26 -> 0.3687931 | BR26: =BP26/$BL$9 -> 2.5480642 | BS26: =BP26/$B$2 -> 744.25009 | BT26: =BU26*BT20 -> 105973.99 | BU26: =BQ26 -> 0.3687931 | BV26: =BT26/$BL$9 -> 2.5550678 | BW26: =BT26/$B$2 -> 746.29572
A27: Total Departemental Expenses | B27: =SUM(B23:B26) -> 2777299.8 | C27: =B27/B21 -> 0.48799538 | D27: =SUM(D23:D26) -> 2592623 | E27: =D27/D21 -> 0.52403143 | F27: =SUM(F23:F26) -> 2994276 | G27: =F27/F21 -> 0.47396534 | H27: =SUM(H23:H26) -> 3016609.4 | I27: =H27/H21 -> 0.45383977 | J27: =SUM(J23:J26) -> 2955572.9 | K27: =J27/J21 -> 0.45107825 | L27: =SUM(L23:L26) -> 2785200 | M27: =L27/L21 -> 0.41478772 | N27: =SUM(N23:N26) -> 2864400 | O27: =N27/N21 -> 0.42304568 | P27: =SUM(P23:P26) -> 772717.98 | Q27: =P27/$X$21 -> 0.1227812 | R27: =SUM(R23:R26) -> 906340.13 | S27: =R27/$X$21 -> 0.14401313 | T27: =SUM(T23:T26) -> 1946266.5 | U27: =T27/$X$21 -> 0.30925246 | V27: =SUM(V23:V26) -> 2601975 | W27: =V27/$X$21 -> 0.41344142 | X27: =SUM(X23:X26) -> 3092390 | Y27: =X27/$X$21 -> 0.49136603 | Z27: =X27/$X$9 -> 80.082204 | AA27: =X27/$B$2 -> 21777.394 | AB27: =SUM(AB23:AB26) -> 3101925.2 | AC27: =AB27/AB21 -> 0.49051825 | AD27: =AB27/$AB$9 -> 80.400331 | AE27: =AB27/$B$2 -> 21844.544 | AF27: =SUM(AF23:AF26) -> 3360161.8 | AG27: =AF27/AF21 -> 0.45923445 | AH27: =AF27/$AF$9 -> 92.929968 | AI27: =AF27/$B$2 -> 23663.111 | AJ27: =SUM(AJ23:AJ26) -> 3499431.5 | AK27: =AJ27/$AJ$21 -> 0.45237021 | AL27: =AJ27/$AJ$9 -> 94.551119 | AM27: =AJ27/$B$2 -> 24643.884 | AN27: =SUM(AN23:AN26) -> 3842682.5 | AO27: =AN27/$AJ$21 -> 0.49674214 | AP27: =AN27/$AN$9 -> 107.0564 | AQ27: =AN27/$B$2 -> 27061.144 | AR27: =SUM(AR23:AR26) -> 4303401.6 | AS27: =AR27/$AJ$21 -> 0.55629913 | AT27: =AR27/$AR$9 -> 108.30254 | AU27: =AR27/$B$2 -> 30305.645 | AV27: =SUM(AV23:AV26) -> 4475757.2 | AW27: =AV27/$AJ$21 -> 0.57857947 | AX27: =AV27/$AV$9 -> 108.11269 | AY27: =AV27/$B$2 -> 31519.417 | AZ27: =SUM(AZ23:AZ26) -> 4541224 | BA27: =AZ27/$AJ$21 -> 0.58704234 | BB27: =AZ27/$AZ$9 -> 109.4904 | BC27: =AZ27/$B$2 -> 31980.451 | BD27: =SUM(BD23:BD26) -> 4610429.5 | BE27: =BD27/$AJ$21 -> 0.5959885 | BF27: =BD27/$BD$9 -> 110.85428 | BG27: =BD27/$B$2 -> 32467.813 | BH27: =SUM(BH23:BH26) -> 4664770.9 | BI27: =BH27/$AJ$21 -> 0.60301319 | BJ27: =BH27/$BH$9 -> 112.46916 | BK27: =BH27/$B$2 -> 32850.499 | BL27: =SUM(BL23:BL26) -> 4728180.5 | BM27: =BL27/$AJ$21 -> 0.61121014 | BN27: =BL27/$BL$9 -> 113.99799 | BO27: =BL27/$B$2 -> 33297.046 | BP27: =SUM(BP23:BP26) -> 4792709.5 | BQ27: =BP27/$AJ$21 -> 0.61955178 | BR27: =BP27/$BL$9 -> 115.5538 | BS27: =BP27/$B$2 -> 33751.475 | BT27: =SUM(BT23:BT26) -> 4866644.3 | BU27: =BT27/$AJ$21 -> 0.6291093 | BV27: =BT27/$BL$9 -> 117.33639 | BW27: =BT27/$B$2 -> 34272.143
A28: Total Departemental Profit | B28: =B21-B27 -> 2913942.2 | C28: =B28/$B$21 -> 0.51200462 | D28: =D21-D27 -> 2354834 | E28: =D28/$D$21 -> 0.47596857 | F28: =F21-F27 -> 3323224 | G28: =F28/$F$21 -> 0.52603466 | H28: =H21-H27 -> 3630250.6 | I28: =H28/$H$21 -> 0.54616023 | J28: =J21-J27 -> 3596667.1 | K28: =J28/$J$21 -> 0.54892175 | L28: =L21-L27 -> 3929560 | M28: =L28/$L$21 -> 0.58521228 | N28: =N21-N27 -> 3906500 | O28: =N28/$N$21 -> 0.57695432 | P28: =P21-P27 -> 829719.44 | Q28: =P28/$P$21 -> 0.51778586 | R28: =R21-R27 -> 1017638.2 | S28: =R28/$R$21 -> 0.52892394 | T28: =T21-T27 -> 2271005.2 | U28: =T28/$T$21 -> 0.53850104 | V28: =V21-V27 -> 2916460 | W28: =V28/$V$21 -> 0.52849404 | X28: =X21-X27 -> 3201065 | Y28: =X28/$X$21 -> 0.50863397 | Z28: =X28/$X$9 -> 82.89651 | AA28: =X28/$B$2 -> 22542.711 | AB28: =AB21-AB27 -> 3221846 | AC28: =AB28/$AB$21 -> 0.50948175 | AD28: =AB28/$AB$9 -> 83.508619 | AE28: =AB28/$B$2 -> 22689.057 | AF28: =AF21-AF27 -> 3956714.8 | AG28: =AF28/$AF$21 -> 0.54076555 | AH28: =AF28/$AF$9 -> 109.42847 | AI28: =AF28/$B$2 -> 27864.188 | AJ28: =AJ21-AJ27 -> 4236337.6 | AK28: =AJ28/$AJ$21 -> 0.54762979 | AL28: =AJ28/$AJ$9 -> 114.46158 | AM28: =AJ28/$B$2 -> 29833.364 | AN28: =AN21-AN27 -> 4538437.7 | AO28: =AN28/$AN$21 -> 0.5415073 | AP28: =AN28/$AN$9 -> 126.44001 | AQ28: =AN28/$B$2 -> 31960.829 | AR28: =AR21-AR27 -> 5387211.6 | AS28: =AR28/$AR$21 -> 0.55592061 | AT28: =AR28/$AR$9 -> 135.5785 | AU28: =AR28/$B$2 -> 37938.11 | AV28: =AV21-AV27 -> 5645067.5 | AW28: =AV28/$AV$21 -> 0.55776754 | AX28: =AV28/$AV$9 -> 136.35758 | AY28: =AV28/$B$2 -> 39753.997 | AZ28: =AZ21-AZ27 -> 5706315.3 | BA28: =AZ28/$AZ$21 -> 0.55684737 | BB28: =AZ28/$AZ$9 -> 137.58114 | BC28: =AZ28/$B$2 -> 40185.319 | BD28: =BD21-BD27 -> 5773032.6 | BE28: =BD28/$BD$21 -> 0.5559834 | BF28: =BD28/$BD$9 -> 138.80819 | BG28: =BD28/$B$2 -> 40655.159 | BH28: =BH21-BH27 -> 5811313.1 | BI28: =BH28/$BH$21 -> 0.55472189 | BJ28: =BH28/$BH$9 -> 140.11267 | BK28: =BH28/$B$2 -> 40924.74 | BL28: =BL21-BL27 -> 5864733.4 | BM28: =BL28/$BL$21 -> 0.55364685 | BN28: =BL28/$BL$9 -> 141.40065 | BO28: =BL28/$B$2 -> 41300.939 | BP28: =BP21-BP27 -> 5918779.9 | BQ28: =BP28/$BP$21 -> 0.55256367 | BR28: =BP28/$BL$9 -> 142.70373 | BS28: =BP28/$B$2 -> 41681.549 | BT28: =BT21-BT27 -> 5988461.1 | BU28: =BT28/$BP$21 -> 0.55906895 | BV28: =BT28/$BL$9 -> 144.38377 | BW28: =BT28/$B$2 -> 42172.261
A29: Undistributed Operating Expenses | AA29: =X29/$B$2 -> 0 | AE29: =AB29/$B$2 -> 0 | AI29: =AF29/$B$2 -> 0 | AM29: =AJ29/$B$2 -> 0 | AQ29: =AN29/$B$2 -> 0 | AU29: =AR29/$B$2 -> 0 | AY29: =AV29/$B$2 -> 0 | BC29: =AZ29/$B$2 -> 0 | BG29: =BD29/$B$2 -> 0 | BK29: =BH29/$B$2 -> 0 | BO29: =BL29/$B$2 -> 0 | BS29: =BP29/$B$2 -> 0 | BW29: =BT29/$B$2 -> 0
A30: Aministrative and General | B30: 598000 | C30: =B30/B$21 -> 0.10507373 | D30: 598700 | E30: =D30/$D$21 -> 0.12101166 | F30: 658400 | G30: =F30/$F$21 -> 0.10421844 | H30: 684200 | I30: =H30/$H$21 -> 0.10293582 | J30: 603000 | K30: =J30/$J$21 -> 0.092029596 | L30: 854000 | M30: =L30/$L$21 -> 0.12718251 | N30: 407000 | O30: =N30/$N$21 -> 0.060110177 | P30: 407000 | Q30: =P30/$P$21 -> 0.25398808 | R30: 407000 | S30: =R30/$R$21 -> 0.21154085 | T30: 407000 | U30: =T30/$T$21 -> 0.096507893 | V30: 666000 | W30: =V30/$V$21 -> 0.12068639 | X30: 380000 | Y30: =X30/X$21 -> 0.060380189 | Z30: =X30/$X$9 -> 9.8406855 | AA30: =X30/$B$2 -> 2676.0563 | AB30: =AE30*$B$2 -> 388049.09 | AC30: =AB30/AB$21 -> 0.061363556 | AD30: =AB30/$AB$9 -> 10.058036 | AE30: =AA30*(1+Inflation) -> 2732.7401 | AF30: =AI30*$B$2 -> 342000 | AG30: =AF30/AF21 -> 0.046741256 | AH30: =AF30/$AF$9 -> 9.4584877 | AI30: =ASSUMPTIONS!F19 -> 2408.4507 | AJ30: =AM30*$B$2 -> 349244.18 | AK30: =AJ30/AJ21 -> 0.045146666 | AL30: =AJ30/$AJ$9 -> 9.4362266 | AM30: =AI30*(1+Inflation) -> 2459.4661 | AN30: =AQ30*$B$2 -> 356641.81 | AO30: =AN30/AN21 -> 0.042553 | AP30: =AN30/$AN$9 -> 9.9359728 | AQ30: =AM30*(1+Inflation) -> 2511.562 | AR30: =AU30*$B$2 -> 364196.13 | AS30: =AR30/AR21 -> 0.037582361 | AT30: =AR30/$AN$9 -> 10.146435 | AU30: =AQ30*(1+Inflation) -> 2564.7615 | AV30: =AY30*$B$2 -> 371910.47 | AW30: =AV30/AV21 -> 0.036747051 | AX30: =AV30/$AN$9 -> 10.361355 | AY30: =AU30*(1+Inflation) -> 2619.0878 | AZ30: =BC30*$B$2 -> 379788.21 | BA30: =AZ30/AZ21 -> 0.037061405 | BB30: =AZ30/$AN$9 -> 10.580827 | BC30: =AY30*(1+Inflation) -> 2674.5648 | BD30: =BG30*$B$2 -> 387832.81 | BE30: =BD30/BD21 -> 0.037351012 | BF30: =BD30/$AN$9 -> 10.804948 | BG30: =BC30*(1+Inflation) -> 2731.217 | BH30: =BK30*$B$2 -> 396047.82 | BI30: =BH30/BH21 -> 0.037804949 | BJ30: =BH30/$AN$9 -> 11.033817 | BK30: =BG30*(1+Inflation) -> 2789.0691 | BL30: =BO30*$B$2 -> 404436.83 | BM30: =BL30/BL21 -> 0.038179941 | BN30: =BL30/$AN$9 -> 11.267533 | BO30: =BK30*(1+Inflation) -> 2848.1467 | BP30: =BS30*$B$2 -> 413003.54 | BQ30: =BP30/BP21 -> 0.03855706 | BR30: =BP30/$AN$9 -> 11.5062 | BS30: =BO30*(1+Inflation) -> 2908.4756 | BT30: =BW30*$B$2 -> 421751.7 | BU30: =BT30/BT21 -> 0.038852843 | BV30: =BT30/$AN$9 -> 11.749922 | BW30: =BS30*(1+Inflation) -> 2970.0824
A31: Sales And Marketing | B31: 424700 | C31: =B31/B$21 -> 0.07462343 | D31: 403250 | E31: =D31/$D$21 -> 0.081506519 | F31: 472140 | G31: =F31/$F$21 -> 0.074735259 | H31: 462370 | I31: =H31/$H$21 -> 0.069562169 | J31: 433000 | K31: =J31/$J$21 -> 0.06608427 | L31: 456000 | M31: =L31/$L$21 -> 0.067910097 | N31: 450000 | O31: =N31/$N$21 -> 0.066460884 | P31: 450000 | Q31: =P31/$P$21 -> 0.2808222 | R31: 450000 | S31: =R31/$R$21 -> 0.23389037 | T31: 450000 | U31: =T31/$T$21 -> 0.10670406 | V31: 366000 | W31: =V31/$V$21 -> 0.066323151 | X31: 230000 | Y31: =X31/X$21 -> 0.036545904 | Z31: =X31/$X$9 -> 5.9562044 | AA31: =X31/$B$2 -> 1619.7183 | AB31: =AE31*$B$2 -> 234871.82 | AC31: =AB31/AB$21 -> 0.0371411 | AD31: =AB31/$AB$9 -> 6.0877587 | AE31: =AA31*(1+Inflation) -> 1654.0269 | AF31: =AI31*$B$2 -> 230000 | AG31: =AF31/AF21 -> 0.031434178 | AH31: =AF31/$AF$9 -> 6.3609713 | AI31: =ASSUMPTIONS!F20 -> 1619.7183 | AJ31: =AM31*$B$2 -> 234871.82 | AK31: =AJ31/AJ21 -> 0.030361793 | AL31: =AJ31/$AJ$9 -> 6.3460003 | AM31: =AI31*(1+Inflation) -> 1654.0269 | AN31: =AQ31*$B$2 -> 239846.83 | AO31: =AN31/AN21 -> 0.028617515 | AP31: =AN31/$AN$9 -> 6.682087 | AQ31: =AM31*(1+Inflation) -> 1689.0622 | AR31: =AU31*$B$2 -> 244927.22 | AS31: =AR31/AR21 -> 0.025274688 | AT31: =AR31/$AN$9 -> 6.8236257 | AU31: =AQ31*(1+Inflation) -> 1724.8396 | AV31: =AY31*$B$2 -> 250115.23 | AW31: =AV31/AV21 -> 0.024712929 | AX31: =AV31/$AN$9 -> 6.9681625 | AY31: =AU31*(1+Inflation) -> 1761.3748 | AZ31: =BC31*$B$2 -> 255413.12 | BA31: =AZ31/AZ21 -> 0.024924337 | BB31: =AZ31/$AN$9 -> 7.1157609 | BC31: =AY31*(1+Inflation) -> 1798.684 | BD31: =BG31*$B$2 -> 260823.24 | BE31: =BD31/BD21 -> 0.025119101 | BF31: =BD31/$AN$9 -> 7.2664856 | BG31: =BC31*(1+Inflation) -> 1836.7834 | BH31: =BK31*$B$2 -> 266347.95 | BI31: =BH31/BH21 -> 0.025424381 | BJ31: =BH31/$AN$9 -> 7.420403 | BK31: =BG31*(1+Inflation) -> 1875.6898 | BL31: =BO31*$B$2 -> 271989.68 | BM31: =BL31/BL21 -> 0.025676569 | BN31: =BL31/$AN$9 -> 7.5775806 | BO31: =BK31*(1+Inflation) -> 1915.4203 | BP31: =BS31*$B$2 -> 277750.92 | BQ31: =BP31/BP21 -> 0.025930186 | BR31: =BP31/$AN$9 -> 7.7380876 | BS31: =BO31*(1+Inflation) -> 1955.9924 | BT31: =BW31*$B$2 -> 283634.19 | BU31: =BT31/BT21 -> 0.026129105 | BV31: =BT31/$AN$9 -> 7.9019943 | BW31: =BS31*(1+Inflation) -> 1997.4238
A32: Franchise Fees (royalty, loyalty, and marketing) | AF32: =ASSUMPTIONS!F21*AF17+55000 -> 375036.3 | AG32: =AF32/AF17 -> 0.082029885 | AH32: =AF32/$AF$9 -> 10.372153 | AI32: =AF32/$B$2 -> 2641.1007 | AJ32: =7%*AJ17 -> 346592.88 | AK32: =ASSUMPTIONS!F21 -> 0.07 | AL32: =AJ32/$AJ$9 -> 9.3645912 | AM32: =AJ32/$B$2 -> 2440.795 | AN32: =7%*AN17 -> 369080.44 | AO32: =AK32 -> 0.07 | AP32: =AN32/$AN$9 -> 10.282511 | AQ32: =AN32/$B$2 -> 2599.158 | AR32: =7%*AR17 -> 448624.24 | AS32: =AO32 -> 0.07 | AT32: =AR32/$AN$9 -> 12.498586 | AU32: =AR32/$B$2 -> 3159.3257 | AV32: =7%*AV17 -> 471160.24 | AW32: =AS32 -> 0.07 | AX32: =AV32/$AN$9 -> 13.126434 | AY32: =AV32/$B$2 -> 3318.0298 | AZ32: =7%*AZ17 -> 475822.42 | BA32: =AW32 -> 0.07 | BB32: =AZ32/$AN$9 -> 13.256322 | BC32: =AZ32/$B$2 -> 3350.8621 | BD32: =7%*BD17 -> 480956.96 | BE32: =BA32 -> 0.07 | BF32: =BD32/$AN$9 -> 13.399369 | BG32: =BD32/$B$2 -> 3387.0209 | BH32: =7%*BH17 -> 483485.46 | BI32: =BE32 -> 0.07 | BJ32: =BH32/$AN$9 -> 13.469813 | BK32: =BH32/$B$2 -> 3404.8272 | BL32: =7%*BL17 -> 487363.14 | BM32: =BI32 -> 0.07 | BN32: =BL32/$AN$9 -> 13.577844 | BO32: =BL32/$B$2 -> 3432.1348 | BP32: =7%*BP17 -> 491271.91 | BQ32: =BM32 -> 0.07 | BR32: =BP32/$AN$9 -> 13.686742 | BS32: =BP32/$B$2 -> 3459.6614 | BT32: =7%*BT17 -> 496573.17 | BU32: =BQ32 -> 0.07 | BV32: =BT32/$AN$9 -> 13.834434 | BW32: =BT32/$B$2 -> 3496.9941
A33: Heat light and Power | B33: 324500 | C33: =B33/B$21 -> 0.057017431 | D33: 314780 | E33: =D33/$D$21 -> 0.063624606 | F33: 384520 | G33: =F33/$F$21 -> 0.060865849 | H33: 395470 | I33: =H33/$H$21 -> 0.059497266 | J33: 395000 | K33: =J33/$J$21 -> 0.060284727 | L33: 266000 | M33: =L33/$L$21 -> 0.039614223 | N33: 297000 | O33: =N33/$N$21 -> 0.043864183 | P33: 297000 | Q33: =P33/$P$21 -> 0.18534265 | R33: 297000 | S33: =R33/$R$21 -> 0.15436764 | T33: 297000 | U33: =T33/$T$21 -> 0.070424679 | V33: 363000 | W33: =V33/$V$21 -> 0.065779519 | X33: 340000 | Y33: =X33/X$21 -> 0.054024379 | Z33: =X33/$X$9 -> 8.8048239 | AA33: =X33/$B$2 -> 2394.3662 | AB33: =AE33*$B$2 -> 347201.82 | AC33: =AB33/AB$21 -> 0.054904235 | AD33: =AB33/$AB$9 -> 8.9992955 | AE33: =AA33*(1+Inflation) -> 2445.0832 | AF33: =AI33*$B$2 -> 323000 | AG33: =AF33/AF21 -> 0.04414452 | AH33: =AF33/$AF$9 -> 8.9330162 | AI33: =ASSUMPTIONS!F22 -> 2274.6479 | AJ33: =AM33*$B$2 -> 329841.73 | AK33: =AJ33/AJ21 -> 0.042638518 | AL33: =AJ33/$AJ$9 -> 8.9119918 | AM33: =AI33*(1+Inflation) -> 2322.8291 | AN33: =AQ33*$B$2 -> 336828.37 | AO33: =AN33/AN21 -> 0.040188944 | AP33: =AN33/$AN$9 -> 9.3839743 | AQ33: =AM33*(1+Inflation) -> 2372.0308 | AR33: =AU33*$B$2 -> 343963.01 | AS33: =AR33/AR21 -> 0.035494452 | AT33: =AR33/$AN$9 -> 9.582744 | AU33: =AQ33*(1+Inflation) -> 2422.2747 | AV33: =AY33*$B$2 -> 351248.77 | AW33: =AV33/AV21 -> 0.034705548 | AX33: =AV33/$AN$9 -> 9.7857239 | AY33: =AU33*(1+Inflation) -> 2473.5829 | AZ33: =BC33*$B$2 -> 358688.86 | BA33: =AZ33/AZ21 -> 0.035002438 | BB33: =AZ33/$AN$9 -> 9.9930033 | BC33: =AY33*(1+Inflation) -> 2525.9779 | BD33: =BG33*$B$2 -> 366286.54 | BE33: =BD33/BD21 -> 0.035275956 | BF33: =BD33/$AN$9 -> 10.204673 | BG33: =BC33*(1+Inflation) -> 2579.4827 | BH33: =BK33*$B$2 -> 374045.16 | BI33: =BH33/BH21 -> 0.035704674 | BJ33: =BH33/$AN$9 -> 10.420827 | BK33: =BG33*(1+Inflation) -> 2634.1208 | BL33: =BO33*$B$2 -> 381968.12 | BM33: =BL33/BL21 -> 0.036058833 | BN33: =BL33/$AN$9 -> 10.641559 | BO33: =BK33*(1+Inflation) -> 2689.9163 | BP33: =BS33*$B$2 -> 390058.89 | BQ33: =BP33/BP21 -> 0.036415001 | BR33: =BP33/$AN$9 -> 10.866966 | BS33: =BO33*(1+Inflation) -> 2746.8936 | BT33: =BW33*$B$2 -> 398321.05 | BU33: =BT33/BT21 -> 0.036694351 | BV33: =BT33/$AN$9 -> 11.097149 | BW33: =BS33*(1+Inflation) -> 2805.0778
A34: Repairs and Maintenance | B34: 271600 | C34: =B34/B$21 -> 0.047722448 | D34: 288047 | E34: =D34/$D$21 -> 0.058221224 | F34: 324940 | G34: =F34/$F$21 -> 0.051434903 | H34: 340360 | I34: =H34/$H$21 -> 0.051206133 | J34: 300000 | K34: =J34/$J$21 -> 0.045785869 | L34: 348000 | M34: =L34/$L$21 -> 0.051826126 | N34: 322000 | O34: =N34/$N$21 -> 0.047556455 | P34: 322000 | Q34: =P34/$P$21 -> 0.20094388 | R34: 322000 | S34: =R34/$R$21 -> 0.16736155 | T34: 322000 | U34: =T34/$T$21 -> 0.076352682 | V34: 595000 | W34: =V34/$V$21 -> 0.10782042 | X34: 400000 | Y34: =X34/X$21 -> 0.063558093 | Z34: =X34/$X$9 -> 10.358616 | AA34: =X34/$B$2 -> 2816.9014 | AB34: =AE34*$B$2 -> 408472.73 | AC34: =AB34/AB$21 -> 0.064593217 | AD34: =AB34/$AB$9 -> 10.587406 | AE34: =AA34*(1+Inflation) -> 2876.5685 | AF34: =AI34*$B$2 -> 440000 | AG34: =AF34/AF21 -> 0.060134949 | AH34: =AF34/$AF$9 -> 12.168815 | AI34: =ASSUMPTIONS!F23 -> 3098.5915 | AJ34: =AM34*$B$2 -> 449320 | AK34: =AJ34/AJ21 -> 0.058083429 | AL34: =AJ34/$AJ$9 -> 12.140175 | AM34: =AI34*(1+Inflation) -> 3164.2254 | AN34: =AQ34*$B$2 -> 458837.41 | AO34: =AN34/AN21 -> 0.05474655 | AP34: =AN34/$AN$9 -> 12.783123 | AQ34: =AM34*(1+Inflation) -> 3231.2494 | AR34: =AU34*$B$2 -> 468556.43 | AS34: =AR34/AR21 -> 0.048351576 | AT34: =AR34/$AN$9 -> 13.053893 | AU34: =AQ34*(1+Inflation) -> 3299.6931 | AV34: =AY34*$B$2 -> 478481.3 | AW34: =AV34/AV21 -> 0.047276908 | AX34: =AV34/$AN$9 -> 13.330398 | AY34: =AU34*(1+Inflation) -> 3369.5866 | AZ34: =BC34*$B$2 -> 488616.41 | BA34: =AZ34/AZ21 -> 0.04768134 | BB34: =AZ34/$AN$9 -> 13.61276 | BC34: =AY34*(1+Inflation) -> 3440.9606 | BD34: =BG34*$B$2 -> 498966.19 | BE34: =BD34/BD21 -> 0.048053933 | BF34: =BD34/$AN$9 -> 13.901103 | BG34: =BC34*(1+Inflation) -> 3513.8464 | BH34: =BK34*$B$2 -> 509535.2 | BI34: =BH34/BH21 -> 0.048637946 | BJ34: =BH34/$AN$9 -> 14.195554 | BK34: =BG34*(1+Inflation) -> 3588.2761 | BL34: =BO34*$B$2 -> 520328.08 | BM34: =BL34/BL21 -> 0.049120392 | BN34: =BL34/$AN$9 -> 14.496241 | BO34: =BK34*(1+Inflation) -> 3664.2823 | BP34: =BS34*$B$2 -> 531349.58 | BQ34: =BP34/BP21 -> 0.049605574 | BR34: =BP34/$AN$9 -> 14.803298 | BS34: =BO34*(1+Inflation) -> 3741.8984 | BT34: =BW34*$B$2 -> 542604.53 | BU34: =BT34/BT21 -> 0.049986113 | BV34: =BT34/$AN$9 -> 15.116859 | BW34: =BS34*(1+Inflation) -> 3821.1586
A35: Total Undistributed Expenses | B35: =SUM(B30:B34) -> 1618800 | C35: =B35/B$21 -> 0.28443704 | D35: =SUM(D30:D34) -> 1604777 | E35: =D35/$D$21 -> 0.32436401 | F35: =SUM(F30:F34) -> 1840000 | G35: =F35/$F$21 -> 0.29125445 | H35: =SUM(H30:H34) -> 1882400 | I35: =H35/$H$21 -> 0.28320139 | J35: =SUM(J30:J34) -> 1731000 | K35: =J35/$J$21 -> 0.26418446 | L35: =SUM(L30:L34) -> 1924000 | M35: =L35/$L$21 -> 0.28653295 | N35: =SUM(N30:N34) -> 1476000 | O35: =N35/$N$21 -> 0.2179917 | P35: =SUM(P30:P34) -> 1476000 | Q35: =P35/$P$21 -> 0.92109681 | R35: =SUM(R30:R34) -> 1476000 | S35: =R35/$R$21 -> 0.76716041 | T35: =SUM(T30:T34) -> 1476000 | U35: =T35/$T$21 -> 0.34998931 | V35: =SUM(V30:V34) -> 1990000 | W35: =V35/$V$21 -> 0.36060948 | X35: =SUM(X30:X34) -> 1350000 | Y35: =X35/X$21 -> 0.21450856 | Z35: =X35/$X$9 -> 34.96033 | AA35: =X35/$B$2 -> 9507.0423 | AB35: =SUM(AB30:AB34) -> 1378595.5 | AC35: =AB35/$AB$21 -> 0.21800211 | AD35: =AB35/$AB$9 -> 35.732497 | AE35: =AB35/$B$2 -> 9708.4187 | AF35: =SUM(AF30:AF34) -> 1710036.3 | AG35: =AF35/$AF$21 -> 0.23371124 | AH35: =AF35/$AF$9 -> 47.293443 | AI35: =AF35/$B$2 -> 12042.509 | AJ35: =SUM(AJ30:AJ34) -> 1709870.6 | AK35: =AJ35/$AJ$21 -> 0.22103434 | AL35: =AJ35/$AJ$9 -> 46.198984 | AM35: =AJ35/$B$2 -> 12041.342 | AN35: =SUM(AN30:AN34) -> 1761234.9 | AO35: =AN35/$AN$21 -> 0.21014313 | AP35: =AN35/$AN$9 -> 49.067668 | AQ35: =AN35/$B$2 -> 12403.062 | AR35: =SUM(AR30:AR34) -> 1870267 | AS35: =AR35/$AR$21 -> 0.1929978 | AT35: =AR35/$AR$9 -> 47.068505 | AU35: =AR35/$B$2 -> 13170.895 | AV35: =SUM(AV30:AV34) -> 1922916 | AW35: =AV35/$AV$21 -> 0.18999598 | AX35: =AV35/$AV$9 -> 46.448368 | AY35: =AV35/$B$2 -> 13541.662 | AZ35: =SUM(AZ30:AZ34) -> 1958329 | BA35: =AZ35/$AZ$21 -> 0.19110237 | BB35: =AZ35/$AZ$9 -> 47.215957 | BC35: =AZ35/$B$2 -> 13791.049 | BD35: =SUM(BD30:BD34) -> 1994865.7 | BE35: =BD35/$BD$21 -> 0.19211952 | BF35: =BD35/$BD$9 -> 47.965034 | BG35: =BD35/$B$2 -> 14048.35 | BH35: =SUM(BH30:BH34) -> 2029461.6 | BI35: =BH35/$BH$21 -> 0.1937233 | BJ35: =BH35/$BH$9 -> 48.930986 | BK35: =BH35/$B$2 -> 14291.983 | BL35: =SUM(BL30:BL34) -> 2066085.8 | BM35: =BL35/$BL$21 -> 0.19504415 | BN35: =BL35/$BL$9 -> 49.814009 | BO35: =BL35/$B$2 -> 14549.9 | BP35: =SUM(BP30:BP34) -> 2103434.8 | BQ35: =BP35/$BP$21 -> 0.19637184 | BR35: =BP35/$BL$9 -> 50.714506 | BS35: =BP35/$B$2 -> 14812.921 | BT35: =SUM(BT30:BT34) -> 2142884.6 | BU35: =BT35/$BP$21 -> 0.20005478 | BV35: =BT35/$BL$9 -> 51.665653 | BW35: =BT35/$B$2 -> 15090.737
A36: Gross Operating Profit (GOP) | B36: =B28-B35 -> 1295142.2 | C36: =B36/$B$21 -> 0.22756758 | D36: =D28-D35 -> 750057.04 | E36: =D36/$D$21 -> 0.15160456 | F36: =F28-F35 -> 1483224 | G36: =F36/$F$21 -> 0.23478021 | H36: =H28-H35 -> 1747850.6 | I36: =H36/$H$21 -> 0.26295883 | J36: =J28-J35 -> 1865667.1 | K36: =J36/$J$21 -> 0.28473729 | L36: =L28-L35 -> 2005560 | M36: =L36/$L$21 -> 0.29867933 | N36: =N28-N35 -> 2430500 | O36: =N36/$N$21 -> 0.35896262 | P36: =P28-P35 -> -646280.56 | Q36: =P36/$P$21 -> -0.40331095 | R36: =R28-R35 -> -458361.81 | S36: =R36/$R$21 -> -0.23823648 | T36: =T28-T35 -> 795005.18 | U36: =T36/$T$21 -> 0.18851173 | V36: =V28-V35 -> 926460 | W36: =V36/$V$21 -> 0.16788455 | X36: =X28-X35 -> 1851065 | Y36: =X36/$X$21 -> 0.2941254 | Z36: =X36/$X$9 -> 47.93618 | AA36: =X36/$B$2 -> 13035.669 | AB36: =AB28-AB35 -> 1843250.6 | AC36: =AB36/$AB$21 -> 0.29147964 | AD36: =AB36/$AB$9 -> 47.776122 | AE36: =AB36/$B$2 -> 12980.638 | AF36: =AF28-AF35 -> 2246678.5 | AG36: =AF36/$AF$21 -> 0.30705431 | AH36: =AF36/$AF$9 -> 62.135031 | AI36: =AF36/$B$2 -> 15821.679 | AJ36: =AJ28-AJ35 -> 2526467 | AK36: =AJ36/$AJ$21 -> 0.32659545 | AL36: =AJ36/$AJ$9 -> 68.262598 | AM36: =AJ36/$B$2 -> 17792.021 | AN36: =AN28-AN35 -> 2777202.9 | AO36: =AN36/$AN$21 -> 0.33136416 | AP36: =AN36/$AN$9 -> 77.372343 | AQ36: =AN36/$B$2 -> 19557.767 | AR36: =AR28-AR35 -> 3516944.6 | AS36: =AR36/$AR$21 -> 0.36292281 | AT36: =AR36/$AR$9 -> 88.509994 | AU36: =AR36/$B$2 -> 24767.216 | AV36: =AV28-AV35 -> 3722151.5 | AW36: =AV36/$AV$21 -> 0.36777156 | AX36: =AV36/$AV$9 -> 89.909213 | AY36: =AV36/$B$2 -> 26212.335 | AZ36: =AZ28-AZ35 -> 3747986.3 | BA36: =AZ36/$AZ$21 -> 0.365745 | BB36: =AZ36/$AZ$9 -> 90.365181 | BC36: =AZ36/$B$2 -> 26394.269 | BD36: =BD28-BD35 -> 3778166.8 | BE36: =BD36/$BD$21 -> 0.36386388 | BF36: =BD36/$BD$9 -> 90.843155 | BG36: =BD36/$B$2 -> 26606.809 | BH36: =BH28-BH35 -> 3781851.5 | BI36: =BH36/$BH$21 -> 0.36099859 | BJ36: =BH36/$BH$9 -> 91.181683 | BK36: =BH36/$B$2 -> 26632.757 | BL36: =BL28-BL35 -> 3798647.5 | BM36: =BL36/$BL$21 -> 0.3586027 | BN36: =BL36/$BL$9 -> 91.586641 | BO36: =BL36/$B$2 -> 26751.039 | BP36: =BP28-BP35 -> 3815345.1 | BQ36: =BP36/$BP$21 -> 0.35619183 | BR36: =BP36/$BL$9 -> 91.989224 | BS36: =BP36/$B$2 -> 26868.627 | BT36: =BT28-BT35 -> 3845576.5 | BU36: =BT36/$BP$21 -> 0.35901417 | BV36: =BT36/$BL$9 -> 92.718114 | BW36: =BT36/$B$2 -> 27081.525
A37: Management Fee | B37: 0 | C37: =B37/$B$21 -> 0 | D37: 0 | E37: =D37/$D$21 -> 0 | F37: 0 | G37: =F37/$F$21 -> 0 | H37: 0 | I37: =H37/$H$21 -> 0 | J37: 0 | K37: =J37/$J$21 -> 0 | L37: 0 | M37: =L37/$L$21 -> 0 | N37: 0 | O37: =N37/$N$21 -> 0 | P37: 0 | Q37: =P37/$P$21 -> 0 | R37: 0 | S37: =R37/$R$21 -> 0 | T37: 0 | U37: =T37/$T$21 -> 0 | V37: 0 | W37: =V37/$V$21 -> 0 | X37: 0 | Y37: =X37/$X$21 -> 0 | Z37: =X37/$X$9 -> 0 | AA37: =X37/$B$2 -> 0 | AB37: =AC37*AB21 -> 0 | AC37: 0 | AD37: =AB37/$AB$9 -> 0 | AE37: =AB37/$B$2 -> 0
A38: Base Fee | AF38: =AF21*AG38 -> 219506.3 | AG38: =ASSUMPTIONS!F25 -> 0.03 | AH38: =AF38/$AF$9 -> 6.0707533 | AI38: =AF38/$B$2 -> 1545.819 | AJ38: =AJ21*AK38 -> 232073.07 | AK38: =AG38 -> 0.03 | AL38: =AJ38/$AF$9 -> 6.418305 | AM38: =AJ38/$B$2 -> 1634.3174 | AN38: =AN21*AO38 -> 251433.61 | AO38: =AK38 -> 0.03 | AP38: =AN38/$AF$9 -> 6.9537476 | AQ38: =AN38/$B$2 -> 1770.6592 | AR38: =AR21*AS38 -> 290718.4 | AS38: =AO38 -> 0.03 | AT38: =AR38/$AF$9 -> 8.0402234 | AU38: =AR38/$B$2 -> 2047.3127 | AV38: =AV21*AW38 -> 303624.74 | AW38: =AS38 -> 0.03 | AX38: =AV38/$AF$9 -> 8.3971664 | AY38: =AV38/$B$2 -> 2138.2024 | AZ38: =AZ21*BA38 -> 307426.18 | BA38: =AW38 -> 0.03 | BB38: =AZ38/$AF$9 -> 8.5023004 | BC38: =AZ38/$B$2 -> 2164.9731 | BD38: =BD21*BE38 -> 311503.86 | BE38: =BA38 -> 0.03 | BF38: =BD38/$AF$9 -> 8.6150744 | BG38: =BD38/$B$2 -> 2193.6892 | BH38: =BH21*BI38 -> 314282.52 | BI38: =BE38 -> 0.03 | BJ38: =BH38/$AF$9 -> 8.6919221 | BK38: =BH38/$B$2 -> 2213.2572 | BL38: =BL21*BM38 -> 317787.42 | BM38: =BI38 -> 0.03 | BN38: =BL38/$AF$9 -> 8.7888549 | BO38: =BL38/$B$2 -> 2237.9396 | BP38: =BP21*BQ38 -> 321344.68 | BQ38: =BM38 -> 0.03 | BR38: =BP38/$AF$9 -> 8.8872361 | BS38: =BP38/$B$2 -> 2262.9907 | BT38: =BT21*BU38 -> 325653.16 | BU38: =BQ38 -> 0.03 | BV38: =BT38/$AF$9 -> 9.0063931 | BW38: =BT38/$B$2 -> 2293.3321
A39: Incentive fee | AF39: =AF36*AG39 -> 179734.28 | AG39: =ASSUMPTIONS!F26 -> 0.08 | AH39: =AF39/$AF$9 -> 4.9708025 | AI39: =AF39/$B$2 -> 1265.7343 | AJ39: =AJ36*AK39 -> 202117.36 | AK39: =AG39 -> 0.08 | AL39: =AJ39/$AJ$9 -> 5.4610079 | AM39: =AJ39/$B$2 -> 1423.3617 | AN39: =AN36*AO39 -> 222176.23 | AO39: =AK39 -> 0.08 | AP39: =AN39/$AF$9 -> 6.144594 | AQ39: =AN39/$B$2 -> 1564.6213 | AR39: =AR36*AS39 -> 281355.57 | AS39: =AO39 -> 0.08 | AT39: =AR39/$AF$9 -> 7.7812813 | AU39: =AR39/$B$2 -> 1981.3772 | AV39: =AV36*AW39 -> 297772.12 | AW39: =AS39 -> 0.08 | AX39: =AV39/$AF$9 -> 8.235304 | AY39: =AV39/$B$2 -> 2096.9868 | AZ39: =AZ36*BA39 -> 299838.9 | BA39: =AW39 -> 0.08 | BB39: =AZ39/$AF$9 -> 8.2924636 | BC39: =AZ39/$B$2 -> 2111.5416 | BD39: =BD36*BE39 -> 302253.34 | BE39: =BA39 -> 0.08 | BF39: =BD39/$AF$9 -> 8.3592385 | BG39: =BD39/$B$2 -> 2128.5447 | BH39: =BH36*BI39 -> 302548.12 | BI39: =BE39 -> 0.08 | BJ39: =BH39/$AF$9 -> 8.3673909 | BK39: =BH39/$B$2 -> 2130.6206 | BL39: =BL36*BM39 -> 303891.8 | BM39: =BI39 -> 0.08 | BN39: =BL39/$AF$9 -> 8.4045523 | BO39: =BL39/$B$2 -> 2140.0831 | BP39: =BP36*BQ39 -> 305227.6 | BQ39: =BM39 -> 0.08 | BR39: =BP39/$AF$9 -> 8.4414958 | BS39: =BP39/$B$2 -> 2149.4902 | BT39: =BT36*BU39 -> 307646.12 | BU39: =BQ39 -> 0.08 | BV39: =BT39/$AF$9 -> 8.5083832 | BW39: =BT39/$B$2 -> 2166.522
A40: Total Management Fee | AF40: =SUM(AF38:AF39) -> 399240.57 | AG40: =AF40/AF21 -> 0.054564345 | AH40: =AF40/$AF$9 -> 11.041556 | AI40: =AF40/$B$2 -> 2811.5533 | AJ40: =SUM(AJ38:AJ39) -> 434190.44 | AK40: =AJ40/AJ21 -> 0.056127636 | AL40: =AJ40/$AF$9 -> 12.008143 | AM40: =AJ40/$B$2 -> 3057.6791 | AN40: =SUM(AN38:AN39) -> 473609.84 | AO40: =AN40/AN21 -> 0.056509133 | AP40: =AN40/$AF$9 -> 13.098342 | AQ40: =AN40/$B$2 -> 3335.2805 | AR40: =SUM(AR38:AR39) -> 572073.97 | AS40: =AR40/AR21 -> 0.059033825 | AT40: =AR40/$AF$9 -> 15.821505 | AU40: =AR40/$B$2 -> 4028.6899 | AV40: =SUM(AV38:AV39) -> 601396.86 | AW40: =AV40/AV21 -> 0.059421725 | AX40: =AV40/$AF$9 -> 16.63247 | AY40: =AV40/$B$2 -> 4235.1892 | AZ40: =SUM(AZ38:AZ39) -> 607265.08 | BA40: =AZ40/AZ21 -> 0.0592596 | BB40: =AZ40/$AF$9 -> 16.794764 | BC40: =AZ40/$B$2 -> 4276.5146 | BD40: =SUM(BD38:BD39) -> 613757.21 | BE40: =BD40/BD21 -> 0.059109111 | BF40: =BD40/$AF$9 -> 16.974313 | BG40: =BD40/$B$2 -> 4322.2338 | BH40: =SUM(BH38:BH39) -> 616830.64 | BI40: =BH40/BH21 -> 0.058879887 | BJ40: =BH40/$AF$9 -> 17.059313 | BK40: =BH40/$B$2 -> 4343.8777 | BL40: =SUM(BL38:BL39) -> 621679.22 | BM40: =BL40/BL21 -> 0.058688216 | BN40: =BL40/$AF$9 -> 17.193407 | BO40: =BL40/$B$2 -> 4378.0227 | BP40: =SUM(BP38:BP39) -> 626572.29 | BQ40: =BP40/BP21 -> 0.058495347 | BR40: =BP40/$AF$9 -> 17.328732 | BS40: =BP40/$B$2 -> 4412.4809 | BT40: =SUM(BT38:BT39) -> 633299.28 | BU40: =BT40/BT21 -> 0.058341145 | BV40: =BT40/$AF$9 -> 17.514776 | BW40: =BT40/$B$2 -> 4459.8541
A41: Income Before Non-Operating Income and Expenses | B41: =B36-B37 -> 1295142.2 | C41: =B41/$B$21 -> 0.22756758 | D41: =D36-D37 -> 750057.04 | E41: =D41/$D$21 -> 0.15160456 | F41: =F36-F37 -> 1483224 | G41: =F41/$F$21 -> 0.23478021 | H41: =H36-H37 -> 1747850.6 | I41: =H41/$H$21 -> 0.26295883 | J41: =J36-J37 -> 1865667.1 | K41: =J41/$J$21 -> 0.28473729 | L41: =L36-L37 -> 2005560 | M41: =L41/$L$21 -> 0.29867933 | N41: =N36-N37 -> 2430500 | O41: =N41/$N$21 -> 0.35896262 | P41: =P36-P37 -> -646280.56 | Q41: =P41/$P$21 -> -0.40331095 | R41: =R36-R37 -> -458361.81 | S41: =R41/$R$21 -> -0.23823648 | T41: =T36-T37 -> 795005.18 | U41: =T41/$T$21 -> 0.18851173 | V41: =V36-V37 -> 926460 | W41: =V41/$V$21 -> 0.16788455 | X41: =X36-X37 -> 1851065 | Y41: =X41/$X$21 -> 0.2941254 | Z41: =X41/$X$9 -> 47.93618 | AA41: =X41/$B$2 -> 13035.669 | AB41: =AB36-AB37 -> 1843250.6 | AC41: =AB41/$AB$21 -> 0.29147964 | AD41: =AB41/$AB$9 -> 47.776122 | AE41: =AB41/$B$2 -> 12980.638 | AF41: =AF36-AF40 -> 1847437.9 | AG41: =AF41/$AF$21 -> 0.25248996 | AH41: =AF41/$AF$9 -> 51.093476 | AI41: =AF41/$B$2 -> 13010.126 | AJ41: =AJ36-AJ40 -> 2092276.6 | AK41: =AJ41/$AJ$21 -> 0.27046782 | AL41: =AJ41/$AJ$9 -> 56.53121 | AM41: =AJ41/$B$2 -> 14734.342 | AN41: =AN36-AN40 -> 2303593 | AO41: =AN41/$AN$21 -> 0.27485503 | AP41: =AN41/$AN$9 -> 64.177663 | AQ41: =AN41/$B$2 -> 16222.486 | AR41: =AR36-AR40 -> 2944870.6 | AS41: =AR41/$AR$21 -> 0.30388899 | AT41: =AR41/$AR$9 -> 74.112763 | AU41: =AR41/$B$2 -> 20738.526 | AV41: =AV36-AV40 -> 3120754.7 | AW41: =AV41/$AV$21 -> 0.30834984 | AX41: =AV41/$AV$9 -> 75.382368 | AY41: =AV41/$B$2 -> 21977.145 | AZ41: =AZ36-AZ40 -> 3140721.2 | BA41: =AZ41/$AZ$21 -> 0.3064854 | BB41: =AZ41/$AZ$9 -> 75.72382 | BC41: =AZ41/$B$2 -> 22117.755 | BD41: =BD36-BD40 -> 3164409.6 | BE41: =BD41/$BD$21 -> 0.30475477 | BF41: =BD41/$BD$9 -> 76.085828 | BG41: =BD41/$B$2 -> 22284.575 | BH41: =BH36-BH40 -> 3165020.9 | BI41: =BH41/$BH$21 -> 0.3021187 | BJ41: =BH41/$BH$9 -> 76.309694 | BK41: =BH41/$B$2 -> 22288.879 | BL41: =BL36-BL40 -> 3176968.3 | BM41: =BL41/$BL$21 -> 0.29991448 | BN41: =BL41/$BL$9 -> 76.59775 | BO41: =BL41/$B$2 -> 22373.016 | BP41: =BP36-BP40 -> 3188772.8 | BQ41: =BP41/$BP$21 -> 0.29769649 | BR41: =BP41/$BL$9 -> 76.88236 | BS41: =BP41/$B$2 -> 22456.146 | BT41: =BT36-BT40 -> 3212277.2 | BU41: =BT41/$BP$21 -> 0.29989081 | BV41: =BT41/$BL$9 -> 77.44906 | BW41: =BT41/$B$2 -> 22621.67
A42: Non-Operating Income and Expenses | AA42: =X42/$B$2 -> 0 | AB42: =AA42*$B$2 -> 0 | AE42: =AB42/$B$2 -> 0 | AF42: =AE42*$B$2 -> 0
A43: Income Minimum lease rental | B43: 1400000 | C43: =B43/$B$21 -> 0.245992 | D43: 1418200 | E43: =D43/$D$21 -> 0.28665231 | F43: 1436636.6 | G43: =F43/$F$21 -> 0.22740587 | H43: 1459000 | I43: =H43/$H$21 -> 0.21950214 | J43: 1376000 | K43: =J43/$J$21 -> 0.21000452 | L43: 1443000 | M43: =L43/$L$21 -> 0.21489971 | N43: 1460316 | O43: =N43/$N$21 -> 0.21567532 | P43: 1350000 | Q43: =P43/$P$21 -> 0.8424666 | R43: 1350000 | S43: =R43/$R$21 -> 0.70167111 | T43: 1350000 | U43: =T43/$T$21 -> 0.32011218
A44: Income Variable Lease Rental (21.5%) | B44: 1223617 | C44: =B44/$B$21 -> 0.215 | D44: 1063703.3 | E44: =D44/$D$21 -> 0.215 | F44: 1358262.5 | G44: =F44/$F$21 -> 0.215 | H44: 1429074.9 | I44: =H44/$H$21 -> 0.215 | J44: 1408731.6 | K44: =J44/$J$21 -> 0.215 | L44: 1443673.4 | M44: =L44/$L$21 -> 0.215 | N44: 1455743.5 | O44: =N44/$N$21 -> 0.215 | P44: 344524.04 | Q44: =P44/$P$21 -> 0.215 | R44: 413655.34 | S44: =R44/$R$21 -> 0.215 | T44: 906713.4 | U44: =T44/$T$21 -> 0.215
A45: Income Retail (90sqm) | AF45: =ASSUMPTIONS!F29 -> 32740.017 | AG45: =AF45/$AF$21 -> 0.0044745892 | AH45: =AF45/$AF$9 -> 0.9054709 | AI45: =AF45/$B$2 -> 230.5635 | AJ45: =AF45*(1+Inflation) -> 33433.51 | AK45: =AJ45/$AJ$21 -> 0.0043219374 | AL45: =AJ45/$AJ$9 -> 0.90333982 | AM45: =AJ45/$B$2 -> 235.44725 | AN45: =AJ45*(1+Inflation) -> 34141.692 | AO45: =AN45/$AN$21 -> 0.0040736431 | AP45: =AN45/$AJ$9 -> 0.92247419 | AQ45: =AN45/$B$2 -> 240.43445 | AR45: =AN45*(1+Inflation) -> 34864.876 | AS45: =AR45/$AR$21 -> 0.0035977987 | AT45: =AR45/$AR$9 -> 0.87743489 | AU45: =AR45/$B$2 -> 245.52729 | AV45: =AR45*(1+Inflation) -> 35603.377 | AW45: =AV45/$AV$21 -> 0.0035178336 | AX45: =AV45/$AV$9 -> 0.86000572 | AY45: =AV45/$B$2 -> 250.72801 | AZ45: =AV45*(1+Inflation) -> 36357.521 | BA45: =AZ45/$AZ$21 -> 0.003547927 | BB45: =AZ45/$AZ$9 -> 0.87659179 | BC45: =AZ45/$B$2 -> 256.03888 | BD45: =AZ45*(1+Inflation) -> 37127.64 | BE45: =BD45/$BD$21 -> 0.0035756513 | BF45: =BD45/$BD$9 -> 0.89270593 | BG45: =BD45/$B$2 -> 261.46225 | BH45: =BD45*(1+Inflation) -> 37914.071 | BI45: =BH45/$BH$21 -> 0.0036191072 | BJ45: =BH45/$BH$9 -> 0.91412071 | BK45: =BH45/$B$2 -> 267.0005 | BL45: =BH45*(1+Inflation) -> 38717.16 | BM45: =BL45/$BL$21 -> 0.0036550056 | BN45: =BL45/$BL$9 -> 0.93348345 | BO45: =BL45/$B$2 -> 272.65605 | BP45: =BL45*(1+Inflation) -> 39537.259 | BQ45: =BP45/$BP$21 -> 0.0036911075 | BR45: =BQ45/$BT$21 -> 3.4003424e-10 | BS45: =BP45/$B$2 -> 278.4314 | BT45: =BP45*(1+Inflation) -> 40374.73 | BU45: =BT45/$BT$21 -> 0.0037194232 | BV45: =BU45/$BT$21 -> 3.4264275e-10 | BW45: =BT45/$B$2 -> 284.32909
A46: Total Income | B46: =MAX(B43:B44) -> 1400000 | C46: =B46/$B$21 -> 0.245992 | D46: =MAX(D43:D44) -> 1418200 | E46: =D46/$D$21 -> 0.28665231 | F46: =MAX(F43:F44) -> 1436636.6 | G46: =F46/$F$21 -> 0.22740587 | H46: =MAX(H43:H44) -> 1459000 | I46: =H46/$H$21 -> 0.21950214 | J46: =MAX(J43:J44) -> 1408731.6 | K46: =J46/$J$21 -> 0.215 | L46: =MAX(L43:L44) -> 1443673.4 | M46: =L46/$L$21 -> 0.215 | N46: =MAX(N43:N44) -> 1460316 | O46: =N46/$N$21 -> 0.21567532 | P46: =MAX(P43:P44) -> 1350000 | Q46: =P46/$P$21 -> 0.8424666 | R46: =MAX(R43:R44) -> 1350000 | S46: =R46/$R$21 -> 0.70167111 | T46: =MAX(T43:T44) -> 1350000 | U46: =T46/$T$21 -> 0.32011218 | AF46: =SUM(AF43:AF45) -> 32740.017 | AG46: =AF46/$AF$21 -> 0.0044745892 | AH46: =AF46/$AF$9 -> 0.9054709 | AI46: =AF46/$B$2 -> 230.5635 | AJ46: =SUM(AJ43:AJ45) -> 33433.51 | AK46: =AJ46/$AJ$21 -> 0.0043219374 | AL46: =AJ46/$AJ$9 -> 0.90333982 | AM46: =AJ46/$B$2 -> 235.44725 | AN46: =SUM(AN43:AN45) -> 34141.692 | AO46: =AN46/$AN$21 -> 0.0040736431 | AP46: =AN46/$AJ$9 -> 0.92247419 | AQ46: =AN46/$B$2 -> 240.43445 | AR46: =SUM(AR43:AR45) -> 34864.876 | AS46: =AR46/$AR$21 -> 0.0035977987 | AT46: =AR46/$AR$9 -> 0.87743489 | AU46: =AR46/$B$2 -> 245.52729 | AV46: =SUM(AV43:AV45) -> 35603.377 | AW46: =AV46/$AV$21 -> 0.0035178336 | AX46: =AV46/$AV$9 -> 0.86000572 | AY46: =AV46/$B$2 -> 250.72801 | AZ46: =SUM(AZ43:AZ45) -> 36357.521 | BA46: =AZ46/$AZ$21 -> 0.003547927 | BB46: =AZ46/$AZ$9 -> 0.87659179 | BC46: =AZ46/$B$2 -> 256.03888 | BD46: =SUM(BD43:BD45) -> 37127.64 | BE46: =BD46/$BD$21 -> 0.0035756513 | BF46: =BD46/$BD$9 -> 0.89270593 | BG46: =BD46/$B$2 -> 261.46225 | BH46: =SUM(BH43:BH45) -> 37914.071 | BI46: =BH46/$BH$21 -> 0.0036191072 | BJ46: =BH46/$BH$9 -> 0.91412071 | BK46: =BH46/$B$2 -> 267.0005 | BL46: =SUM(BL43:BL45) -> 38717.16 | BM46: =BL46/$BL$21 -> 0.0036550056 | BN46: =BL46/$BL$9 -> 0.93348345 | BO46: =BL46/$B$2 -> 272.65605 | BP46: =SUM(BP43:BP45) -> 39537.259 | BQ46: =BP46/$BP$21 -> 0.0036911075 | BR46: =BQ46/$BT$21 -> 3.4003424e-10 | BS46: =BP46/$B$2 -> 278.4314 | BT46: =SUM(BT43:BT45) -> 40374.73 | BU46: =BT46/$BT$21 -> 0.0037194232 | BV46: =BU46/$BT$21 -> 3.4264275e-10 | BW46: =BT46/$B$2 -> 284.32909
A47: Rent
A48: Proprety tax and Inssurance | B48: 41000 | C48: =B48/$B$21 -> 0.0072040514 | D48: 41000 | E48: =D48/$D$21 -> 0.0082870857 | F48: 41000 | G48: =F48/$F$21 -> 0.006489909 | H48: 41000 | I48: =H48/$H$21 -> 0.0061683261 | J48: 41000 | K48: =J48/$J$21 -> 0.006257402 | L48: 43000 | M48: =L48/$L$21 -> 0.006403803 | N48: 43000 | O48: =N48/$N$21 -> 0.0063507067 | P48: 43000 | Q48: =P48/$P$21 -> 0.026834121 | R48: 43000 | S48: =R48/$R$21 -> 0.022349524 | T48: 43000 | U48: =T48/$T$21 -> 0.010196166 | V48: 43000 | W48: =V48/$V$21 -> 0.0077920642 | X48: 45000 | Y48: =X48/$X$21 -> 0.0071502855 | Z48: =X48/$X$9 -> 1.1653443 | AA48: =X48/$B$2 -> 316.90141 | AB48: =AA48*$B$2 -> 45000 | AC48: =AB48/$AB$21 -> 0.007116007 | AD48: =AB48/$AB$9 -> 1.1663772 | AE48: =AB48/$B$2 -> 316.90141 | AF48: 45000 | AG48: =AF48/$AB$21 -> 0.007116007 | AH48: =AF48/$AF$9 -> 1.2445379 | AI48: =AF48/$B$2 -> 316.90141 | AJ48: =AM48*$B$2 -> 47250 | AK48: =AJ48/$AJ$21 -> 0.0061079899 | AL48: =AJ48/$AJ$9 -> 1.2766475 | AM48: =ASSUMPTIONS!F31 -> 332.74648 | AN48: =AJ48 -> 47250 | AO48: =AN48/$AN$21 -> 0.0056376712 | AP48: =AN48/$AN$9 -> 1.316376 | AQ48: =AN48/$B$2 -> 332.74648 | AR48: =AN48 -> 47250 | AS48: =AR48/$AR$21 -> 0.0048758524 | AT48: =AR48/$AR$9 -> 1.189128 | AU48: =AR48/$B$2 -> 332.74648 | AV48: =AR48 -> 47250 | AW48: =AV48/$AV$21 -> 0.0046685919 | AX48: =AV48/$AV$9 -> 1.1413319 | AY48: =AV48/$B$2 -> 332.74648 | AZ48: =AV48 -> 47250 | BA48: =AZ48/$AZ$21 -> 0.004610863 | BB48: =AZ48/$AZ$9 -> 1.139213 | BC48: =AZ48/$B$2 -> 332.74648 | BD48: =AZ48 -> 47250 | BE48: =BD48/$BD$21 -> 0.0045505054 | BF48: =BD48/$BD$9 -> 1.1360904 | BG48: =BD48/$B$2 -> 332.74648 | BH48: =BD48 -> 47250 | BI48: =BH48/$BH$21 -> 0.0045102731 | BJ48: =BH48/$BH$9 -> 1.139213 | BK48: =BH48/$B$2 -> 332.74648 | BL48: =BH48 -> 47250 | BM48: =BL48/$BL$21 -> 0.004460529 | BN48: =BL48/$BL$9 -> 1.139213 | BO48: =BL48/$B$2 -> 332.74648 | BP48: =BL48 -> 47250 | BQ48: =BP48/$BP$21 -> 0.0044111513 | BR48: =BP48/$BL$9 -> 1.139213 | BS48: =BP48/$B$2 -> 332.74648 | BT48: =BP48 -> 47250 | BU48: =BT48/$BP$21 -> 0.0044111513 | BV48: =BT48/$BL$9 -> 1.139213 | BW48: =BT48/$B$2 -> 332.74648
A49: Insurrance
A50: Other
A51: Total Non-Operating Income and Expenses | B51: =B46-SUM(B47:B50) -> 1359000 | C51: =B51/$B$21 -> 0.23878795 | D51: =D46-D48 -> 1377200 | E51: =D51/$D$21 -> 0.27836523 | F51: =F46-F48 -> 1395636.6 | G51: =F51/$F$21 -> 0.22091596 | H51: =H46-H48 -> 1418000 | I51: =H51/$H$21 -> 0.21333381 | J51: =J46-J48 -> 1367731.6 | K51: =J51/$J$21 -> 0.2087426 | L51: =L46-L48 -> 1400673.4 | M51: =L51/$L$21 -> 0.2085962 | N51: =N46-N48 -> 1417316 | O51: =N51/$N$21 -> 0.20932461 | P51: =P46-P48 -> 1307000 | Q51: =P51/$P$21 -> 0.81563248 | R51: =R46-R48 -> 1307000 | S51: =R51/$R$21 -> 0.67932159 | T51: =T46-T48 -> 1307000 | U51: =T51/$T$21 -> 0.30991601 | V51: =V46-V48 -> -43000 | W51: =V51/$V$21 -> -0.0077920642 | X51: =X46-X48 -> -45000 | Y51: =X51/$X$21 -> -0.0071502855 | Z51: =X51/$X$9 -> -1.1653443 | AA51: =AA46-AA48 -> -316.90141 | AB51: =AB46-AB48 -> -45000 | AC51: =AB51/$AB$21 -> -0.007116007 | AD51: =AB51/$AB$9 -> -1.1663772 | AE51: =AB51/$B$2 -> -316.90141 | AF51: =AF46-AF48 -> -12259.983 | AG51: =AF51/$AF$21 -> -0.0016755761 | AH51: =AF51/$AF$9 -> -0.33906696 | AI51: =AF51/$B$2 -> -86.33791 | AJ51: =AJ46-AJ48 -> -13816.49 | AK51: =AJ51/$AJ$21 -> -0.0017860525 | AL51: =AJ51/$AJ$9 -> -0.37330767 | AM51: =AJ51/$B$2 -> -97.299226 | AN51: =AN46-AN48 -> -13108.308 | AO51: =AN51/$AN$21 -> -0.0015640281 | AP51: =AN51/$AN$9 -> -0.36519495 | AQ51: =AN51/$B$2 -> -92.312025 | AR51: =AR46-AR48 -> -12385.124 | AS51: =AR51/$AR$21 -> -0.0012780537 | AT51: =AR51/$AR$9 -> -0.31169308 | AU51: =AR51/$B$2 -> -87.219186 | AV51: =AV46-AV48 -> -11646.623 | AW51: =AV51/$AV$21 -> -0.0011507583 | AX51: =AV51/$AV$9 -> -0.28132619 | AY51: =AV51/$B$2 -> -82.018472 | AZ51: =AZ46-AZ48 -> -10892.479 | BA51: =AZ51/$AZ$21 -> -0.001062936 | BB51: =AZ51/$AZ$9 -> -0.26262124 | BC51: =AZ51/$B$2 -> -76.707597 | BD51: =BD46-BD48 -> -10122.36 | BE51: =BD51/$BD$21 -> -0.00097485408 | BF51: =BD51/$BD$9 -> -0.24338448 | BG51: =BD51/$B$2 -> -71.284228 | BH51: =BH46-BH48 -> -9335.9294 | BI51: =BH51/$BH$21 -> -0.00089116596 | BJ51: =BH51/$BH$9 -> -0.22509233 | BK51: =BH51/$B$2 -> -65.745982 | BL51: =BL46-BL48 -> -8532.8405 | BM51: =BL51/$BL$21 -> -0.00080552345 | BN51: =BL51/$BL$9 -> -0.20572959 | BO51: =BL51/$B$2 -> -60.090426 | BP51: =BP46-BP48 -> -7712.7406 | BQ51: =BP51/$BP$21 -> -0.00072004372 | BR51: =BP51/$BL$9 -> -0.18595671 | BS51: =BP51/$B$2 -> -54.315075 | BT51: =BT46-BT48 -> -6875.2696 | BU51: =BT51/$BP$21 -> -0.00064185935 | BV51: =BT51/$BL$9 -> -0.16576501 | BW51: =BT51/$B$2 -> -48.417392
A52: Earnings Before Interest, Taxes, Depreciation, and Amortization (EBITDA) | B52: =B41+B51 -> 2654142.2 | C52: =B52/$B$21 -> 0.46635553 | D52: =D41+D51 -> 2127257 | E52: =D52/$D$21 -> 0.42996979 | F52: =F41+F51 -> 2878860.6 | G52: =F52/$F$21 -> 0.45569617 | H52: =H41+H51 -> 3165850.6 | I52: =H52/$H$21 -> 0.47629265 | J52: =J41+J51 -> 3233398.7 | K52: =J52/$J$21 -> 0.49347989 | L52: =L41+L51 -> 3406233.4 | M52: =L52/$L$21 -> 0.50727552 | N52: =N41+N51 -> 3847816 | O52: =N52/$N$21 -> 0.56828723 | P52: =P41+P51 -> 660719.44 | Q52: =P52/$P$21 -> 0.41232152 | R52: =R41+R51 -> 848638.19 | S52: =R52/$R$21 -> 0.44108511 | T52: =T41+T51 -> 2102005.2 | U52: =T52/$T$21 -> 0.49842774 | V52: =V41+V51 -> 883460 | W52: =V52/$V$21 -> 0.16009249 | X52: =X41+X51 -> 1806065 | Y52: =X52/$X$21 -> 0.28697512 | Z52: =X52/$X$9 -> 46.770836 | AA52: =AA41+AA51 -> 12718.768 | AB52: =AB41+AB51 -> 1798250.6 | AC52: =AB52/$AB$21 -> 0.28436364 | AD52: =AB52/$AB$9 -> 46.609745 | AE52: =AB52/$B$2 -> 12663.736 | AF52: =AF41+AF51 -> 1835177.9 | AG52: =AF52/$AF$21 -> 0.25081439 | AH52: =AF52/$AF$9 -> 50.754409 | AI52: =AF52/$B$2 -> 12923.788 | AJ52: =AJ41+AJ51 -> 2078460.1 | AK52: =AJ52/$AJ$21 -> 0.26868177 | AL52: =AJ52/$AJ$9 -> 56.157902 | AM52: =AJ52/$B$2 -> 14637.043 | AN52: =AN41+AN51 -> 2290484.7 | AO52: =AN52/$AN$21 -> 0.273291 | AP52: =AN52/$AN$9 -> 63.812468 | AQ52: =AN52/$B$2 -> 16130.174 | AR52: =AR41+AR51 -> 2932485.5 | AS52: =AR52/$AR$21 -> 0.30261093 | AT52: =AR52/$AR$9 -> 73.80107 | AU52: =AR52/$B$2 -> 20651.306 | AV52: =AV41+AV51 -> 3109108 | AW52: =AV52/$AV$21 -> 0.30719908 | AX52: =AV52/$AV$9 -> 75.101042 | AY52: =AV52/$B$2 -> 21895.127 | AZ52: =AZ41+AZ51 -> 3129828.7 | BA52: =AZ52/$AZ$21 -> 0.30542246 | BB52: =AZ52/$AZ$9 -> 75.461199 | BC52: =AZ52/$B$2 -> 22041.047 | BD52: =BD41+BD51 -> 3154287.2 | BE52: =BD52/$BD$21 -> 0.30377992 | BF52: =BD52/$BD$9 -> 75.842444 | BG52: =BD52/$B$2 -> 22213.29 | BH52: =BH41+BH51 -> 3155684.9 | BI52: =BH52/$BH$21 -> 0.30122753 | BJ52: =BH52/$BH$9 -> 76.084601 | BK52: =BH52/$B$2 -> 22223.133 | BL52: =BL41+BL51 -> 3168435.5 | BM52: =BL52/$BL$21 -> 0.29910896 | BN52: =BL52/$BL$9 -> 76.392021 | BO52: =BL52/$B$2 -> 22312.926 | BP52: =BP41+BP51 -> 3181060 | BQ52: =BP52/$BP$21 -> 0.29697644 | BR52: =BP52/$BL$9 -> 76.696404 | BS52: =BP52/$B$2 -> 22401.831 | BT52: =BT41+BT51 -> 3205401.9 | BU52: =BT52/$BP$21 -> 0.29924895 | BV52: =BT52/$BL$9 -> 77.283295 | BW52: =BT52/$B$2 -> 22573.253
A53: FF&E Reserve (4%) | B53: 227649.68 | C53: =B53/$B$21 -> 0.04 | D53: 197898.28 | E53: =D53/$D$21 -> 0.04 | F53: 252700 | G53: =F53/$F$21 -> 0.04 | H53: 265874.4 | I53: =H53/$H$21 -> 0.04 | J53: 262089.6 | K53: =J53/$J$21 -> 0.04 | L53: 268590.4 | M53: =L53/$L$21 -> 0.04 | N53: 270836 | O53: =N53/$N$21 -> 0.04 | P53: 64097.497 | Q53: =P53/$P$21 -> 0.04 | R53: 76959.133 | S53: =R53/$R$21 -> 0.04 | T53: 168690.87 | U53: =T53/$T$21 -> 0.04 | V53: 220737.4 | W53: =V53/$V$21 -> 0.04 | X53: 251738.2 | Y53: =X53/$X$21 -> 0.04 | Z53: =X53/$X$9 -> 6.5191486 | AA53: =X53/$B$2 -> 1772.8042 | AB53: =Y53*AB21 -> 252950.85 | AC53: =AB53/$AB$21 -> 0.04 | AD53: =AB53/$AB$9 -> 6.556358 | AE53: =AB53/$B$2 -> 1781.344 | AF53: =AC53*AF21 -> 292675.06 | AG53: =AF53/$AF$21 -> 0.04 | AH53: =AF53/$AF$9 -> 8.0943377 | AI53: =AF53/$B$2 -> 2061.092 | AJ53: =AG53*AJ21 -> 309430.76 | AK53: =AJ53/$AJ$21 -> 0.04 | AL53: =AJ53/$AJ$9 -> 8.3605081 | AM53: =AJ53/$B$2 -> 2179.0899 | AN53: =AK53*AN21 -> 335244.81 | AO53: =AN53/$AN$21 -> 0.04 | AP53: =AN53/$AN$9 -> 9.3398565 | AQ53: =AN53/$B$2 -> 2360.8789 | AR53: =AO53*AR21 -> 387624.53 | AS53: =AR53/$AR$21 -> 0.04 | AT53: =AR53/$AR$9 -> 9.7552417 | AU53: =AR53/$B$2 -> 2729.7502 | AV53: =AS53*AV21 -> 404832.99 | AW53: =AV53/$AV$21 -> 0.04 | AX53: =AV53/$AV$9 -> 9.7788108 | AY53: =AV53/$B$2 -> 2850.9366 | AZ53: =AW53*AZ21 -> 409901.57 | BA53: =AZ53/$AZ$21 -> 0.04 | BB53: =AZ53/$AZ$9 -> 9.8828617 | BC53: =AZ53/$B$2 -> 2886.6308 | BD53: =BA53*BD21 -> 415338.48 | BE53: =BD53/$BD$21 -> 0.04 | BF53: =BD53/$BD$9 -> 9.9864987 | BG53: =BD53/$B$2 -> 2924.9189 | BH53: =BE53*BH21 -> 419043.36 | BI53: =BH53/$BH$21 -> 0.04 | BJ53: =BH53/$BH$9 -> 10.103273 | BK53: =BH53/$B$2 -> 2951.0096 | BL53: =BI53*BL21 -> 423716.55 | BM53: =BL53/$BL$21 -> 0.04 | BN53: =BL53/$BL$9 -> 10.215945 | BO53: =BL53/$B$2 -> 2983.9194 | BP53: =BM53*BP21 -> 428459.58 | BQ53: =BP53/$BP$21 -> 0.04 | BR53: =BP53/$BL$9 -> 10.330301 | BS53: =BP53/$B$2 -> 3017.321 | BT53: =BQ53*BT21 -> 434204.22 | BU53: =BT53/$BP$21 -> 0.040536306 | BV53: =BT53/$BL$9 -> 10.468806 | BW53: =BT53/$B$2 -> 3057.7762
A54: EBITDA after Remplacement Reserve | B54: =B52-B53 -> 2426492.5 | C54: =B54/$B$21 -> 0.42635553 | D54: =D52-D53 -> 1929358.8 | E54: =D54/$D$21 -> 0.38996979 | F54: =F52-F53 -> 2626160.6 | G54: =F54/$F$21 -> 0.41569617 | H54: =H52-H53 -> 2899976.2 | I54: =H54/$H$21 -> 0.43629265 | J54: =J52-J53 -> 2971309.1 | K54: =J54/$J$21 -> 0.45347989 | L54: =L52-L53 -> 3137643 | M54: =L54/$L$21 -> 0.46727552 | N54: =N52-N53 -> 3576980 | O54: =N54/$N$21 -> 0.52828723 | P54: =P52-P53 -> 596621.94 | Q54: =P54/$P$21 -> 0.37232152 | R54: =R52-R53 -> 771679.05 | S54: =R54/$R$21 -> 0.40108511 | T54: =T52-T53 -> 1933314.3 | U54: =T54/$T$21 -> 0.45842774 | V54: =V52-V53 -> 662722.6 | W54: =V54/$V$21 -> 0.12009249 | X54: =X52-X53 -> 1554326.8 | Y54: =X54/$X$21 -> 0.24697512 | Z54: =X54/$X$9 -> 40.251687 | AA54: =X54/$B$2 -> 10945.963 | AB54: =AB52-AB53 -> 1545299.7 | AC54: =AB54/$AB$21 -> 0.24436364 | AD54: =AB54/$AB$9 -> 40.053387 | AE54: =AB54/$B$2 -> 10882.392 | AF54: =AF52-AF53 -> 1542502.8 | AG54: =AF54/$AF$21 -> 0.21081439 | AH54: =AF54/$AF$9 -> 42.660071 | AI54: =AF54/$B$2 -> 10862.696 | AJ54: =AJ52-AJ53 -> 1769029.3 | AK54: =AJ54/$AJ$21 -> 0.22868177 | AL54: =AJ54/$AJ$9 -> 47.797394 | AM54: =AJ54/$B$2 -> 12457.953 | AN54: =AN52-AN53 -> 1955239.9 | AO54: =AN54/$AN$21 -> 0.233291 | AP54: =AN54/$AN$9 -> 54.472612 | AQ54: =AN54/$B$2 -> 13769.295 | AR54: =AR52-AR53 -> 2544861 | AS54: =AR54/$AR$21 -> 0.26261093 | AT54: =AR54/$AR$9 -> 64.045828 | AU54: =AR54/$B$2 -> 17921.556 | AV54: =AV52-AV53 -> 2704275 | AW54: =AV54/$AV$21 -> 0.26719908 | AX54: =AV54/$AV$9 -> 65.322231 | AY54: =AV54/$B$2 -> 19044.19 | AZ54: =AZ52-AZ53 -> 2719927.1 | BA54: =AZ54/$AZ$21 -> 0.26542246 | BB54: =AZ54/$AZ$9 -> 65.578338 | BC54: =AZ54/$B$2 -> 19154.416 | BD54: =BD52-BD53 -> 2738948.8 | BE54: =BD54/$BD$21 -> 0.26377992 | BF54: =BD54/$BD$9 -> 65.855945 | BG54: =BD54/$B$2 -> 19288.372 | BH54: =BH52-BH53 -> 2736641.6 | BI54: =BH54/$BH$21 -> 0.26122753 | BJ54: =BH54/$BH$9 -> 65.981328 | BK54: =BH54/$B$2 -> 19272.124 | BL54: =BL52-BL53 -> 2744718.9 | BM54: =BL54/$BL$21 -> 0.25910896 | BN54: =BL54/$BL$9 -> 66.176075 | BO54: =BL54/$B$2 -> 19329.006 | BP54: =BP52-BP53 -> 2752600.5 | BQ54: =BP54/$BP$21 -> 0.25697644 | BR54: =BP54/$BL$9 -> 66.366102 | BS54: =BP54/$B$2 -> 19384.51 | BT54: =BT52-BT53 -> 2771197.7 | BU54: =BT54/$BP$21 -> 0.25871264 | BV54: =BT54/$BL$9 -> 66.814488 | BW54: =BT54/$B$2 -> 19515.477
A57: 1 - Market value
A58: https://hypofriend.de/en/mortgage-rates-germany/hesse/wiesbaden
A59: Discount rate | B59: ='PRELIMINARY ANALYSIS'!$F$42 -> 0.0695
A60: Adjusted Cap Rate | B60: ='PRELIMINARY ANALYSIS'!$F$50 -> 0.061479747
A61: Going out Cap Rate ( = +0.5%) | B61: =B60+0.5% -> 0.066479747
A62: Property Discount Rate | B62: =B61+B4 -> 0.0745
A63: Sales transaction cost | B63: 0.06
B64: -1 | C64: 0 | D64: 1 | E64: 2 | F64: 3 | G64: 4 | H64: 5 | I64: 6 | J64: 7 | K64: 8 | L64: 9 | M64: 10
A65: Year | B65: 2024 | C65: 2025 | D65: 2026 | E65: 2027 | F65: 2028 | G65: 2029 | H65: 2030 | I65: 2031 | J65: 2032 | K65: 2033 | L65: 2034 | M65: 2035
A66: EBITDA aRR | C66: =AB54 -> 1545299.7 | D66: =AF54 -> 1542502.8 | E66: =AJ54 -> 1769029.3 | F66: =AN54 -> 1955239.9 | G66: =AR54 -> 2544861 | H66: =AV54 -> 2704275 | I66: =AZ54 -> 2719927.1 | J66: =BD54 -> 2738948.8 | K66: =BH54 -> 2736641.6 | L66: =BL54 -> 2744718.9 | M66: =BP54 -> 2752600.5
A67: Exit value | M67: =M66/B61 -> 41405098
A68: Transaction cost | M68: =-M67*B63 -> -2484305.9
A69: Initial investment | B69: =-21000000 -> -21000000
A70: Total CF | B70: =SUM(B66:B69) -> -21000000 | C70: =SUM(C66:C69) -> 1545299.7 | D70: =SUM(D66:D69) -> 1542502.8 | E70: =SUM(E66:E69) -> 1769029.3 | F70: =SUM(F66:F69) -> 1955239.9 | G70: =SUM(G66:G69) -> 2544861 | H70: =SUM(H66:H69) -> 2704275 | I70: =SUM(I66:I69) -> 2719927.1 | ... M70: =SUM(M66:M69) -> 41673393
A72: Incremental Value | B72: =NPV(B59,C70:M70) -> 35456540
A73: Market Value | B73: =NPV(B62,C70:M70) -> 34063982
A74: Net Present Value | B74: =NPV(B59,C70:M70)+B70 -> 14456540
A75: IRR | B75: =IRR(B70:M70) -> 0.13956885
A76: MIRR | B76: =MIRR(B70:M70,B59,B59) -> 0.12165816

Sheet 1-F&B
A1: 1- F&B in details
A2: Inflation Rate | B2: ='PRELIMINARY ANALYSIS'!K23 -> 0.021181818 | F2: 2026 | H2: 2027 | J2: 2028 | L2: 2029 | N2: 2030 | P2: 2031 | R2: 2032 | T2: 2033 | V2: 2034 | X2: 2035 | Z2: 2036 | AC2: COMPETITOR | AD2: MEETING, €/person | AF2: BREAKFAST | AG2: LUNCH | AH2: DINNER | AI2: DRINKS
A3: STR Report 2023 F&B Cost of Sales | B3: ='APPENDIX 1-STR Trend '!E64/100 -> 0.818 | AC3: Hyatt Regency Mainz | AD3: =109-55 -> 54 | AE3: Average starters | AG3: - | AH3: =AVERAGE(17,24,24.5,24,19,12) -> 20.083333 | AI3: =AVERAGE(4.6,4.3,4.7,4.9,5,5,5,3,6,1,7) -> 4.5909091 | AJ3: Coffee
A4: STR Report 2023 F&B Labor Cost | B4: ='APPENDIX 1-STR Trend '!E112/100 -> 0.515
A5: VAT Deutschland (Future new law might decrease rate to 7% on Food) | B5: 0.19 | C5: Source | E5: Room sold | F5: ='1-P&L Modified'!AF9 -> 36158 | H5: ='1-P&L Modified'!AJ9 -> 37011 | J5: ='1-P&L Modified'!AN9 -> 35894 | L5: ='1-P&L Modified'!AR9 -> 39735 | N5: ='1-P&L Modified'!AV9 -> 41399 | P5: ='1-P&L Modified'!AZ9 -> 41476 | R5: ='1-P&L Modified'!BD9 -> 41590 | T5: ='1-P&L Modified'!BH9 -> 41476 | V5: ='1-P&L Modified'!BL9 -> 41476 | X5: ='1-P&L Modified'!BP9 -> 41476 | Z5: ='1-P&L Modified'!BT9 -> 41590 | AE5: Average Mains | AF5: =AVERAGE(34,25,17) -> 25.333333 | AG5: 25 | AH5: =AVERAGE(39,37,32,39,26,52,59,36,28,36,7,9,110,9) -> 37.071429 | AI5: =AVERAGE(4.2,9.5,4.5,7,5,5) -> 5.8666667 | AJ5: Soft
AE6: Average Dessert | AG6: - | AH6: =AVERAGE(15,15,15,19) -> 16 | AI6: =AVERAGE(8,18,20,5,5,6,6,6,6,6,8.5,9) -> 8.625 | AJ6: Wine
A7: BREAKFAST at Le Capricorne | AE7: Average Beverage | AG7: 5 | AH7: =AVERAGE(6,7,7.5,7.5,8.5,9.5,8,9,9,9.5,18,20,7.5,8,8.5,8.5,9.5,10) -> 9.5277778 | AI7: =AVERAGE(10,10,10,10,10,10,12,12,13,13,13,13,13,11,11,12,13,13,12,13,15) -> 11.857143 | AJ7: Coktail
E8: #days open per week | F8: 7 | H8: 7 | J8: 7 | L8: 7 | N8: 7 | P8: 7 | R8: 7 | T8: 7 | V8: 7 | X8: 7 | Z8: 7 | AI8: =AVERAGE(6,29,16,15,5) -> 14.2 | AJ8: Snacks
A9: Catpure Rate | B9: =AE31 -> 0.82 | E9: Number of days open | F9: 365 | H9: 365 | J9: 365 | L9: 365 | N9: 365 | P9: 365 | R9: 365 | T9: 365 | V9: 365 | X9: 365 | Z9: 365 | AC9: Hotel Nassauer Hof | AD9: 44 | AE9: Average starters | AG9: =AVERAGE(9,28,28,28,15) -> 21.6 | AH9: =AVERAGE(19,18,23,24,22,21) -> 21.166667 | AI9: =AVERAGE(3.8,4,6,6,6,7,12) -> 6.4 | AJ9: Coffee
A10: Number of guest per room | B10: 1.3 | AE10: Average Mains | AG10: =AVERAGE(31,52,54,48,24,) -> 34.833333 | AH10: =AVERAGE(30,39,32,38,29,37) -> 34.166667 | AI10: =AVERAGE(5,10.5,5,5,9) -> 6.9 | AJ10: Soft
A11: Open Daily | E11: Number of seats | F11: 80 | H11: 80 | J11: 80 | L11: 80 | N11: 80 | P11: 80 | R11: 80 | T11: 80 | V11: 80 | X11: 80 | Z11: 80 | AE11: Average Dessert | AG11: =AVERAGE(9,16,20,2.5,5.5) -> 10.6 | AH11: =AVERAGE(15,15,15,9) -> 13.5 | AI11: =AVERAGE(5,8,7,7) -> 6.75 | AJ11: Beer
A12: We estimated a capture rate according to our projected guest segment mix. Same for guest per room. Cost of sales decrease thanks to buffet (less staff cost) | E12: Capture rate | F12: =$B$9 -> 0.82 | H12: =$B$9 -> 0.82 | J12: =$B$9 -> 0.82 | L12: =$B$9 -> 0.82 | N12: =$B$9 -> 0.82 | P12: =$B$9 -> 0.82 | R12: =$B$9 -> 0.82 | T12: =$B$9 -> 0.82 | V12: =$B$9 -> 0.82 | X12: =$B$9 -> 0.82 | Z12: =$B$9 -> 0.82 | AE12: Snacks | AG12: =AVERAGE(18,26,32) -> 25.333333 | AI12: =AVERAGE(18,23,12,19) -> 18 | AJ12: Cocktail
E13: Total Covers per Year | F13: =F12*F5*$B$10 -> 38544.428 | H13: =H12*H5*$B$10 -> 39453.726 | J13: =J12*J5*$B$10 -> 38263.004 | L13: =L12*L5*$B$10 -> 42357.51 | N13: =N12*N5*$B$10 -> 44131.334 | P13: =P12*P5*$B$10 -> 44213.416 | R13: =R12*R5*$B$10 -> 44334.94 | T13: =T12*T5*$B$10 -> 44213.416 | V13: =V12*V5*$B$10 -> 44213.416 | X13: =X12*X5*$B$10 -> 44213.416 | Z13: =Z12*Z5*$B$10 -> 44334.94 | AI13: =AVERAGE(10,12,18,20,14,12,14,12,15,14,16,14,15,14,10) -> 14 | AJ13: Wine
E14: Average Check | F14: =AF31 -> 16.318 | H14: =F14*(1+Inflation) -> 16.663645 | J14: =H14*(1+Inflation) -> 17.016611 | L14: =J14*(1+Inflation) -> 17.377054 | N14: =L14*(1+Inflation) -> 17.745132 | P14: =N14*(1+Inflation) -> 18.121006 | R14: =P14*(1+Inflation) -> 18.504842 | T14: =R14*(1+Inflation) -> 18.896808 | V14: =T14*(1+Inflation) -> 19.297077 | X14: =V14*(1+Inflation) -> 19.705824 | Z14: =X14*(1+Inflation) -> 20.123229 | AC14: Mercure Hotel Wiesbaden City | AE14: Average starters | AF14: 20 | AG14: =AVERAGE(17,16.5,16,7.5,11) -> 13.6 | AH14: =AVERAGE(17,16.5,16,7.5,11) -> 13.6
C15: Total Outlet Revenue | F15: =F14*F13*(1-VAT) -> 509464.06 | H15: =H14*H13*(1-VAT) -> 532528.73 | J15: =J14*J13*(1-VAT) -> 527396.4 | L15: =L14*L13*(1-VAT) -> 596199.48 | N15: =N14*N13*(1-VAT) -> 634324.23 | P15: =P14*P13*(1-VAT) -> 648965.17 | R15: =R14*R13*(1-VAT) -> 664532.94 | T15: =T14*T13*(1-VAT) -> 676748.86 | V15: =V14*V13*(1-VAT) -> 691083.63 | X15: =X14*X13*(1-VAT) -> 705722.04 | Z15: =Z14*Z13*(1-VAT) -> 722651.34 | AE15: Average Mains | AG15: =AVERAGE(21.6,29.5,29.5,16.5,16,15,17,15.5,38.5,39,30,40.5) -> 25.716667 | AH15: =AVERAGE(21.6,29.5,29.5,16.5,16,15,17,15.5,38.5,39,30,40.5) -> 25.716667
C16: Cost of sales | D16: Adjusted cost rate | E16: =$B$3-15% -> 0.668 | F16: =F15*$E$16 -> 340321.99 | H16: =H15*$E$16 -> 355729.19 | J16: =J15*$E$16 -> 352300.79 | L16: =L15*$E$16 -> 398261.25 | N16: =N15*$E$16 -> 423728.58 | P16: =P15*$E$16 -> 433508.73 | R16: =R15*$E$16 -> 443908.01 | T16: =T15*$E$16 -> 452068.24 | V16: =V15*$E$16 -> 461643.87 | X16: =X15*$E$16 -> 471422.32 | Z16: =Z15*$E$16 -> 482731.09 | AE16: Average Dessert | AG16: =AVERAGE(8.5,8.5,14.5) -> 10.5 | AH16: =AVERAGE(8.5,8.5,14.5) -> 10.5
C17: Total Profit | F17: =F15-F16 -> 169142.07 | H17: =H15-H16 -> 176799.54 | J17: =J15-J16 -> 175095.6 | L17: =L15-L16 -> 197938.23 | N17: =N15-N16 -> 210595.64 | P17: =P15-P16 -> 215456.44 | R17: =R15-R16 -> 220624.94 | T17: =T15-T16 -> 224680.62 | V17: =V15-V16 -> 229439.77 | X17: =X15-X16 -> 234299.72 | Z17: =Z15-Z16 -> 239920.24 | AE17: Wine | AG17: =AVERAGE(7.5,8,8,8.5,8.5,8.5,15.5,8,8,8.5,8.5,8.5,10) -> 8.9230769 | AH17: =AVERAGE(7.5,8,8,8.5,8.5,8.5,15.5,8,8,8.5,8.5,8.5,10) -> 8.9230769
AC19: Dorint Pallas Wiesbaden | AE19: Average starters | AG19: =AVERAGE(11.5,14.5,18.5,24.5,27.5) -> 19.3 | AH19: =AVERAGE(11.5,14.5,18.5,24.5,27.5) -> 19.3
AE20: Average Mains | AG20: =AVERAGE(27.5,35,36.5,22.5) -> 30.375 | AH20: =AVERAGE(27.5,35,36.5) -> 33
AE21: Average Dessert | AG21: =AVERAGE(14.5,14.5,15,19) -> 15.75 | AH21: =AVERAGE(14.5,14.5,15,19) -> 15.75
A22: BRASSERIE & TERRACE Le Capricorne | F22: Lunch | G22: Dinner | H22: Lunch | I22: Dinner | J22: Lunch | K22: Dinner | L22: Lunch | M22: Dinner | N22: Lunch | O22: Dinner | P22: Lunch | Q22: Dinner | R22: Lunch | S22: Dinner | T22: Lunch | U22: Dinner | V22: Lunch | W22: Dinner | X22: Lunch | Y22: Dinner | Z22: Lunch | AA22: Dinner
A23: Open from tuesday to saturday - Lunch & Dinner | E23: #days open per week | F23: 5 | G23: 5 | H23: 5 | I23: 5 | J23: 5 | K23: 5 | L23: 5 | M23: 5 | N23: 5 | O23: 5 | P23: 5 | Q23: 5 | R23: 5 | S23: 5 | T23: 5 | U23: 5 | V23: 5 | W23: 5 | X23: 5 | Y23: 5 | Z23: 5 | AA23: 5 | AC23: Hotel Oranien Wiesbaden | AD23: =AVERAGE(75,79)-AG24 -> 47.65 | AE23: Average starters | AF23: 21 | AG23: =AVERAGE(9,10.5,11.5,11.8,7.5,16.8,19.2,18.5,19.8) -> 13.844444 | AH23: =AVERAGE(9,10.5,11.5,11.8,7.5,16.8,19.2,18.5,19.8) -> 13.844444 | AI23: =AVERAGE(3.4,3.9,4.2,7.5) -> 4.75 | AJ23: Coffee
A24: Cost of sales increase due to : | E24: Number of days open | F24: =F23*52 -> 260 | G24: =G23*52 -> 260 | H24: =H23*52 -> 260 | I24: =I23*52 -> 260 | J24: =J23*52 -> 260 | K24: =K23*52 -> 260 | L24: =L23*52 -> 260 | M24: =M23*52 -> 260 | ... AA24: =AA23*52 -> 260 | AE24: Average Mains | AG24: =AVERAGE(18.5+7.5, 18.5,32.5,26.8,29.5,30.5,34.5,36.5) -> 29.35 | AH24: =AVERAGE(18.5+7.5, 18.5,32.5,26.8,29.5,30.5,34.5,36.5) -> 29.35 | AI24: =AVERAGE(8.9,9.8,9,11.5,9,9.8,9,9,9,10.5,9.8,) -> 8.775 | AJ24: Wine
A25: Higher quality products | AE25: Average Dessert | AG25: =AVERAGE(10.5,12.5,12.8,10.5,14.8) -> 12.22 | AH25: =AVERAGE(10.5,12.5,12.8,10.5,14.8) -> 12.22 | AI25: =AVERAGE(4.9,4.9,6.2,5.9) -> 5.475 | AJ25: Beer
A26: More high-end service | E26: Number of seats | F26: 80 | G26: 80 | H26: 80 | I26: 80 | J26: 80 | K26: 80 | L26: 80 | M26: 80 | N26: 80 | O26: 80 | P26: 80 | Q26: 80 | R26: 80 | S26: 80 | T26: 80 | U26: 80 | V26: 80 | W26: 80 | X26: 80 | Y26: 80 | Z26: 80 | AA26: 80 | AE26: Wine | AH26: =AVERAGE(8.9,9.8,9,11.5,9,9.8,9,9,9,10.5,9.8,) -> 8.775 | AI26: =AVERAGE(10,10,10,10,12,7.5,7.5) -> 9.5714286 | AJ26: Cocktail
E27: Average Covers per service | F27: =($AJ$51*$AK$51+$AJ$53*$AK$53)/52 *(1-0.1) -> 45.519231 | G27: =($AJ$52*$AK$52+$AJ$54*$AK$54)/52*(1-0.1) -> 42.507692 | H27: =($AJ$51*$AK$51+$AJ$53*$AK$53)/52*(1-0.05) -> 48.048077 | I27: =($AJ$52*$AK$52+$AJ$54*$AK$54)/52*(1-0.05) -> 44.869231 | J27: =($AJ$51*$AK$51+$AJ$53*$AK$53)/52 -> 50.576923 | K27: =($AJ$52*$AK$52+$AJ$54*$AK$54)/52 -> 47.230769 | L27: =($AJ$51*$AK$51+$AJ$53*$AK$53)/52 -> 50.576923 | M27: =($AJ$52*$AK$52+$AJ$54*$AK$54)/52 -> 47.230769 | N27: =($AJ$51*$AK$51+$AJ$53*$AK$53)/52 -> 50.576923 | O27: =($AJ$52*$AK$52+$AJ$54*$AK$54)/52 -> 47.230769 | P27: =($AJ$51*$AK$51+$AJ$53*$AK$53)/52 -> 50.576923 | Q27: =($AJ$52*$AK$52+$AJ$54*$AK$54)/52 -> 47.230769 | R27: =($AJ$51*$AK$51+$AJ$53*$AK$53)/52 -> 50.576923 | S27: =($AJ$52*$AK$52+$AJ$54*$AK$54)/52 -> 47.230769 | T27: =($AJ$51*$AK$51+$AJ$53*$AK$53)/52 -> 50.576923 | U27: =($AJ$52*$AK$52+$AJ$54*$AK$54)/52 -> 47.230769 | V27: =($AJ$51*$AK$51+$AJ$53*$AK$53)/52 -> 50.576923 | W27: =($AJ$52*$AK$52+$AJ$54*$AK$54)/52 -> 47.230769 | X27: =($AJ$51*$AK$51+$AJ$53*$AK$53)/52 -> 50.576923 | Y27: =($AJ$52*$AK$52+$AJ$54*$AK$54)/52 -> 47.230769 | Z27: =($AJ$51*$AK$51+$AJ$53*$AK$53)/52 -> 50.576923 | AA27: =($AJ$52*$AK$52+$AJ$54*$AK$54)/52 -> 47.230769
E28: Occupancy | F28: =F27/F26 -> 0.56899038 | G28: =G27/G26 -> 0.53134615 | H28: =H27/H26 -> 0.60060096 | I28: =I27/I26 -> 0.56086538 | J28: =J27/J26 -> 0.63221154 | K28: =K27/K26 -> 0.59038462 | L28: =L27/L26 -> 0.63221154 | M28: =M27/M26 -> 0.59038462 | ... AA28: =AA27/AA26 -> 0.59038462
E29: Average Check | F29: =AF36 -> 36.683694 | G29: =AF41 -> 52.749008 | H29: =F29*(1+$B$2) -> 37.460722 | I29: =G29*(1+$B$2) -> 53.866328 | J29: =H29*(1+$B$2) -> 38.254208 | K29: =I29*(1+$B$2) -> 55.007315 | L29: =J29*(1+$B$2) -> 39.064502 | M29: =K29*(1+$B$2) -> 56.17247 | N29: =L29*(1+$B$2) -> 39.891959 | O29: =M29*(1+$B$2) -> 57.362305 | ... AA29: =Y29*(1+$B$2) -> 65.04966 | AC29: AVERAGE CHECK BENCHMARK
C30: Total Outlet Revenue | F30: =F29*F27*F24*(1-VAT) -> 351662.73 | G30: =G29*G27*G24*(1-VAT) -> 472215.45 | H30: =H29*H27*H24*(1-VAT) -> 379062.23 | I30: =I29*I27*I24*(1-VAT) -> 509007.71 | J30: =J29*J27*J24*(1-VAT) -> 407464.7 | K30: =K29*K27*K24*(1-VAT) -> 547146.76 | L30: =L29*L27*L24*(1-VAT) -> 416095.54 | M30: =M29*M27*M24*(1-VAT) -> 558736.32 | ... AA30: =AA29*AA27*AA24*(1-VAT) -> 647035.96 | AD30: AVERAGE | AE30: CAPTURE RATE | AG30: Assumptions
C31: Cost of sales | D31: Adjusted cost rate | E31: =$B$3+2% -> 0.838 | F31: =F30*$E$31 -> 294693.37 | G31: =G30*$E$31 -> 395716.55 | H31: =H30*$E$31 -> 317654.15 | I31: =I30*$E$31 -> 426548.46 | J31: =J30*$E$31 -> 341455.42 | K31: =K30*$E$31 -> 458508.98 | L31: =L30*$E$31 -> 348688.06 | M31: =M30*$E$31 -> 468221.04 | ... AA31: =AA30*$E$31 -> 542216.14 | AC31: Breakfast | AD31: Average Check (inc VAT) | AE31: 0.82 | AF31: =AVERAGE(AF5,AF14,AF23)*AE31*0.9 -> 16.318 | AG31: Minus 10% for Breakfast+room package
C32: Total Profit | F32: =F30-F31 -> 56969.363 | G32: =G30-G31 -> 76498.903 | H32: =H30-H31 -> 61408.082 | I32: =I30-I31 -> 82459.249 | J32: =J30-J31 -> 66009.281 | K32: =K30-K31 -> 88637.775 | L32: =L30-L31 -> 67407.477 | M32: =M30-M31 -> 90515.284 | ... AA32: =AA30-AA31 -> 104819.83 | AC32: Lunch | AD32: Starters | AE32: 0.1 | AF32: =AVERAGE(AG3,AG9,AG14,AG19,AG23)*AE32 -> 1.7086111
AD33: Mains | AE33: 1 | AF33: =AVERAGE(AG5,AG10,AG15,AG20,AG24)*AE33 -> 29.055
AD34: Desserts | AE34: 0.1 | AF34: =AVERAGE(AG6,AG11,AG16,AG21,AG25)*AE34 -> 1.22675
AD35: Drinks | AE35: 0.8 | AF35: =AI5*AE35 -> 4.6933333
A36: ECK BAR / Lobby | AD36: Average Check (inc VAT) | AF36: =SUM(AF32:AF35) -> 36.683694
A37: Open Daily | E37: #days open per week | F37: 7 | H37: 7 | J37: 7 | L37: 7 | N37: 7 | P37: 7 | R37: 7 | T37: 7 | V37: 7 | X37: 7 | Z37: 7 | AC37: Dinner | AD37: Starters | AE37: 0.4 | AF37: =AVERAGE(AH3,AH9,AH14,AH19,AH23)*AE37 -> 7.0395556
A38: Serving drinks and snacks | E38: Number of days open | F38: 365 | H38: =2*30 -> 60 | J38: 365 | L38: 365 | N38: 365 | P38: 365 | R38: 365 | T38: 365 | V38: 365 | X38: 365 | Z38: 365 | AD38: Mains | AE38: 1 | AF38: =AVERAGE(AH5,AH10,AH15,AH20,AH24)*AE38 -> 31.860952
A39: Cost of sales decrease due to : | AD39: Desserts | AE39: 0.25 | AF39: =AVERAGE(AH6,AH11,AH16,AH21,AH25)*AE39 -> 3.3985
A40: Less staff | E40: Number of seats | F40: 60 | H40: 60 | J40: 60 | L40: 70 | N40: 70 | P40: 70 | R40: 70 | T40: 70 | V40: 70 | X40: 70 | Z40: 70 | AD40: Drinks | AE40: 1 | AF40: =AVERAGE(AI13,AI10)*AE40 -> 10.45
A41: Higher margins on drinks | E41: Average Covers per day | F41: 40 | H41: 40 | J41: =(5*60+2*50)/7 -> 57.142857 | L41: =(5*60+2*50)/7 -> 57.142857 | N41: =(5*60+2*50)/7 -> 57.142857 | P41: =(5*60+2*50)/7 -> 57.142857 | R41: =(5*60+2*50)/7 -> 57.142857 | T41: =(5*60+2*50)/7 -> 57.142857 | V41: =(5*60+2*50)/7 -> 57.142857 | X41: =(5*60+2*50)/7 -> 57.142857 | Z41: =(5*60+2*50)/7 -> 57.142857 | AD41: Average Check (inc VAT) | AF41: =SUM(AF37:AF40) -> 52.749008
E42: Occupancy | F42: =F41/F40 -> 0.66666667 | H42: =H41/H40 -> 0.66666667 | J42: =J41/J40 -> 0.95238095 | L42: =L41/L40 -> 0.81632653 | N42: =N41/N40 -> 0.81632653 | P42: =P41/P40 -> 0.81632653 | R42: =R41/R40 -> 0.81632653 | T42: =T41/T40 -> 0.81632653 | V42: =V41/V40 -> 0.81632653 | X42: =X41/X40 -> 0.81632653 | Z42: =Z41/Z40 -> 0.81632653 | AC42: Meetings & Events | AD42: Coffee break + soft drinks, pastries | AF42: =AVERAGE(AD3,AD9,AD23) -> 48.55
A43: https://www.lhotellerie-restauration.fr/sos-experts/ratios-financiers-les-cafes-bars | E43: Average Check | F43: =AF46 -> 15.45551 | H43: =F43*(1+$B$2) -> 15.782886 | J43: =H43*(1+$B$2) -> 16.117196 | L43: =J43*(1+$B$2) -> 16.458588 | N43: =L43*(1+$B$2) -> 16.807211 | P43: =N43*(1+$B$2) -> 17.163218 | R43: =P43*(1+$B$2) -> 17.526766 | T43: =R43*(1+$B$2) -> 17.898015 | V43: =T43*(1+$B$2) -> 18.277127 | X43: =V43*(1+$B$2) -> 18.66427 | Z43: =X43*(1+$B$2) -> 19.059613 | AD43: Average Check (inc VAT) | AF43: =SUM(AF42) -> 48.55
C44: Total Outlet Revenue | F44: =F43*F41*F38*(1-VAT) -> 182776.86 | H44: =H43*H41*H38*(1-VAT)*25% -> 7670.4826 | J44: =J43*J41*J38*(1-VAT) -> 272288.52 | L44: =L43*L41*L38*(1-VAT) -> 278056.08 | N44: =N43*N41*N38*(1-VAT) -> 283945.82 | P44: =P43*P41*P38*(1-VAT) -> 289960.31 | R44: =R43*R41*R38*(1-VAT) -> 296102.19 | T44: =T43*T41*T38*(1-VAT) -> 302374.18 | V44: =V43*V41*V38*(1-VAT) -> 308779.01 | X44: =X43*X41*X38*(1-VAT) -> 315319.51 | Z44: =Z43*Z41*Z38*(1-VAT) -> 321998.55 | AC44: Bar | AD44: Drinks | AE44: 1 | AF44: =AVERAGE(AI6:AI7,AI9,AI11:AI12,AI25:AI26)*AE44 -> 9.5255102
C45: Cost of sales | D45: Adjusted cost rate | E45: =$B$3-10% -> 0.718 | F45: =F44*$E$45 -> 131233.79 | H45: =H44*$E$45 -> 5507.4065 | J45: =J44*$E$45 -> 195503.16 | L45: =L44*$E$45 -> 199644.27 | N45: =N44*$E$45 -> 203873.1 | P45: =P44*$E$45 -> 208191.5 | R45: =R44*$E$45 -> 212601.37 | T45: =T44*$E$45 -> 217104.66 | V45: =V44*$E$45 -> 221703.33 | X45: =X44*$E$45 -> 226399.41 | Z45: =Z44*$E$45 -> 231194.96 | AD45: Snack | AE45: 0.3 | AF45: =AVERAGE(AI8,AG12)*AE45 -> 5.93
C46: Total Profit | F46: =F44-F45 -> 51543.076 | H46: =H44-H45 -> 2163.0761 | J46: =J44-J45 -> 76785.362 | L46: =L44-L45 -> 78411.816 | N46: =N44-N45 -> 80072.72 | P46: =P44-P45 -> 81768.806 | R46: =R44-R45 -> 83500.818 | T46: =T44-T45 -> 85269.517 | V46: =V44-V45 -> 87075.681 | X46: =X44-X45 -> 88920.102 | Z46: =Z44-Z45 -> 90803.592 | AD46: Average Check (inc VAT) | AF46: =SUM(AF44:AF45) -> 15.45551
AC48: Brasserie & Terrace
AC49: Low season in summer/holidays will be compensate by the terrasse | AF49: We esimated covers by taking into account more Business guest in high season during the week, less in weekends, more leisure, etc.
A50: MEETINGS & EVENTS | AC50: #Covers Estimation | AE50: Tuesday | AF50: Wednesday | AG50: Thursday | AH50: Friday | AI50: Saturday | AJ50: Average | AK50: #weeks
A51: Available daily | E51: #days open per week | F51: 7 | H51: 7 | J51: 7 | L51: 7 | N51: 7 | P51: 7 | R51: 7 | T51: 7 | V51: 7 | X51: 7 | Z51: 7 | AC51: High season | AD51: Lunch | AE51: 50 | AF51: 50 | AG51: 60 | AH51: 60 | AI51: 55 | AJ51: =AVERAGE(AE51:AI51) -> 55 | AK51: 38
A52: We estimated the occupancy 3 days/week during high season (38 weeks) | E52: Number of days open | F52: =3*38 -> 114 | H52: =3*38 -> 114 | J52: =3*38 -> 114 | L52: =3*38 -> 114 | N52: =3*38 -> 114 | P52: =3*38 -> 114 | R52: =3*38 -> 114 | T52: =3*38 -> 114 | V52: =3*38 -> 114 | X52: =3*38 -> 114 | Z52: =3*38 -> 114 | AC52: High season | AD52: Dinner | AE52: 50 | AF52: 60 | AG52: 55 | AH52: 50 | AI52: 45 | AJ52: =AVERAGE(AE52:AI52) -> 52 | AK52: 38
A53: Cost of sales decrease thanks to : | AC53: Low season | AD53: Lunch | AE53: 35 | AF53: 45 | AG53: 45 | AH53: 50 | AI53: 50 | AJ53: =AVERAGE(AE53:AI53) -> 45 | AK53: 12
A54: Mostly coffee, water, small pastries with less staff needed | E54: Number of seats | F54: 300 | H54: 300 | J54: 300 | L54: 300 | N54: 300 | P54: 300 | R54: 300 | T54: 300 | V54: 300 | X54: 300 | Z54: 300 | AC54: Low season | AD54: Dinner | AE54: 35 | AF54: 35 | AG54: 40 | AH54: 45 | AI54: 45 | AJ54: =AVERAGE(AE54:AI54) -> 40 | AK54: 12
E55: Average Covers per day | F55: 95 | H55: =F55 -> 95 | J55: =H55 -> 95 | L55: =J55 -> 95 | N55: =L55 -> 95 | P55: =N55 -> 95 | R55: =P55 -> 95 | T55: =R55 -> 95 | V55: =T55 -> 95 | X55: =V55 -> 95 | Z55: =X55 -> 95
E56: Occupancy | F56: =F55/F54 -> 0.31666667 | H56: =H55/H54 -> 0.31666667 | J56: =J55/J54 -> 0.31666667 | L56: =L55/L54 -> 0.31666667 | N56: =N55/N54 -> 0.31666667 | P56: =P55/P54 -> 0.31666667 | R56: =R55/R54 -> 0.31666667 | T56: =T55/T54 -> 0.31666667 | V56: =V55/V54 -> 0.31666667 | X56: =X55/X54 -> 0.31666667 | Z56: =Z55/Z54 -> 0.31666667
E57: Average Check | F57: =AF43 -> 48.55 | H57: =F57*(1+$B$2) -> 49.578377 | J57: =H57*(1+$B$2) -> 50.628537 | L57: =J57*(1+$B$2) -> 51.700942 | N57: =L57*(1+$B$2) -> 52.796062 | P57: =N57*(1+$B$2) -> 53.914378 | R57: =P57*(1+$B$2) -> 55.056383 | T57: =R57*(1+$B$2) -> 56.222577 | V57: =T57*(1+$B$2) -> 57.413474 | X57: =V57*(1+$B$2) -> 58.629595 | Z57: =X57*(1+$B$2) -> 59.871477
C58: Total Outlet Revenue | F58: =F57*F55*F52*(1-VAT) -> 425895.17 | H58: =H57*H55*H52*(1-VAT) -> 434916.4 | J58: =J57*J55*J52*(1-VAT) -> 444128.72 | L58: =L57*L55*L52*(1-VAT) -> 453536.17 | N58: =N57*N55*N52*(1-VAT) -> 463142.89 | P58: =P57*P55*P52*(1-VAT) -> 472953.1 | R58: =R57*R55*R52*(1-VAT) -> 482971.11 | T58: =T57*T55*T52*(1-VAT) -> 493201.31 | V58: =V57*V55*V52*(1-VAT) -> 503648.22 | X58: =X57*X55*X52*(1-VAT) -> 514316.4 | Z58: =Z57*Z55*Z52*(1-VAT) -> 525210.56
C59: Cost of sales | D59: Adjusted cost rate | E59: =$B$3-15% -> 0.668 | F59: =F58*$E$59 -> 284497.97 | H59: =H58*$E$59 -> 290524.15 | J59: =J58*$E$59 -> 296677.98 | L59: =L58*$E$59 -> 302962.16 | N59: =N58*$E$59 -> 309379.45 | P59: =P58*$E$59 -> 315932.67 | R59: =R58*$E$59 -> 322624.7 | T59: =T58*$E$59 -> 329458.48 | V59: =V58*$E$59 -> 336437.01 | X59: =X58*$E$59 -> 343563.36 | Z59: =Z58*$E$59 -> 350840.65
C60: Total Profit | F60: =F58-F59 -> 141397.19 | H60: =H58-H59 -> 144392.24 | J60: =J58-J59 -> 147450.73 | L60: =L58-L59 -> 150574.01 | N60: =N58-N59 -> 153763.44 | P60: =P58-P59 -> 157020.43 | R60: =R58-R59 -> 160346.41 | T60: =T58-T59 -> 163742.84 | V60: =V58-V59 -> 167211.21 | X60: =X58-X59 -> 170753.04 | Z60: =Z58-Z59 -> 174369.9
A64: CAFE INGELHEIMER | F64: Day | G64: Evening | H64: Day | I64: Evening | J64: Day | K64: Evening | L64: Day | M64: Evening | N64: Day | O64: Evening | P64: Day | Q64: Evening | R64: Day | S64: Evening | T64: Day | U64: Evening | V64: Day | W64: Evening | X64: Day | Y64: Evening | Z64: Day | AA64: Evening
A65: Open 5 days/w + evening upon request for afterwork / wine tasting | E65: #days open per week | F65: 0 | G65: 0 | H65: 5 | I65: 2.5 | J65: 5 | K65: 2.5 | L65: 5 | M65: 2.5 | N65: 5 | O65: 2.5 | P65: 5 | Q65: 2.5 | R65: 5 | S65: 2.5 | T65: 5 | U65: 2.5 | V65: 5 | W65: 2.5 | X65: 5 | Y65: 2.5 | Z65: 5 | AA65: 2.5
A66: Estimaed coffe price + pastries | E66: Number of days open | F66: =F65*52 -> 0 | G66: =G65*52 -> 0 | H66: =H65*52 -> 260 | I66: =I65*52 -> 130 | J66: =J65*52 -> 260 | K66: =K65*52 -> 130 | L66: =L65*52 -> 260 | M66: =M65*52 -> 130 | ... AA66: =AA65*52 -> 130
A67: Estimated 2 to 3 evenings with wine tasting for afterworks
A68: (Wine price volontary low to try this new offer) | E68: Number of seats | F68: 0 | G68: 0 | H68: 40 | I68: 40 | J68: 40 | K68: 40 | L68: 40 | M68: 40 | N68: 40 | O68: 40 | P68: 40 | Q68: 40 | R68: 40 | S68: 40 | T68: 40 | U68: 40 | V68: 40 | W68: 40 | X68: 40 | Y68: 40 | Z68: 40 | AA68: 40
E69: Average Covers per day | F69: 0 | G69: 0 | H69: 55 | I69: 17 | J69: 55 | K69: 17 | L69: 55 | M69: 17 | N69: 55 | O69: 17 | P69: 55 | Q69: 17 | R69: 55 | S69: 17 | T69: 55 | U69: 17 | V69: 55 | W69: 17 | X69: 55 | Y69: 17 | Z69: 55 | AA69: 17
E70: Occupancy | F70: =IFERROR(F69/F68,0) -> 0 | G70: =IFERROR(G69/G68,0) -> 0 | H70: =H69/H68 -> 1.375 | I70: =I69/I68 -> 0.425 | J70: =J69/J68 -> 1.375 | K70: =K69/K68 -> 0.425 | L70: =L69/L68 -> 1.375 | M70: =M69/M68 -> 0.425 | N70: =N69/N68 -> 1.375 | O70: =O69/O68 -> 0.425 | ... AA70: =AA69/AA68 -> 0.425
E71: Average Check | F71: 0 | G71: 0 | H71: 6 | I71: 17 | J71: =H71*(1+$B$2) -> 6.1270909 | K71: =I71*(1+$B$2) -> 17.360091 | L71: =J71*(1+$B$2) -> 6.2568738 | M71: =K71*(1+$B$2) -> 17.727809 | N71: =L71*(1+$B$2) -> 6.3894058 | O71: =M71*(1+$B$2) -> 18.103316 | P71: =N71*(1+$B$2) -> 6.524745 | Q71: =O71*(1+$B$2) -> 18.486778 | ... AA71: =Y71*(1+$B$2) -> 20.529416
C72: Total Outlet Revenue | F72: =F71*F69*F66 -> 0 | G72: =G71*G69*G66 -> 0 | H72: =H71*H69*H66*(1-VAT) -> 69498 | I72: =I71*I69*I66*(1-VAT) -> 30431.7 | J72: =J71*J69*J66*(1-VAT) -> 70970.094 | K72: =K71*K69*K66*(1-VAT) -> 31076.299 | L72: =L71*L69*L66*(1-VAT) -> 72473.37 | M72: =M71*M69*M66*(1-VAT) -> 31734.551 | N72: =N71*N69*N66*(1-VAT) -> 74008.487 | O72: =O71*O69*O66*(1-VAT) -> 32406.747 | ... AA72: =AA71*AA69*AA66*(1-VAT) -> 36749.707
C73: Cost of sales | D73: Adjusted cost rate | E73: =$B$3-20% -> 0.618 | F73: =F72*$E$73 -> 0 | G73: =G72*$E$73 -> 0 | H73: =H72*$E$73 -> 42949.764 | I73: =I72*$E$73 -> 18806.791 | J73: =J72*$E$73 -> 43859.518 | K73: =K72*$E$73 -> 19205.153 | L73: =L72*$E$73 -> 44788.542 | M73: =M72*$E$73 -> 19611.953 | ... AA73: =AA72*$E$73 -> 22711.319
C74: Total Profit | F74: =F72-F73 -> 0 | G74: =G72-G73 -> 0 | H74: =H72-H73 -> 26548.236 | I74: =I72-I73 -> 11624.909 | J74: =J72-J73 -> 27110.576 | K74: =K72-K73 -> 11871.146 | L74: =L72-L73 -> 27684.827 | M74: =M72-M73 -> 12122.599 | ... AA74: =AA72-AA73 -> 14038.388
A78: ROOM SERVICE
A79: Available daily | E79: #days open per week | F79: 7 | H79: 7 | J79: 7 | L79: 7 | N79: 7 | P79: 7 | R79: 7 | T79: 7 | V79: 7 | X79: 7 | Z79: 7
A80: Food from Le Capricone when open. | E80: Number of days open | F80: =F79*52 -> 364 | H80: =H79*52 -> 364 | J80: =J79*52 -> 364 | L80: =L79*52 -> 364 | N80: =N79*52 -> 364 | P80: =P79*52 -> 364 | R80: =R79*52 -> 364 | T80: =T79*52 -> 364 | V80: =V79*52 -> 364 | X80: =X79*52 -> 364 | Z80: =Z79*52 -> 364
A81: Food menu from Eck bar when Capricorne closed.
A82: We estimated 1 main + 1 drink | E82: Number of seats | F82: =15+(142-15)*2 -> 269 | H82: =15+(142-15)*2 -> 269 | J82: =15+(142-15)*2 -> 269 | L82: =15+(142-15)*2 -> 269 | N82: =15+(142-15)*2 -> 269 | P82: =15+(142-15)*2 -> 269 | R82: =15+(142-15)*2 -> 269 | T82: =15+(142-15)*2 -> 269 | V82: =15+(142-15)*2 -> 269 | X82: =15+(142-15)*2 -> 269 | Z82: =15+(142-15)*2 -> 269
A83: Increasing price +20% for the service | E83: Average Covers per day | F83: 17 | H83: 17 | J83: 17 | L83: 17 | N83: 17 | P83: 17 | R83: 17 | T83: 17 | V83: 17 | X83: 17 | Z83: 17
A84: Cost of sales increase due to : | E84: Occupancy | F84: =F83/F82 -> 0.063197026 | H84: =H83/H82 -> 0.063197026 | J84: =J83/J82 -> 0.063197026 | L84: =L83/L82 -> 0.063197026 | N84: =N83/N82 -> 0.063197026 | P84: =P83/P82 -> 0.063197026 | R84: =R83/R82 -> 0.063197026 | T84: =T83/T82 -> 0.063197026 | V84: =V83/V82 -> 0.063197026 | X84: =X83/X82 -> 0.063197026 | Z84: =Z83/Z82 -> 0.063197026
A85: Less efficency & low volume | E85: Average Check | F85: =(AF38+AF35)*1.2 -> 43.865143 | H85: =F85*(1+$B$2) -> 44.794286 | J85: =H85*(1+$B$2) -> 45.743111 | L85: =J85*(1+$B$2) -> 46.712033 | N85: =L85*(1+$B$2) -> 47.701479 | P85: =N85*(1+$B$2) -> 48.711883 | R85: =P85*(1+$B$2) -> 49.743689 | T85: =R85*(1+$B$2) -> 50.797351 | V85: =T85*(1+$B$2) -> 51.873331 | X85: =V85*(1+$B$2) -> 52.972103 | Z85: =X85*(1+$B$2) -> 54.094148
C86: Total Outlet Revenue | F86: =F85*F83*F80*(1-VAT) -> 219864.38 | H86: =H85*H83*H80*(1-VAT) -> 224521.51 | J86: =J85*J83*J80*(1-VAT) -> 229277.28 | L86: =L85*L83*L80*(1-VAT) -> 234133.79 | N86: =N85*N83*N80*(1-VAT) -> 239093.17 | P86: =P85*P83*P80*(1-VAT) -> 244157.6 | R86: =R85*R83*R80*(1-VAT) -> 249329.3 | T86: =T85*T83*T80*(1-VAT) -> 254610.55 | V86: =V85*V83*V80*(1-VAT) -> 260003.66 | X86: =X85*X83*X80*(1-VAT) -> 265511.01 | Z86: =Z85*Z83*Z80*(1-VAT) -> 271135.02
C87: Cost of sales | D87: Adjusted cost rate | E87: =$B$3+10% -> 0.918 | F87: =F86*$E$87 -> 201835.5 | H87: =H86*$E$87 -> 206110.74 | J87: =J86*$E$87 -> 210476.54 | L87: =L86*$E$87 -> 214934.82 | N87: =N86*$E$87 -> 219487.53 | P87: =P86*$E$87 -> 224136.67 | R87: =R86*$E$87 -> 228884.3 | T87: =T86*$E$87 -> 233732.48 | V87: =V86*$E$87 -> 238683.36 | X87: =X86*$E$87 -> 243739.11 | Z87: =Z86*$E$87 -> 248901.95
C88: Total Profit | F88: =F86-F87 -> 18028.879 | H88: =H86-H87 -> 18410.763 | J88: =J86-J87 -> 18800.737 | L88: =L86-L87 -> 19198.971 | N88: =N86-N87 -> 19605.64 | P88: =P86-P87 -> 20020.923 | R88: =R86-R87 -> 20445.002 | T88: =T86-T87 -> 20878.065 | V88: =V86-V87 -> 21320.3 | X88: =X86-X87 -> 21771.903 | Z88: =Z86-Z87 -> 22233.071
A89: https://www.independent.co.uk/travel/hotels/room-service-the-final-call-on-a-luxury-that-is-just-not-profitable-8644598.html
A92: TOTAL F&B OUTLETS | F92: 2026 | H92: 2027 | J92: 2028 | L92: 2029 | N92: 2030 | P92: 2031 | R92: 2032 | T92: 2033 | V92: 2034 | X92: 2035 | Z92: 2036
C93: Total F&B Revenue | F93: =SUM(F15:G15,F30:G30,F44:G44,F58:G58,F72:G72,F86:G86) -> 2161878.7 | H93: =SUM(H15:I15,H30:I30,H44:I44,H58:I58,H72:I72,H86:I86) -> 2187636.8 | J93: =SUM(J15:K15,J30:K30,J44:K44,J58:K58,J72:K72,J86:K86) -> 2529748.8 | L93: =SUM(L15:M15,L30:M30,L44:M44,L58:M58,L72:M72,L86:M86) -> 2640965.3 | N93: =SUM(N15:O15,N30:O30,N44:O44,N58:O58,N72:O72,N86:O86) -> 2722401.9 | P93: =SUM(P15:Q15,P30:Q30,P44:Q44,P58:Q58,P72:Q72,P86:Q86) -> 2781272.1 | R93: =SUM(R15:S15,R30:S30,R44:S44,R58:S58,R72:S72,R86:S86) -> 2842006 | T93: =SUM(T15:U15,T30:U30,T44:U44,T58:U58,T72:U72,T86:U86) -> 2900344.8 | V93: =SUM(V15:W15,V30:W30,V44:W44,V58:W58,V72:W72,V86:W86) -> 2961779.4 | X93: =SUM(X15:Y15,X30:Y30,X44:Y44,X58:Y58,X72:Y72,X86:Y86) -> 3024515.3 | Z93: =SUM(Z15:AA15,Z30:AA30,Z44:AA44,Z58:AA58,Z72:AA72,Z86:AA86) -> 3090560.8
C94: Total F&B Cost of sales | F94: =SUM(F16:G16,F31:G31,F45:G45,F59:G59,F73:G73,F87:G87) -> 1648299.2 | G94: =F94/F93 -> 0.76243834 | H94: =SUM(H16:I16,H31:I31,H45:I45,H59:I59,H73:I73,H87:I87) -> 1663830.7 | I94: =H94/H93 -> 0.76056075 | J94: =SUM(J16:K16,J31:K31,J45:K45,J59:K59,J73:K73,J87:K87) -> 1917987.5 | K94: =J94/J93 -> 0.75817313 | L94: =SUM(L16:M16,L31:M31,L45:M45,L59:M59,L73:M73,L87:M87) -> 1997112.1 | M94: =L94/L93 -> 0.75620535 | N94: =SUM(N16:O16,N31:O31,N45:O45,N59:O59,N73:O73,N87:O87) -> 2056446 | O94: =N94/N93 -> 0.75537928 | P94: =SUM(P16:Q16,P31:Q31,P45:Q45,P59:Q59,P73:Q73,P87:Q87) -> 2100810.1 | Q94: =P94/P93 -> 0.75534143 | R94: =SUM(R16:S16,R31:S31,R45:S45,R59:S59,R73:S73,R87:S87) -> 2146525.8 | S94: =R94/R93 -> 0.75528545 | T94: =SUM(T16:U16,T31:U31,T45:U45,T59:U59,T73:U73,T87:U87) -> 2190750.6 | U94: =T94/T93 -> 0.75534143 | V94: =SUM(V16:W16,V31:W31,V45:W45,V59:W59,V73:W73,V87:W87) -> 2237154.7 | W94: =V94/V93 -> 0.75534143 | X94: =SUM(X16:Y16,X31:Y31,X45:Y45,X59:Y59,X73:Y73,X87:Y87) -> 2284541.7 | Y94: =X94/X93 -> 0.75534143 | Z94: =SUM(Z16:AA16,Z31:AA31,Z45:AA45,Z59:AA59,Z73:AA73,Z87:AA87) -> 2334255.6 | AA94: =Z94/Z93 -> 0.75528545
C95: Total F&B Profit | F95: =SUM(F17:G17,F32:G32,F46:G46,F60:G60,F74:G74,F88:G88) -> 513579.48 | H95: =SUM(H17:I17,H32:I32,H46:I46,H60:I60,H74:I74,H88:I88) -> 523806.1 | J95: =SUM(J17:K17,J32:K32,J46:K46,J60:K60,J74:K74,J88:K88) -> 611761.21 | L95: =SUM(L17:M17,L32:M32,L46:M46,L60:M60,L74:M74,L88:M88) -> 643853.21 | N95: =SUM(N17:O17,N32:O32,N46:O46,N60:O60,N74:O74,N88:O88) -> 665955.92 | P95: =SUM(P17:Q17,P32:Q32,P46:Q46,P60:Q60,P74:Q74,P88:Q88) -> 680462.07 | R95: =SUM(R17:S17,R32:S32,R46:S46,R60:S60,R74:S74,R88:S88) -> 695480.23 | T95: =SUM(T17:U17,T32:U32,T46:U46,T60:U60,T74:U74,T88:U88) -> 709594.22 | V95: =SUM(V17:W17,V32:W32,V46:W46,V60:W60,V74:W74,V88:W88) -> 724624.71 | X95: =SUM(X17:Y17,X32:Y32,X46:Y46,X60:Y60,X74:Y74,X88:Y88) -> 739973.58 | Z95: =SUM(Z17:AA17,Z32:AA32,Z46:AA46,Z60:AA60,Z74:AA74,Z88:AA88) -> 756305.2

Sheet 1-CAPEX
A1: 1 - CAPEX
S6: Number of room per cluster | X6: Slpit rénovation per sqm
B7: TYPE OF RENOVATION | C7: FF&E | D7: SOFT GOOD | E7: CONSTRUCTION | F7: TOTAL N/A ADJUSTED CAPEX | G7: Architect fee 10% | H7: FF&E ajustment 15% | I7: Contractor Markup 15% | J7: Labor 17% | K7: Capex Reserves Check 6% | L7: Contingency 10% | M7: TOTAL ADJUSTED CAPEX | O7: TYPE OF ROOMS | P7: #ROOMS | Q7: SIZE (sqm) | R7: TOTAL (sqm) | S7: CLUSTER 1 | T7: CLUSTER 2 | U7: CLUSTER 3 | V7: CLUSTER 4 | W7: CLUSTER 5 | X7: CLUSTER 1 | Y7: CLUSTER 2 | Z7: CLUSTER 3 | AA7: CLUSTER 4 | AB7: CLUSTER 5
B8: Individual room | C8: =E84+R8*30 -> 37264.32 | D8: =F84 -> 11982.95 | E8: =G84 -> 18596.334 | F8: =SUM(C8:E8) -> 67843.604 | G8: =F8*10% -> 6784.3604 | H8: =C8*15% -> 5589.648 | I8: =E8*15% -> 2789.4501 | J8: =F8*16.8797% -> 11451.797 | K8: =F8*6% -> 4070.6162 | L8: =F8*10% -> 6784.3604 | M8: =SUM(F8:L8) -> 105313.84 | O8: Individual room | P8: 15 | Q8: 18 | R8: =P8*Q8 -> 270 | S8: 0 | T8: 4 | U8: 4 | V8: 4 | W8: 3 | X8: =$Q8*S8 -> 0 | Y8: =$Q8*T8 -> 72 | Z8: =$Q8*U8 -> 72 | AA8: =$Q8*V8 -> 72 | AB8: =$Q8*W8 -> 54
B9: Standard Room | C9: =E111+R9*30 -> 139120.13 | D9: =F111 -> 44736.346 | E9: =G111 -> 69426.314 | F9: =SUM(C9:E9) -> 253282.79 | G9: =F9*10% -> 25328.279 | H9: =C9*15% -> 20868.019 | I9: =E9*15% -> 10413.947 | J9: =F9*16.8797% -> 42753.375 | K9: =F9*6% -> 15196.967 | L9: =F9*10% -> 25328.279 | M9: =SUM(F9:L9) -> 393171.65 | O9: Standard Room | P9: 42 | Q9: 24 | R9: =P9*Q9 -> 1008 | S9: 8 | T9: 8 | U9: 9 | V9: 9 | W9: 8 | X9: =$Q9*S9 -> 192 | Y9: =$Q9*T9 -> 192 | Z9: =$Q9*U9 -> 216 | AA9: =$Q9*V9 -> 216 | AB9: =$Q9*W9 -> 192
B10: Superior Room | C10: =E138+R10*30 -> 223585.92 | D10: =F138 -> 71897.698 | E10: =G138 -> 111578 | F10: =SUM(C10:E10) -> 407061.62 | G10: =F10*10% -> 40706.162 | H10: =C10*15% -> 33537.888 | I10: =E10*15% -> 16736.701 | J10: =F10*16.8797% -> 68710.781 | K10: =F10*6% -> 24423.697 | L10: =F10*10% -> 40706.162 | M10: =SUM(F10:L10) -> 631883.01 | O10: Superior Room | P10: 54 | Q10: 30 | R10: =P10*Q10 -> 1620 | S10: 0 | T10: 14 | U10: 13 | V10: 13 | W10: 14 | X10: =$Q10*S10 -> 0 | Y10: =$Q10*T10 -> 420 | Z10: =$Q10*U10 -> 390 | AA10: =$Q10*V10 -> 390 | AB10: =$Q10*W10 -> 420
B11: Premium Room | C11: =E165+R11*30 -> 96546.903 | D11: =F165 -> 31237.709 | E11: =G165 -> 48477.787 | F11: =SUM(C11:E11) -> 176262.4 | G11: =F11*10% -> 17626.24 | H11: =C11*15% -> 14482.035 | I11: =E11*15% -> 7271.668 | J11: =F11*16.8797% -> 29752.564 | K11: =F11*6% -> 10575.744 | L11: =F11*10% -> 17626.24 | M11: =SUM(F11:L11) -> 273596.89 | O11: Premum Romm | P11: 19 | Q11: 36 | R11: =P11*Q11 -> 684 | S11: 0 | T11: 5 | U11: 5 | V11: 4 | W11: 5 | X11: =$Q11*S11 -> 0 | Y11: =$Q11*T11 -> 180 | Z11: =$Q11*U11 -> 180 | AA11: =$Q11*V11 -> 144 | AB11: =$Q11*W11 -> 180
B12: Junior suite | C12: =E192+R12*30 -> 59622.912 | D12: =F192 -> 19172.72 | E12: =G192 -> 29754.134 | F12: =SUM(C12:E12) -> 108549.77 | G12: =F12*10% -> 10854.977 | H12: =C12*15% -> 8943.4368 | I12: =E12*15% -> 4463.1202 | J12: =F12*16.8797% -> 18322.875 | K12: =F12*6% -> 6512.986 | L12: =F12*10% -> 10854.977 | M12: =SUM(F12:L12) -> 168502.14 | O12: Junior suite | P12: 9 | Q12: 48 | R12: =P12*Q12 -> 432 | S12: 9 | T12: 0 | U12: 0 | V12: 0 | W12: 0 | X12: =$Q12*S12 -> 432 | Y12: =$Q12*T12 -> 0 | Z12: =$Q12*U12 -> 0 | AA12: =$Q12*V12 -> 0 | AB12: =$Q12*W12 -> 0
B13: One bedroom suite | C13: =E219+R13*30 -> 18770.176 | D13: =F219 -> 6035.8562 | E13: =G219 -> 9367.0423 | F13: =SUM(C13:E13) -> 34173.074 | G13: =F13*10% -> 3417.3074 | H13: =C13*15% -> 2815.5264 | I13: =E13*15% -> 1405.0564 | J13: =F13*16.8797% -> 5768.3125 | K13: =F13*6% -> 2050.3845 | L13: =F13*10% -> 3417.3074 | M13: =SUM(F13:L13) -> 53046.969 | O13: one bedroom suite | P13: 2 | Q13: 68 | R13: =P13*Q13 -> 136 | S13: 2 | T13: 0 | U13: 0 | V13: 0 | W13: 0 | X13: =$Q13*S13 -> 136 | Y13: =$Q13*T13 -> 0 | Z13: =$Q13*U13 -> 0 | AA13: =$Q13*V13 -> 0 | AB13: =$Q13*W13 -> 0
B14: Family room | C14: =E263+R14*30 -> 23765.721 | D14: =F263 -> 1452.1017 | E14: =G263 -> 9315.3239 | F14: =SUM(C14:E14) -> 34533.146 | G14: =F14*10% -> 3453.3146 | H14: =C14*15% -> 3564.8581 | I14: =E14*15% -> 1397.2986 | J14: =F14*16.8797% -> 5829.0915 | K14: =F14*6% -> 2071.9888 | L14: =F14*10% -> 3453.3146 | M14: =SUM(F14:L14) -> 54303.012 | O14: Family room | P14: 1 | Q14: 90 | R14: =P14*Q14 -> 90 | S14: 1 | T14: 0 | U14: 0 | V14: 0 | W14: 0 | X14: =$Q14*S14 -> 90 | Y14: =$Q14*T14 -> 0 | Z14: =$Q14*U14 -> 0 | AA14: =$Q14*V14 -> 0 | AB14: =$Q14*W14 -> 0
B15: Individual Bathroom | C15: =N74 -> 7777.8263 | D15: =O74 -> 1451.2897 | E15: =P74 -> 4315.3192 | F15: =SUM(C15:E15) -> 13544.435 | G15: =F15*10% -> 1354.4435 | H15: =C15*15% -> 1166.6739 | I15: =E15*15% -> 647.29788 | J15: =F15*16.8797% -> 2286.26 | K15: =F15*6% -> 812.66611 | L15: =F15*10% -> 1354.4435 | M15: =SUM(F15:L15) -> 21166.22 | O15: TOTAL | P15: =SUM(P8:P14) -> 142 | Q15: =SUM(Q8:Q14) -> 314 | R15: =SUM(R8:R14) -> 4240 | S15: =SUM(S8:S14) -> 20 | T15: =SUM(T8:T14) -> 31 | U15: =SUM(U8:U14) -> 31 | V15: =SUM(V8:V14) -> 30 | W15: =SUM(W8:W14) -> 30 | ... AB15: =SUM(AB8:AB14) -> 846
B16: Standard Bathroom | C16: =N101 -> 29037.218 | D16: =O101 -> 5418.1483 | E16: =P101 -> 16110.525 | F16: =SUM(C16:E16) -> 50565.891 | G16: =F16*10% -> 5056.5891 | H16: =C16*15% -> 4355.5827 | I16: =E16*15% -> 2416.5787 | J16: =F16*16.8797% -> 8535.3708 | K16: =F16*6% -> 3033.9535 | L16: =F16*10% -> 5056.5891 | M16: =SUM(F16:L16) -> 79020.555
B17: Superior Bathroom | C17: =N128 -> 46666.958 | D17: =O128 -> 8707.7383 | E17: =P128 -> 25891.915 | F17: =SUM(C17:E17) -> 81266.611 | G17: =F17*10% -> 8126.6611 | H17: =C17*15% -> 7000.0436 | I17: =E17*15% -> 3883.7873 | J17: =F17*16.8797% -> 13717.56 | K17: =F17*6% -> 4875.9967 | L17: =F17*10% -> 8126.6611 | M17: =SUM(F17:L17) -> 126997.32
B18: Premium Bathroom | C18: =N155 -> 19703.827 | D18: =O155 -> 3676.6006 | E18: =P155 -> 10932.142 | F18: =SUM(C18:E18) -> 34312.569 | G18: =F18*10% -> 3431.2569 | H18: =C18*15% -> 2955.574 | I18: =E18*15% -> 1639.8213 | J18: =F18*16.8797% -> 5791.8587 | K18: =F18*6% -> 2058.7541 | L18: =F18*10% -> 3431.2569 | M18: =SUM(F18:L18) -> 53621.091
B19: Junior suite Bathroom | C19: =N182 -> 12444.522 | D19: =O182 -> 2322.0635 | E19: =P182 -> 6904.5107 | F19: =SUM(C19:E19) -> 21671.096 | G19: =F19*10% -> 2167.1096 | H19: =C19*15% -> 1866.6783 | I19: =E19*15% -> 1035.6766 | J19: =F19*16.8797% -> 3658.016 | K19: =F19*6% -> 1300.2658 | L19: =F19*10% -> 2167.1096 | M19: =SUM(F19:L19) -> 33865.952
B20: One bedroom suite Bathroom | C20: =N209 -> 3917.7199 | D20: =O209 -> 731.02 | E20: =P209 -> 2173.6423 | F20: =SUM(C20:E20) -> 6822.3822 | G20: =F20*10% -> 682.23822 | H20: =C20*15% -> 587.65798 | I20: =E20*15% -> 326.04634 | J20: =F20*16.8797% -> 1151.5976 | K20: =F20*6% -> 409.34293 | L20: =F20*10% -> 682.23822 | M20: =SUM(F20:L20) -> 10661.503
B21: Family Bathroom | C21: =N250 -> 10304.155 | D21: =O250 -> 483.76324 | E21: =P250 -> 19360.167 | F21: =SUM(C21:E21) -> 30148.085 | G21: =F21*10% -> 3014.8085 | H21: =C21*15% -> 1545.6233 | I21: =E21*15% -> 2904.0251 | J21: =F21*16.8797% -> 5088.9064 | K21: =F21*6% -> 1808.8851 | L21: =F21*10% -> 3014.8085 | M21: =SUM(F21:L21) -> 47525.142
B22: Eck Bar | C22: =W95+AA62*30 -> 175336.77 | D22: =X95 -> 20534.789 | E22: =Y95 -> 76591.021 | F22: =SUM(C22:E22) -> 272462.58 | G22: =F22*10% -> 27246.258 | H22: =C22*15% -> 26300.516 | I22: =E22*15% -> 11488.653 | J22: =F22*16.8797% -> 45990.866 | K22: =F22*6% -> 16347.755 | L22: =F22*10% -> 27246.258 | M22: =SUM(F22:L22) -> 427082.89 | O22: TYPE OF RENOVATION | P22: FF&E | Q22: SOFT GOOD | R22: CONSTRUCTION | S22: TOTAL N/A ADJUSTED CAPEX | T22: Architect fee 10% | U22: FF&E ajustement 15% | V22: Contractor Markup 15% | W22: Labor 17% | X22: Capex Reserves Check 6% | Y22: Contingency 10% | Z22: TOTAL ADJUSTED CAPEX
B23: Ingelheimer Room | C23: =W133+AA100*30 -> 152793.47 | D23: =X133 -> 17894.602 | E23: =Y133 -> 66743.604 | F23: =SUM(C23:E23) -> 237431.68 | G23: =F23*10% -> 23743.168 | H23: =C23*15% -> 22919.021 | I23: =E23*15% -> 10011.541 | J23: =F23*16.8797% -> 40077.755 | K23: =F23*6% -> 14245.901 | L23: =F23*10% -> 23743.168 | M23: =SUM(F23:L23) -> 372172.23 | O23: Cluster 1 | P23: =E110*8+E191*9+E218*2+E262+N100*8+N181*9+N208*2+N249+X15*BJ63 -> 160855.18 | Q23: =F110*8+F191*9+F218*2+F262+O100*8+O181*9+O208*2+O249 -> 39750.761 | R23: =G110*8+G191*9+G218*2+G262+P100*8+P181*9+P208*2+P249 -> 93167.552 | S23: =SUM(P23:R23) -> 293773.49 | T23: =S23*10% -> 29377.349 | U23: =P23*15% -> 24128.276 | V23: =R23*15% -> 13975.133 | W23: =S23*16.8797% -> 49588.084 | X23: =S23*6% -> 17626.409 | Y23: =S23*10% -> 29377.349 | Z23: =SUM(S23:Y23) -> 457846.09
B24: Meetings Rooms | C24: =AF72+AJ63*30 -> 24377.111 | D24: =AG72 -> 126278.19 | E24: =AH72 -> 34947.343 | F24: =SUM(C24:E24) -> 185602.64 | G24: =F24*10% -> 18560.264 | H24: =C24*15% -> 3656.5667 | I24: =E24*15% -> 5242.1015 | J24: =F24*16.8797% -> 31329.17 | K24: =F24*6% -> 11136.159 | L24: =F24*10% -> 18560.264 | M24: =SUM(F24:L24) -> 274087.17 | O24: Cluster 2 | P24: =E83*4+E110*8+E137*14+E164*5+N73*4+N100*8+N127*14+N154*5+Y15*BJ63 -> 144699.07 | Q24: =F83*4+F110*8+F137*14+F164*5+O73*4+O100*8+O127*14+O154*5 -> 43221.383 | R24: =G83*4+G110*8+G137*14+G164*5+P73*4+P100*8+P127*14+P154*5 -> 73677.047 | S24: =SUM(P24:R24) -> 261597.5 | T24: =S24*10% -> 26159.75 | U24: =P24*15% -> 21704.86 | V24: =R24*15% -> 11051.557 | W24: =S24*16.8797% -> 44156.873 | X24: =S24*6% -> 15695.85 | Y24: =S24*10% -> 26159.75 | Z24: =SUM(S24:Y24) -> 406526.14
B25: Lobby | C25: =AO90+AS63*30 -> 61528.58 | D25: =AP90 -> 4312.391 | E25: =AQ90 -> 109670.57 | F25: =SUM(C25:E25) -> 175511.54 | G25: =F25*10% -> 17551.154 | H25: =C25*15% -> 9229.287 | I25: =E25*15% -> 16450.585 | J25: =F25*16.8797% -> 29625.821 | K25: =F25*6% -> 10530.692 | L25: =F25*10% -> 17551.154 | M25: =SUM(F25:L25) -> 276450.23 | O25: Cluster 3 | P25: =E83*4+E110*9+E137*13+E164*5+N73*4+N100*9+N127*13+N154*5+Z15*BJ63 -> 143698.13 | Q25: =F83*4+F110*9+F137*13+F164*5+O73*4+O100*9+O127*13+O154*5 -> 42922.844 | R25: =G83*4+G110*9+G137*13+G164*5+P73*4+P100*9+P127*13+P154*5 -> 73167.899 | S25: =SUM(P25:R25) -> 259788.87 | T25: =S25*10% -> 25978.887 | U25: =P25*15% -> 21554.72 | V25: =R25*15% -> 10975.185 | W25: =S25*16.8797% -> 43851.583 | X25: =S25*6% -> 15587.332 | Y25: =S25*10% -> 25978.887 | Z25: =SUM(S25:Y25) -> 403715.47
B26: Spa & Wellness | C26: =AX66+BA63*30 -> 162711.49 | D26: =AY66 -> 12912.293 | E26: =AZ66 -> 26174.45 | F26: =SUM(C26:E26) -> 201798.23 | G26: =F26*10% -> 20179.823 | H26: =C26*15% -> 24406.723 | I26: =E26*15% -> 3926.1676 | J26: =F26*16.8797% -> 34062.936 | K26: =F26*6% -> 12107.894 | L26: =F26*10% -> 20179.823 | M26: =SUM(F26:L26) -> 316661.6 | O26: Cluster 4 | P26: =E83*4+E110*9+E137*13+E164*4+N73*4+N100*9+N127*13+N154*4+AA15*BJ63 -> 137579.67 | Q26: =F83*4+F110*9+F137*13+F164*4+O73*4+O100*9+O127*13+O154*4 -> 41085.249 | R26: =G83*4+G110*9+G137*13+G164*4+P73*4+P100*9+P127*13+P154*4 -> 70041.06 | S26: =SUM(P26:R26) -> 248705.98 | T26: =S26*10% -> 24870.598 | U26: =P26*15% -> 20636.951 | V26: =R26*15% -> 10506.159 | W26: =S26*16.8797% -> 41980.823 | X26: =S26*6% -> 14922.359 | Y26: =S26*10% -> 24870.598 | Z26: =SUM(S26:Y26) -> 386493.47
B27: Energy Other (ESG) | C27: =BG68*BJ68+240*30 -> 9900 | F27: =SUM(C27:E27) -> 9900 | G27: =F27*10% -> 990 | H27: =C27*15% -> 1485 | I27: =E27*15% -> 0 | J27: =F27*16.8797% -> 1671.0903 | K27: =F27*6% -> 594 | L27: =F27*10% -> 990 | M27: =SUM(F27:L27) -> 15630.09 | O27: Cluster 5 | P27: =E83*3+E110*8+E137*14+E164*5+N73*3+N100*8+N127*14+N154*5+AB15*BJ63 -> 141696.26 | Q27: =F83*3+F110*8+F137*14+F164*5+O73*3+O100*8+O127*14+O154*5 -> 42325.767 | R27: =G83*3+G110*8+G137*14+G164*5+P73*3+P100*8+P127*14+P154*5 -> 72149.603 | S27: =SUM(P27:R27) -> 256171.63 | T27: =S27*10% -> 25617.163 | U27: =P27*15% -> 21254.439 | V27: =R27*15% -> 10822.44 | W27: =S27*16.8797% -> 43241.002 | X27: =S27*6% -> 15370.298 | Y27: =S27*10% -> 25617.163 | Z27: =SUM(S27:Y27) -> 398094.13
B28: Total | C28: =SUM(C8:C26) -> 1305275.7 | D28: =SUM(D8:D26) -> 391238.27 | E28: =SUM(E8:E26) -> 696330.15 | F28: =SUM(F8:F26) -> 2392844.1 | G28: =SUM(G8:G26) -> 239284.41 | H28: =SUM(H8:H26) -> 195791.36 | I28: =SUM(I8:I26) -> 104449.52 | J28: =SUM(J8:J26) -> 403904.91 | ... L28: =SUM(L8:L26) -> 239284.41 | M28: =SUM(M8:M27) -> 3734759.5 | O28: Eck Bar | P28: =W95+AA62*BJ67 -> 175336.77 | Q28: =X95 -> 20534.789 | R28: =Y95 -> 76591.021 | S28: =SUM(P28:R28) -> 272462.58 | T28: =S28*10% -> 27246.258 | U28: =P28*15% -> 26300.516 | V28: =R28*15% -> 11488.653 | W28: =S28*16.8797% -> 45990.866 | X28: =S28*6% -> 16347.755 | Y28: =S28*10% -> 27246.258 | Z28: =SUM(S28:Y28) -> 427082.89
O29: Ingelheimer Room | P29: =W133+AA100*BJ67 -> 152793.47 | Q29: =X133 -> 17894.602 | R29: =Y133 -> 66743.604 | S29: =SUM(P29:R29) -> 237431.68 | T29: =S29*10% -> 23743.168 | U29: =P29*15% -> 22919.021 | V29: =R29*15% -> 10011.541 | W29: =S29*16.8797% -> 40077.755 | X29: =S29*6% -> 14245.901 | Y29: =S29*10% -> 23743.168 | Z29: =SUM(S29:Y29) -> 372172.23
B30: TOTAL ADJUSGTED CAPEX | O30: Meetings Rooms | P30: =AF72+AJ63*BJ66 -> 24377.111 | Q30: =AG72 -> 126278.19 | R30: =AH72 -> 34947.343 | S30: =SUM(P30:R30) -> 185602.64 | T30: =S30*10% -> 18560.264 | U30: =P30*15% -> 3656.5667 | V30: =R30*15% -> 5242.1015 | W30: =S30*16.8797% -> 31329.17 | X30: =S30*6% -> 11136.159 | Y30: =S30*10% -> 18560.264 | Z30: =SUM(S30:Y30) -> 274087.17
B31: ROOMS | D31: =SUM(C32:C35) -> 2052675.3 | O31: Lobby | P31: =AO90+AS63*BJ64 -> 61528.58 | Q31: =AP90 -> 4312.391 | R31: =AQ90 -> 109670.57 | S31: =SUM(P31:R31) -> 175511.54 | T31: =S31*10% -> 17551.154 | U31: =P31*15% -> 9229.287 | V31: =R31*15% -> 16450.585 | W31: =S31*16.8797% -> 29625.821 | X31: =S31*6% -> 10530.692 | Y31: =S31*10% -> 17551.154 | Z31: =SUM(S31:Y31) -> 276450.23
B32: 141 rooms | C32: =SUM(M8:M13) -> 1625514.5 | O32: Spa & Wellness | P32: =AX66+BA63*BJ65 -> 162711.49 | Q32: =AY66 -> 12912.293 | R32: =AZ66 -> 26174.45 | S32: =SUM(P32:R32) -> 201798.23 | T32: =S32*10% -> 20179.823 | U32: =P32*15% -> 24406.723 | V32: =R32*15% -> 3926.1676 | W32: =S32*16.8797% -> 34062.936 | X32: =S32*6% -> 12107.894 | Y32: =S32*10% -> 20179.823 | Z32: =SUM(S32:Y32) -> 316661.6
B33: Family room | C33: =M14 -> 54303.012 | O33: Energy Other (ESG) | P33: =BG68*BJ68+240*30 -> 9900 | S33: =SUM(P33:R33) -> 9900 | T33: =S33*10% -> 990 | U33: =P33*15% -> 1485 | V33: =R33*15% -> 0 | W33: =S33*16.8797% -> 1671.0903 | X33: =S33*6% -> 594 | Y33: =S33*10% -> 990 | Z33: =SUM(S33:Y33) -> 15630.09
B34: 141 bathrooms | C34: =SUM(M15:M20) -> 325332.64 | O34: TOTAL | P34: =SUM(P23:P33) -> 1315175.7 | Q34: =SUM(Q23:Q33) -> 391238.27 | R34: =SUM(R23:R33) -> 696330.15 | S34: =SUM(S23:S33) -> 2402744.1 | T34: =SUM(T23:T33) -> 240274.41 | U34: =SUM(U23:U33) -> 197276.36 | V34: =SUM(V23:V33) -> 104449.52 | W34: =SUM(W23:W33) -> 405576 | ... Z34: =SUM(Z23:Z33) -> 3734759.5
B35: 1 bathroom family | C35: =M21 -> 47525.142
B36: F&B | D36: =SUM(C37:C38) -> 799255.12 | O36: ROOMS | P36: =D31 -> 2052675.3
B37: Eck bar | C37: =M22 -> 427082.89 | O37: F&B | P37: =D36 -> 799255.12
B38: Ingelheimer room | C38: =M23 -> 372172.23 | O38: MEETING ROOMS | P38: =D39 -> 274087.17
B39: MEETING ROOMS | D39: =M24 -> 274087.17 | O39: LOBBY | P39: =D40 -> 276450.23
B40: LOBBY | D40: =M25 -> 276450.23 | O40: SPA | P40: =Z32 -> 316661.6
B41: SPA &WELLNES | D41: =Z32 -> 316661.6 | O41: Energy Other (ESG) | P41: =D42 -> 15630.09
B42: ENERGY OTHER (ESG) | D42: =M27 -> 15630.09 | O42: TOTAL | P42: =SUM(P36:P41) -> 3734759.5
B43: TOTAL | D43: =SUM(D31:D42) -> 3734759.5
B46: BEDROOMS RENOVATION | K46: BATHROOMS RENOVATION | T46: F&B ( restaurants+bar) | AC46: MEETING ROOMS | AL46: LOBBY | AU46: SPA & WELLNESS | BE46: ENERGY (ESG)
B48: TYPE OF ROOMS | C48: #ROOMS | D48: SSIZE (sqm) | F48: TOTAL SOFT RENOVATION (sqm) | G48: =SUMPRODUCT(C49:C54,D49:D54) -> 4150 | K48: TYPE OF ROOM | L48: #ROOMS | M48: SIZE (sqm) | T48: TYPE OF F&B | U48: SIZE (sqm) | AC48: TYPE OF MEETING ROOMS | AD48: SIZE (sqm)
B49: Individual room | C49: 15 | D49: 18 | F49: TOTAL HARD RENOVATION (sqm) | G49: =D55 -> 90 | K49: Individual room | L49: 15 | M49: 18 | T49: Le Capricorne | U49: 120 | AC49: Ballroom | AD49: 114
B50: Standard Room | C50: 42 | D50: 24 | K50: Standard Room | L50: 42 | M50: 24 | T50: Terrace (Hofgarten) | U50: 120 | AC50: Ingelheimer Room | AD50: 61
B51: Superior Room | C51: 54 | D51: 30 | K51: Superior Room | L51: 54 | M51: 30 | T51: Eck Bar | U51: 70 | AC51: Diana Room | AD51: 140
B52: Premium Room | C52: 19 | D52: 36 | K52: Premium Room | L52: 19 | M52: 36 | T52: Ingelheimer Room | U52: 61 | AC52: Schöne Aussicht | AD52: 67
B53: Junior suite | C53: 9 | D53: 48 | K53: Junior suite | L53: 9 | M53: 48 | T53: TOTAL | U53: =SUM(U49:U52) -> 371 | AC53: Kochbrunnen room | AD53: 80
B54: One bedroom suite | C54: 2 | D54: 68 | K54: One bedroom suite | L54: 2 | M54: 68 | AC54: Drei Lilien Room | AD54: 72
B55: Family room | C55: 1 | D55: 90 | K55: Family room | L55: 1 | M55: 90 | AC55: Noreberg Room | AD55: 56
B56: TOTAL | C56: =SUM(C49:C55) -> 142 | D56: =SUM(D49:D55) -> 314 | K56: TOTAL | L56: =SUM(L49:L55) -> 142 | M56: =SUM(M49:M55) -> 314 | AC56: Mattiaca Room | AD56: 46
AC57: TOTAL | AD57: =SUM(AD49:AD56) -> 636
B58: Last renovation 2014
B59: Guestroom Soft goods Renovation - Individual Room | E59: Cost Allocations | K59: Guest Bathroom Softgoods Renovation - Individual Room | N59: Cost Allocations | T59: Bar / Lounge Hard Renovation - Eck Bar | W59: Cost Allocations | AC59: Last renovation 2017 | AL59: Last Renovation 2010
B60: Category | C60: HVS Cost (USD) | D60: Actual Cost (USD) | E60: FF&E | F60: Soft Good | G60: Construction | K60: Category | L60: HVS Cost (USD) | M60: Actual Cost (USD) | N60: FF&E | O60: Soft Good | P60: Construction | T60: Category | U60: HVS Cost (USD) | V60: Actual Cost (USD) | W60: FF&E | X60: Soft Good | Y60: Construction | AC60: Meeting Rooms SoftGoods Renovation | AF60: Cost Allocations | AL60: Lobby Hard Renovation | AO60: Cost Allocations | AU60: Spa & Wellness | AX60: Cost Allocations | BE60: Energy (ESG) | BI60: Cost Allocations
B61: Demolition | C61: 479.42 | D61: =C61*$I$62/$H$62 -> 196.79726 | G61: =D61 -> 196.79726 | H61: HVS Area m2 | I61: Actual Area m2 | K61: Demolition | L61: 199.44 | M61: =L61*$R$62/$Q$62 -> 81.868187 | P61: =M61 -> 81.868187 | Q61: HVS Area m2 | R61: Actual Area m2 | T61: Demolition | U61: 3207.92 | V61: =U61*$AA$62/$Z$62 -> 2014.2371 | Y61: =V61 -> 2014.2371 | Z61: HVS Area m2 | AA61: Actual Area m2 | AC61: Category | AD61: HVS Cost (USD) | AE61: Actual Cost (USD) | AF61: FF&E | AG61: Soft Good | AH61: Construction | AL61: Category | AM61: HVS Cost (USD) | AN61: Actual Cost (USD) | AO61: FF&E | AP61: Soft Good | AQ61: Construction | AV61: HVS Cost (USD) | AW61: Actual Cost (USD) | AX61: FF&E | AY61: Soft Good | AZ61: Construction | BF61: Department | BG61: Size (sqm) | BH61: Actual Cost (€) | BI61: FF&E | BJ61: €/sqm | BK61: Source
B62: FF&E Installation | C62: 333.84 | D62: =C62*$I$62/$H$62 -> 137.03808 | E62: =D62 -> 137.03808 | H62: 43.85 | I62: =D49 -> 18 | K62: Artwork (Installed) | L62: 207.83 | M62: =L62*$R$62/$Q$62 -> 85.312201 | N62: =M62 -> 85.312201 | Q62: 5.9457946 | R62: =Q62*I62/H62 -> 2.440691 | T62: Artwork, Accessories, and Mirrors (Installed) | U62: 13957.78 | V62: =U62*$AA$62/$Z$62 -> 8764.0209 | W62: =V62 -> 8764.0209 | Z62: 111.4836 | AA62: =U51 -> 70 | AC62: Demolition | AD62: 22455.47 | AE62: =AD62*$AJ$63/$AI$63 -> 18300.929 | AH62: =AE62 -> 18300.929 | AI62: HVS Area m2 | AJ62: Actual Area m2 | AL62: Demolition | AM62: 9790.07 | AN62: =AM62*$AS$63/$AR$63 -> 2195.4275 | AQ62: =AN62 -> 2195.4275 | AR62: HVS Area m2 | AS62: Actual Area m2 | AU62: Indoor Pool | AV62: =AV76 -> 156319.04 | AW62: =AW76 -> 133987.75 | AX62: =AX76 -> 133436.15 | AY62: =AY76 -> 0 | AZ62: =AZ76 -> 551.59714 | BA62: Actual Area m2 | BE62: Updating Light to LED | BK62: https://dominionlighting.com/commercial-lighting-installation/
B63: Artwork, Mirrors, and Accessories (Installed Package) | C63: 903.79 | D63: =C63*$I$62/$H$62 -> 370.99704 | E63: =D63 -> 370.99704 | K63: Lighted Mirror | L63: 752.61 | M63: =L63*$R$62/$Q$62 -> 308.93911 | N63: =M63 -> 308.93911 | T63: Bar / Back Bar (Refinish) | U63: 4156.18 | V63: =U63*$AA$62/$Z$62 -> 2609.6448 | X63: =V63 -> 2609.6448 | AC63: Carpet and Pad | AD63: 53777.77 | AE63: =AD63*$AJ$63/$AI$63 -> 43828.214 | AG63: =AE63 -> 43828.214 | AI63: 780.38 | AJ63: =AD57 -> 636 | AL63: Artwork and Artifacts (installed) | AM63: 17796.67 | AN63: =AM63*$AS$63/$AR$63 -> 3990.9111 | AO63: =AN63 -> 3990.9111 | AR63: 445.93 | AS63: 100 | AU63: Wet Area | AV63: =AV88 -> 41718.63 | AW63: =AW88 -> 56039.951 | AX63: =AX88 -> 37809.269 | AY63: =AY88 -> 10789.079 | AZ63: =AZ88 -> 7441.603 | BA63: 400 | BF63: Rooms | BG63: =SUM(G48:G49) -> 4240 | BH63: =BG63*30 -> 127200 | BI63: =BH63 -> 127200 | BJ63: =BH63/BG63 -> 30
B64: Full-height Framed Dressing Mirror | C64: 291.31 | D64: =C64*$I$62/$H$62 -> 119.57993 | E64: =D64 -> 119.57993 | K64: Makeup Mirror | L64: 277.46 | M64: =L64*$R$62/$Q$62 -> 113.89464 | N64: =M64 -> 113.89464 | T64: Carpet and Pad (55% of Floor Area) | U64: 5195.49 | V64: =U64*$AA$62/$Z$62 -> 3262.2224 | W64: =V64 -> 3262.2224 | AC64: Paint Articulated Drywall Ceiling | AD64: 17942.25 | AE64: =AD64*$AJ$63/$AI$63 -> 14622.711 | AH64: =AE64 -> 14622.711 | AL64: Are Rugs | AM64: 11220.67 | AN64: =AM64*$AS$63/$AR$63 -> 2516.2402 | AP64: =AN64 -> 2516.2402 | AU64: Dry Are | AV64: =AV103 -> 45293.97 | AW64: =AW103 -> 33551.089 | AX64: =AX103 -> 4000.4963 | AY64: =AY103 -> 4225.2148 | AZ64: =AZ103 -> 22442.207 | BF64: Lobby | BG64: =AS63 -> 100 | BH64: =BG64*30 -> 3000 | BI64: =BH64 -> 3000 | BJ64: =BH64/BG64 -> 30
B65: Bed Skirt or Box Spring Cover | C65: 213 | D65: =C65*$I$62/$H$62 -> 87.434436 | F65: =D65 -> 87.434436 | K65: Night Light | L65: 115.5 | M65: =L65*$R$62/$Q$62 -> 47.411631 | N65: =M65 -> 47.411631 | T65: Millwork Running Trim (refinish) | U65: 1000.33 | V65: =U65*$AA$62/$Z$62 -> 628.10225 | Y65: =V65 -> 628.10225 | AC65: Paint Doors and Trim | AD65: 2568.87 | AE65: =AD65*$AJ$63/$AI$63 -> 2093.5971 | AH65: =AE65 -> 2093.5971 | AL65: Millwork (Refinish) | AM65: 3460.69 | AN65: =AM65*$AS$63/$AR$63 -> 776.06127 | AQ65: =AN65 -> 776.06127 | AU65: Total (USD) | AV65: =SUM(AV62:AV64) -> 243331.64 | AW65: =SUM(AW62:AW64) -> 223578.79 | AX65: =SUM(AX62:AX64) -> 175245.92 | AY65: =SUM(AY62:AY64) -> 15014.294 | AZ65: =SUM(AZ62:AZ64) -> 30435.408 | BF65: Spa & Wellnes | BG65: =BA63 -> 400 | BH65: =BG65*30 -> 12000 | BI65: =BH65 -> 12000 | BJ65: =BH65/BG65 -> 30
